Workbook
Name Slicer_Category: #N/A
Name Slicer_Region: #N/A
Name Slicer_Store_name: #N/A

Sheet Customer_Dim
A1: Customer_ID | B1: Name | C1: Age | D1: Gender | E1: City | F1: State | G1: Country | H1: Loyalty_Level
A2: CUST1000 | B2: sheena bonilla | C2: 55 | D2: Male | E2: Donaldton | F2: North Carolina | G2: USA
A3: CUST1001 | B3: Eugene Nelson | C3: 26 | D3: Female | E3: Phillipsmouth | F3: North Dakota | G3: USA | H3: Platinum
A4: CUST1002 | B4: dr. Benjamin Price | C4: 29 | D4: Female | E4: Kylebury | F4: Alabama | G4: USA | H4: Platinum
A5: CUST1003 | B5: jeremy harris | C5: 59 | D5: Female | E5: Thomastown | F5: Ohio | G5: USA | H5: Bronze
A6: CUST1004 | B6: Caroline Collins | C6: 64 | D6: Female | E6: Nicholasshire | F6: California | G6: USA | H6: Silver
A7: CUST1005 | B7: Christine Vaughn | C7: 24 | D7: Male | E7: East Amandamouth | F7: Oregon | G7: USA | H7: Bronze
A8: CUST1006 | B8: Amber Jackson | C8: 29 | D8: Female | E8: Deborahborough | F8: South Dakota | G8: USA | H8: Platinum
A9: CUST1007 | B9: Daniel Boyd | C9: 29 | D9: Female | E9: West Pamelafurt | F9: West Virginia | G9: USA | H9: Bronze
A10: CUST1008 | B10: Melissa Howard | C10: 53 | D10: Female | E10: Maynardton | F10: New Hampshire | G10: USA | H10: Gold
A11: CUST1009 | B11: Ms. Maria Leach | C11: 64 | D11: Male | E11: Melissashire | F11: Pennsylvania | G11: USA | H11: Platinum
A12: CUST1010 | B12: Dominic Page | C12: 53 | D12: Male | E12: Port Michaelburgh | F12: Pennsylvania | G12: USA | H12: Bronze
A13: CUST1011 | B13: Brian Lopez | C13: 28 | D13: Female | E13: East Krista | F13: New York | G13: USA | H13: Gold
A14: CUST1012 | B14: Kenneth Lambert | C14: 55 | D14: Female | E14: North Kathryn | F14: Kansas | G14: USA | H14: Platinum
... A19: CUST1017 | B19: Adam Cruz | C19: 60 | D19: Female | E19: Brandonville | F19: Georgia | G19: USA | H19: Platinum
A20: CUST1018 | B20: Rhonda Moss | C20: 43 | D20: Male | E20: South William | F20: Kansas | G20: USA
A21: CUST1019 | B21: Michael Torres | C21: 46 | D21: Female | E21: Gonzalezfort | F21: New Jersey | G21: USA | H21: Platinum
A22: CUST1020 | B22: Bridget Allen | C22: 59 | D22: Male | E22: Lake Shaneburgh | F22: Delaware | G22: USA | H22: Silver
A23: CUST1021 | B23: Jeff Martinez | C23: 36 | D23: Female | E23: Smithburgh | F23: Oklahoma | G23: USA | H23: Gold
A24: CUST1022 | B24: paul fox | C24: 33 | D24: Female | E24: Michaelton | F24: Hawaii | G24: USA | H24: Silver
A25: CUST1023 | B25: Jonathan Steele | C25: 52 | D25: Female | E25: Molinabury | F25: Oregon | G25: USA | H25: Silver
A26: CUST1024 | B26: Heather Collins | C26: 40 | D26: Male | E26: Rogerschester | F26: Idaho | G26: USA | H26: Platinum
A27: CUST1025 | B27: Diana Taylor | C27: 59 | D27: Female | E27: Vasqueztown | F27: California | G27: USA | H27: Bronze
A28: CUST1026 | B28: Amber Carlson | C28: 18 | D28: Female | E28: East Michellemouth | F28: Missouri | G28: USA | H28: Gold
A29: CUST1027 | B29: Leslie Johnson | C29: 31 | D29: Male | E29: Mollyshire | F29: Utah | G29: USA
A30: CUST1028 | B30: Joshua Ryan | C30: 27 | D30: Female | E30: New David | F30: New Jersey | G30: USA | H30: Platinum
A31: CUST1029 | B31: David Arnold | C31: 54 | D31: Female | E31: East Jennifer | F31: California | G31: USA | H31: Silver
A32: CUST1030 | B32: Jessica Acevedo | C32: 64 | D32: Female | E32: Amybury | F32: Pennsylvania | G32: USA | H32: Bronze
A33: CUST1031 | B33: Sarah Vance | C33: 41 | D33: Male | E33: Johnsonville | F33: Oregon | G33: USA | H33: Silver
A34: CUST1032 | B34: Mike Jennings | C34: 48 | D34: Female | E34: Fostermouth | F34: Arizona | G34: USA | H34: Gold
A35: CUST1033 | B35: Robert Jones DDS | C35: 25 | D35: Male | E35: Tristanton | F35: Oklahoma | G35: USA | H35: Platinum
A36: CUST1034 | B36: Christopher Olson | C36: 27 | D36: Female | E36: West Richard | F36: Maryland | G36: USA | H36: Platinum
A37: CUST1035 | B37: Rachel Myers | C37: 52 | D37: Male | E37: Robertberg | F37: North Dakota | G37: USA | H37: Silver
A38: CUST1036 | B38: Thomas Phillips | C38: 20 | D38: Female | E38: Luisfurt | F38: Georgia | G38: USA | H38: Gold
A39: CUST1037 | B39: Christopher Carter | C39: 27 | D39: Female | E39: Brendastad | F39: South Dakota | G39: USA
A40: CUST1038 | B40: Deanna Simpson | C40: 35 | D40: Female | E40: Brownport | F40: North Dakota | G40: USA | H40: Bronze
A41: CUST1039 | B41: Tonya Reynolds | C41: 55 | D41: Female | E41: Darleneton | F41: Michigan | G41: USA | H41: Gold
A42: CUST1040 | B42: Eric Vega | C42: 50 | D42: Male | E42: Williamsonland | F42: Kansas | G42: USA | H42: Gold
A43: CUST1041 | B43: James Gibbs | C43: 21 | D43: Male | E43: Mooneyshire | F43: Alaska | G43: USA | H43: Platinum
A44: CUST1042 | B44: William Martin | C44: 19 | D44: Male | E44: Ryanburgh | F44: Connecticut | G44: USA | H44: Platinum
A45: CUST1043 | B45: Joseph Snow | C45: 45 | D45: Male | E45: South Michaelfort | F45: Vermont | G45: USA | H45: Gold
A46: CUST1044 | B46: Denise Williams | C46: 34 | D46: Male | E46: Christianstad | F46: Hawaii | G46: USA | H46: Bronze
A47: CUST1045 | B47: Jordan Jackson DDS | C47: 54 | D47: Male | E47: North Johnview | F47: Arizona | G47: USA | H47: Gold
A48: CUST1046 | B48: Michelle Garcia DDS | C48: 55 | D48: Female | E48: Perezbury | F48: Ohio | G48: USA | H48: Platinum
A49: CUST1047 | B49: Gina Knight | C49: 54 | D49: Female | E49: Lake Roberthaven | F49: Nevada | G49: USA | H49: Silver
A50: CUST1048 | B50: April Mullins | C50: 54 | D50: Male | E50: Dawsonbury | F50: North Carolina | G50: USA | H50: Platinum
A51: CUST1049 | B51: Timothy Weaver | C51: 45 | D51: Female | E51: New Amy | F51: Ohio | G51: USA | H51: Gold
... A501: C-1499 | B501: Philip Pennington | C501: 27 | D501: Female | E501: East Valerieview | F501: Oregon | G501: USA | H501: Platinum

Sheet Product_Dim
A1: Product_ID | B1: Product_Name | C1: Category | D1: Sub_Category | E1: Brand | F1: Cost | G1: Stock
A2: PROD0 | B2: Brother Laser Printer | C2: Electronics | D2: Computer | E2: Hunt Inc | F2: 112.42 | G2: 416
A3: PROD1 | B3: Men's Graphic T-Shirt | C3: Clothing | D3: Tops | E3: Terry-Moore | F3: 342.56 | G3: 181
A4: PROD2 | B4: Women's Casual Hoodie | C4: Clothing | D4: Outerwear | E4: Sims Inc | G4: 352
A5: P-3 | B5: Men's Running Jacket | C5: Clothing | D5: Outerwear | E5: Pineda Ltd | F5: 364.67 | G5: 452
A6: PROD4 | B6: Women's Yoga Pants | C6: Clothing | D6: Bottoms | E6: Gonzales-Davis | F6: 306.46 | G6: 487
A7: PROD5 | B7: Men's Leather Belt | C7: Clothing | D7: Accessories | E7: Baldwin, Garza and Gonzalez | F7: 261 | G7: 59
A8: PROD6 | B8: Herbal Face Moisturizer | C8: Beauty | D8: Skincare | E8: Davidson PLC | F8: 312.8 | G8: 350
A9: PROD7 | B9: LED Table Lamp | C9: Home | D9: Lighting | E9: Harrell LLC | F9: 218.86 | G9: 170
A10: PROD8 | B10: Wireless Bluetooth Earbuds | C10: Electronics | D10: Audio | E10: Perez-Johnston | F10: 439.07 | G10: 142
A11: PROD9 | B11: Adjustable Dumbbell Set | C11: Sports | D11: Fitness | E11: Hill PLC | F11: 495.72 | G11: 323
A12: PROD10 | B12: Ceramic Kitchen Bowl Set | C12: Home | D12: Kitchen | E12: Hamilton Group | F12: 298.86 | G12: 308
A13: PROD11 | B13: HD Smart TV Stick | C13: Electronics | D13: Accessories | E13: Gibson, Hobbs and Weaver | F13: 449.4
A14: PROD12 | B14: Hair Strengthening Shampoo | C14: Beauty | D14: Haircare | E14: Rice LLC | F14: 115.82 | G14: 460
A15: PROD13 | B15: USB-C Fast Charger | C15: Electronics | D15: Accessories | E15: Dawson-Perkins | F15: 242.23 | G15: 453
A16: PROD14 | B16: Decorative Wall Mirror | C16: Home | D16: Decor | E16: Luna, Anderson and Bowman | F16: 48.01 | G16: 439
A17: PROD15 | B17: 4K Home Projector | C17: Electronics | D17: Appliances | E17: Thomas LLC | F17: 465.34 | G17: 301
A18: P-16 | B18: Beard Grooming Kit | C18: Beauty | D18: Grooming | E18: Erickson-Green | F18: 337.42 | G18: 256
A19: PROD17 | B19: Soccer Training Cone Set | C19: Sports | D19: Accessories | E19: Ford, Murphy and Wilson | F19: 144.53 | G19: 367
A20: PROD18 | B20: Women's Denim Jeans | C20: Clothing | D20: Bottoms | E20: Guerra-Hendrix | G20: 343
A21: PROD19 | B21: Knee Support Brace | C21: Sports | D21: Equipment | E21: May-Reese | F21: 21.34 | G21: 65
A22: PROD20 | B22: Outdoor Sports Water Bottle | C22: Sports | D22: Accessories | E22: Soto-Ellis | F22: 131.51
A23: PROD21 | B23: Multi-Purpose Storage Box | C23: Home | D23: Storage | E23: Gardner-Montes | F23: 123.46 | G23: 76
A24: PROD22 | B24: Carbon Fiber Tennis Racket | C24: Sports | D24: Equipment | E24: Flores, Pineda and Rodriguez | F24: 484.62 | G24: 432
A25: PROD23 | B25: Men's Formal Shirt | C25: Clothing | D25: Tops | E25: Moon, Mora and Santos | G25: 360
A26: PROD24 | B26: Foldable Camping Chair | C26: Sports | D26: Outdoor | E26: Cook Ltd | F26: 166.06 | G26: 340
A27: PROD25 | B27: Women's Scarf Set | C27: Clothing | D27: Accessories | E27: Brown and Sons | F27: 174.02 | G27: 268
A28: PROD26 | B28: Wireless Bluetooth Speaker | C28: Electronics | D28: Audio | E28: Reed-Schmidt | F28: 322.41 | G28: 213
A29: PROD27 | B29: Decorative Floor Vase | C29: Home | D29: Decor | E29: Khan, Jones and Paul | G29: 378
A30: PROD28 | B30: Sports Stopwatch Timer | C30: Sports | D30: Accessories | E30: Burns-Hansen | F30: 38.76 | G30: 137
A31: PROD29 | B31: Fabric Sofa Throw Blanket | C31: Home | D31: Decor | E31: Hoffman Group | F31: 218.48 | G31: 276
A32: PROD30 | B32: Stainless Steel Cutlery Set | C32: Home | D32: Kitchen | E32: Stevens, Fernandez and Martin | F32: 19.52 | G32: 57
A33: PROD31 | B33: Basketball | C33: Sports | D33: Team Sports | E33: Nolan-Snow | F33: 204.39 | G33: 281
A34: PROD32 | B34: Vitamin C Face Serum | C34: Beauty | D34: Skincare | E34: Griffin Ltd | F34: 283.83 | G34: 244
A35: PROD33 | B35: Modern Wall Clock | C35: Home | D35: Decor | E35: Weiss-Watson | F35: 179.77 | G35: 305
A36: PROD34 | B36: Gaming Mechanical Keyboard | C36: Electronics | D36: Computer | E36: Lucero LLC | F36: 419.28 | G36: 86
A37: PROD35 | B37: Bedroom Table Lamp | C37: Home | D37: Lighting | E37: Jones LLC | F37: 382.22 | G37: 329
A38: PROD36 | B38: Women's Summer Dress | C38: Clothing | D38: Tops | E38: Smith-Mills | F38: 223.43 | G38: 154
A39: PROD37 | B39: Men's Casual Sneakers | C39: Clothing | D39: Footwear | E39: Hogan-Lee | F39: 353.47 | G39: 214
A40: PROD38 | B40: Sports Water Hydration Pack | C40: Sports | D40: Outdoor | E40: Sims-Smith | F40: 135.61 | G40: 394
A41: PROD39 | B41: Portable Power Bank | C41: Electronics | D41: Mobile | E41: Cummings and Sons | F41: 326.06 | G41: 301
... A48: PROD46 | B48: Men's Winter Jacket | C48: Clothing | D48: Outerwear | E48: Kelly, Smith and Perez | F48: 167.34 | G48: 296
A49: PROD47 | B49: Makeup Brush Set | C49: Beauty | D49: Makeup | E49: Cook Inc | G49: 431
A50: PROD48 | B50: Car Dashboard Phone Holder | C50: Electronics | D50: Accessories | E50: Byrd, Stewart and Valdez | F50: 177.98 | G50: 103
A51: PROD49 | B51: Men's Roll-On Perfume | C51: Beauty | D51: Fragrance | E51: Sullivan and Sons | F51: 43.29 | G51: 267
A52: PROD50 | B52: Boxing Hand Wraps | C52: Sports | D52: Fitness | E52: Smith-King | F52: 190.29 | G52: 260
A53: PROD51 | B53: HDMI Cable – 2m | C53: Electronics | D53: Accessories | E53: Bautista, Green and Hale | F53: 88.49 | G53: 246
A54: PROD52 | B54: Rugby Ball | C54: Sports | D54: Team Sports | E54: Harris Inc | F54: 212.26 | G54: 82
A55: PROD53 | B55: Men's Track Pants | C55: Clothing | D55: Bottoms | E55: Hamilton, Woods and Walker | F55: 386.56 | G55: 125
A56: PROD54 | B56: Sports Stopwatch Pro | C56: Sports | D56: Accessories | E56: Thompson-French | F56: 434.84 | G56: 185
A57: PROD55 | B57: Ceramic Plant Pot | C57: Home | D57: Decor | E57: Hatfield, Baird and Torres | F57: 81.75
A58: PROD56 | B58: Premium Blanket Throw | C58: Home | D58: Decor | E58: Hernandez, Kennedy and Porter | F58: 461.47 | G58: 190
A59: PROD57 | B59: Foam Roller | C59: Sports | D59: Fitness | E59: Atkinson, Camacho and Oliver | F59: 30.62 | G59: 138
A60: PROD58 | B60: Womens Cotton Scarf | C60: Clothing | D60: Accessories | E60: Shepherd-Gould | F60: 113.83 | G60: 485
A61: PROD59 | B61: Men's Hair Styling Gel | C61: Beauty | D61: Haircare | E61: Cline-Mccarthy | F61: 17.31 | G61: 399
A62: PROD60 | B62: Luxury Perfume Spray | C62: Beauty | D62: Fragrance | E62: Gibson, Green and Lopez | F62: 482.75 | G62: 444
A63: PROD61 | B63: Tennis Ball 3-Pack | C63: Sports | D63: Equipment | E63: Lopez LLC | F63: 103.45 | G63: 465
A64: PROD62 | B64: Laptop Cooling Pad | C64: Electronics | D64: Computer | E64: Murray, Gould and Ware | F64: 86.42 | G64: 222
A65: PROD63 | B65: Organic Sunscreen Lotion | C65: Beauty | D65: Skincare | E65: Anderson-Riley | F65: 266.86 | G65: 458
A66: PROD64 | B66: Matte Lipstick Set | C66: Beauty | D66: Makeup | E66: Zhang Inc | F66: 299.11 | G66: 118
A67: PROD65 | B67: Adjustable Dumbbells 20kg | C67: Sports | D67: Fitness | E67: Montgomery, Benton and Miller | F67: 240.63 | G67: 423
A68: PROD66 | B68: Women's Hair Dryer Brush | C68: Beauty | D68: Haircare | E68: Torres, Spencer and Potter | F68: 340.39 | G68: 177
A69: PROD67 | B69: Smart LED Light Strip | C69: Electronics | D69: Accessories | E69: Flores-Davis | F69: 349.17 | G69: 476
... A84: PROD82 | B84: Fitness Resistance Bands | C84: Sports | D84: Fitness | E84: Reese-Watson | F84: 152.92 | G84: 281
A85: PROD83 | B85: Hydrating Face Cleanser | C85: Beauty | D85: Skincare | E85: Butler Group | G85: 159
A86: PROD84 | B86: Wooden Bookshelf | C86: Home | D86: Furniture | E86: Collins-Stephenson | F86: 388.46 | G86: 208
A87: PROD85 | B87: Women's Beanie Hat | C87: Clothing | D87: Accessories | E87: Richardson-Carrillo | F87: 119.57 | G87: 210
A88: PROD86 | B88: Kitchen Cutting Board | C88: Home | D88: Kitchen | E88: Taylor, Dodson and Johnston | F88: 176.07 | G88: 82
A89: PROD87 | B89: LED Bedside Lamp | C89: Home | D89: Lighting | E89: Aguilar, Horton and Lewis | F89: 371.38 | G89: 220
A90: PROD88 | B90: Sports Wrist Sweatbands | C90: Sports | D90: Accessories | E90: Olsen-Daniels | F90: 131.24 | G90: 232
A91: PROD89 | B91: Face Foundation Kit | C91: Beauty | D91: Makeup | E91: Taylor-Elliott | F91: 183.04 | G91: 457
A92: PROD90 | B92: Gaming Mouse Pad XL | C92: Electronics | D92: Accessories | E92: Sharp, Taylor and Rodriguez | F92: 340.14 | G92: 361
A93: PROD91 | B93: Women's High Heels | C93: Clothing | D93: Footwear | E93: Smith-Charles | F93: 438.25 | G93: 496
A94: PROD92 | B94: Microwave Oven | C94: Home | D94: Appliances | E94: Green, Powell and Palmer | F94: 447.43 | G94: 191
A95: PROD93 | B95: USB-C Laptop Charger | C95: Electronics | D95: Computer | E95: Martin LLC | F95: 377.52 | G95: 485
A96: PROD94 | B96: Vitamin E Body Lotion | C96: Beauty | D96: Skincare | E96: Hoffman-Williams | F96: 358.47 | G96: 213
A97: PROD95 | B97: Sports Stopwatch Basic | C97: Sports | D97: Accessories | E97: Wilson Group | F97: 60.65 | G97: 75
... A101: PROD99 | B101: Stainless Steel Cookware Set | C101: Home | D101: Kitchen | E101: Campbell Ltd | F101: 201.41 | G101: 146

Sheet Store_Dim
A1: Store_ID | B1: Store_Name | C1: Region | D1: City | E1: Store_Type
A2: STORE0 | B2: Rivera-Warner | C2: East | D2: Washingtonfurt | E2: Flagship
A3: STORE1 | B3: Martinez, Adkins and Johnson | C3: North | D3: Danielmouth | E3: Flagship
A4: STORE2 | B4: Black-Horn | C4: South | D4: North Nancyview | E4: Outlet
A5: STORE3 | B5: Johnson-Wright | C5: North | D5: Hoodberg | E5: Outlet
A6: STORE4 | B6: Alexander Group | C6: South | D6: Port Sharon | E6: Online
A7: STORE5 | B7: Gray Ltd | C7: North | D7: New Michaelchester | E7: Outlet
A8: STORE6 | B8: Benson-Elliott | C8: East | D8: Port Josephberg | E8: Online
A9: STORE7 | B9: Martinez-Mullins | C9: South | D9: Williamsfurt | E9: Online
A10: STORE8 | B10: Bean, Jones and Park | C10: West | D10: Thompsonborough | E10: Online
A11: STORE9 | B11: Moore, Padilla and Butler | C11: South | D11: East Johnstad | E11: Flagship
A12: STORE10 | B12: Hill, Wagner and Ballard | C12: East | D12: East Davidville | E12: Online
... A21: STORE19 | B21: Mann-Austin | C21: East | D21: Vasquezborough | E21: Online

Sheet Sales_Fact
A1: Sales_ID | B1: Order_Date | C1: Customer_ID | D1: Product_ID | E1: Store_ID | F1: Quantity | G1: Unit_Price | H1: Discount | I1: Payment_Type | J1: Total_Amount
A2: SALE0 | B2: 45480 | C2: CUST1409 | D2: PROD97 | E2: STORE3 | F2: 1 | G2: 218.04 | H2: 0.09 | I2: Credit Card | J2: 198.4164
A3: SALE1 | B3: 45285 | C3: CUST1467 | D3: PROD74 | E3: STORE17 | F3: 3 | G3: 104.47 | H3: 0.27 | I3: PayPal | J3: 228.7893
A4: SALE2 | B4: 45446 | C4: CUST1056 | D4: PROD49 | E4: STORE8 | F4: 4 | G4: 914.05 | H4: 0.25 | I4: Credit Card | J4: 2742.15
A5: SALE3 | B5: 45259 | C5: CUST1346 | D5: PROD76 | E5: STORE8 | F5: 1 | G5: 921.51 | H5: 0.16 | I5: COD | J5: 774.0684
A6: SALE4 | B6: 45297 | C6: CUST1493 | D6: PROD59 | E6: STORE5 | F6: 3 | G6: 745.3 | H6: 0.18 | I6: Credit Card | J6: 1833.438
A7: SALE5 | B7: 45499 | C7: CUST1116 | D7: PROD15 | E7: STORE7 | F7: 3 | G7: 147.01 | H7: 0.19 | I7: COD | J7: 357.2343
A8: SALE6 | B8: 45850 | C8: CUST1016 | D8: PROD56 | E8: STORE4 | F8: 2 | G8: 785.31 | H8: 0.15 | I8: PayPal | J8: 1335.027
A9: SALE7 | B9: 45248 | C9: CUST1152 | D9: PROD70 | E9: STORE8 | F9: 4 | G9: 342.39 | H9: 0.23 | I9: PayPal | J9: 1054.5612
A10: SALE8 | B10: 45781 | C10: CUST1187 | D10: PROD99 | E10: STORE5 | G10: 448.25 | H10: 0.07 | I10: PayPal | J10: 1250.6175
A11: SALE9 | B11: 45869 | C11: CUST1464 | D11: PROD33 | E11: STORE0 | F11: 2 | G11: 873.17 | H11: 0.23 | I11: PayPal | J11: 1344.6818
A12: SALE10 | B12: 45335 | C12: CUST1065 | D12: PROD24 | E12: STORE14 | F12: 1 | G12: 278.63 | H12: 0.07 | I12: Credit Card | J12: 259.1259
A13: SALE11 | B13: 45801 | C13: CUST1320 | D13: PROD39 | E13: STORE1 | F13: 4 | G13: 286.92 | H13: 0.17 | I13: Credit Card | J13: 952.5744
A14: SALE12 | B14: 45528 | C14: CUST1237 | D14: PROD88 | E14: STORE4 | F14: 4 | G14: 644.58 | H14: 0.01 | I14: Credit Card | J14: 2552.5368
A15: SALE13 | B15: 45875 | C15: CUST1443 | D15: PROD34 | E15: STORE16 | F15: 2 | G15: 316.9 | H15: 0.3 | I15: PayPal | J15: 443.66
A16: SALE14 | B16: 45829 | C16: CUST1348 | D16: PROD24 | E16: STORE15 | F16: 4 | G16: 403.47 | H16: 0.29 | I16: PayPal | J16: 1145.8548
A17: SALE15 | B17: 45636 | C17: CUST1435 | D17: PROD36 | E17: STORE9 | G17: 871.34 | H17: 0.04 | I17: COD | J17: 2509.4592
A18: SALE16 | B18: 45913 | C18: CUST1276 | D18: PROD65 | E18: STORE19 | F18: 2 | G18: 451.98 | H18: 0.25 | I18: Credit Card | J18: 677.97
A19: SALE17 | B19: 45637 | C19: CUST1079 | D19: PROD27 | E19: STORE4 | F19: 2 | G19: 502.69 | H19: 0.23 | I19: Credit Card | J19: 774.1426
A20: SALE18 | B20: 45517 | C20: CUST1094 | D20: PROD39 | E20: STORE4 | F20: 2 | G20: 559.23 | H20: 0.25 | I20: COD | J20: 838.845
A21: SALE19 | B21: 45369 | C21: CUST1239 | D21: PROD60 | E21: STORE13 | F21: 4 | H21: 0.04 | I21: COD | J21: 1782.4512
A22: SALE20 | B22: 45843 | C22: CUST1144 | D22: PROD72 | E22: STORE17 | F22: 3 | G22: 986.04 | H22: 0.27 | I22: COD | J22: 2159.4276
A23: SALE21 | B23: 45447 | C23: CUST1396 | D23: PROD43 | E23: STORE18 | F23: 1 | G23: 589.56 | H23: 0.22 | I23: Credit Card | J23: 459.8568
A24: SALE22 | B24: 45394 | C24: CUST1476 | D24: PROD69 | E24: STORE10 | F24: 3 | G24: 979.42 | H24: 0.03 | I24: PayPal | J24: 2850.1122
A25: SALE23 | B25: 45466 | C25: CUST1368 | D25: PROD12 | E25: STORE8 | F25: 1 | G25: 719.28 | H25: 0.08 | I25: Credit Card | J25: 661.7376
A26: SALE24 | B26: 45908 | C26: CUST1186 | D26: PROD67 | E26: STORE6 | F26: 3 | G26: 77.6 | H26: 0.07 | I26: Credit Card | J26: 216.504
A27: SALE25 | B27: 45552 | C27: CUST1381 | D27: PROD5 | E27: STORE3 | F27: 4 | G27: 852.71 | H27: 0.14 | I27: PayPal | J27: 2933.3224
A28: SALE26 | B28: 45294 | C28: CUST1213 | D28: PROD98 | E28: STORE8 | F28: 4 | G28: 156.16 | I28: Credit Card | J28: 599.6544
A29: SALE27 | B29: 45710 | C29: CUST1200 | D29: PROD77 | E29: STORE8 | F29: 3 | G29: 815.49 | H29: 0.17 | I29: Credit Card | J29: 2030.5701
A30: SALE28 | B30: 45923 | C30: CUST1148 | D30: PROD13 | E30: STORE2 | F30: 2 | G30: 74.21 | H30: 0.11 | I30: PayPal | J30: 132.0938
A31: SALE29 | B31: 45302 | C31: CUST1348 | D31: PROD99 | E31: STORE3 | G31: 451.67 | H31: 0.15 | I31: Credit Card | J31: 1535.678
A32: SALE30 | B32: 45217 | C32: CUST1028 | D32: PROD5 | E32: STORE19 | F32: 1 | G32: 429.38 | H32: 0.13 | I32: PayPal | J32: 373.5606
A33: SALE31 | B33: 45593 | C33: CUST1412 | D33: PROD53 | E33: STORE12 | F33: 2 | G33: 148.96 | H33: 0.03 | I33: COD | J33: 288.9824
A34: SALE32 | B34: 45597 | C34: CUST1398 | D34: PROD75 | E34: STORE8 | F34: 4 | G34: 313.83 | H34: 0.08 | I34: Credit Card | J34: 1154.8944
A35: SALE33 | B35: 45620 | C35: CUST1453 | D35: PROD12 | E35: STORE6 | F35: 2 | G35: 717.31 | H35: 0.15 | I35: Credit Card | J35: 1219.427
A36: SALE34 | B36: 45215 | C36: CUST1344 | D36: PROD79 | E36: STORE1 | G36: 873.22 | H36: 0.18 | I36: Credit Card | J36: 2148.1212
A37: SALE35 | B37: 45878 | C37: CUST1218 | D37: PROD16 | E37: STORE3 | F37: 4 | G37: 109.36 | H37: 0.19 | I37: COD | J37: 354.3264
A38: SALE36 | B38: 45635 | C38: CUST1086 | D38: PROD5 | E38: STORE7 | F38: 3 | G38: 559.52 | H38: 0.16 | I38: PayPal | J38: 1409.9904
A39: SALE37 | B39: 45329 | C39: CUST1492 | D39: PROD10 | E39: STORE17 | F39: 3 | G39: 121.76 | H39: 0.27 | I39: PayPal | J39: 266.6544
A40: SALE38 | B40: 45378 | C40: CUST1189 | D40: PROD33 | E40: STORE13 | F40: 4 | G40: 735.32 | H40: 0.06 | I40: COD | J40: 2764.8032
A41: SALE39 | B41: 45264 | C41: CUST1431 | D41: PROD94 | E41: STORE3 | F41: 2 | G41: 600.73 | H41: 0.08 | I41: Credit Card | J41: 1105.3432
A42: SALE40 | B42: 45486 | C42: CUST1072 | D42: PROD26 | E42: STORE19 | F42: 2 | G42: 873.86 | H42: 0.07 | I42: COD | J42: 1625.3796
A43: SALE41 | B43: 45241 | C43: CUST1302 | D43: PROD23 | E43: STORE8 | F43: 3 | G43: 342.47 | H43: 0.08 | I43: PayPal | J43: 945.2172
A44: SALE42 | B44: 45649 | C44: CUST1335 | D44: PROD29 | E44: STORE9 | F44: 2 | G44: 915.15 | H44: 0.16 | I44: PayPal | J44: 1537.452
A45: SALE43 | B45: 45677 | C45: CUST1084 | D45: PROD33 | E45: STORE17 | G45: 863.11 | H45: 0.28 | I45: PayPal | J45: 1864.3176
A46: SALE44 | B46: 45538 | C46: CUST1203 | D46: PROD43 | E46: STORE12 | F46: 2 | G46: 209.32 | H46: 0.23 | I46: COD | J46: 322.3528
A47: SALE45 | B47: 45606 | C47: CUST1470 | D47: PROD59 | E47: STORE8 | F47: 4 | G47: 288.6 | H47: 0.09 | I47: PayPal | J47: 1050.504
A48: SALE46 | B48: 45570 | C48: CUST1070 | D48: PROD78 | E48: STORE16 | F48: 1 | G48: 418.69 | H48: 0.06 | I48: PayPal | J48: 393.5686
A49: SALE47 | B49: 45466 | C49: CUST1008 | D49: PROD30 | E49: STORE11 | F49: 1 | G49: 135.78 | H49: 0.14 | I49: PayPal | J49: 116.7708
A50: SALE48 | B50: 45218 | C50: CUST1203 | D50: PROD44 | E50: STORE17 | F50: 1 | G50: 517.13 | H50: 0.28 | I50: Credit Card | J50: 372.3336
A51: SALE49 | B51: 45607 | C51: CUST1420 | D51: PROD21 | E51: STORE16 | F51: 2 | G51: 384.66 | H51: 0.08 | I51: COD | J51: 707.7744
A52: SALE50 | B52: 45291 | C52: CUST1070 | D52: PROD52 | E52: STORE9 | F52: 3 | G52: 83.7 | H52: 0.24 | I52: PayPal | J52: 190.836
A53: SALE51 | B53: 45689 | C53: CUST1142 | D53: PROD69 | E53: STORE7 | F53: 3 | G53: 76.57 | H53: 0.26 | I53: Credit Card | J53: 169.9854
A54: SALE52 | B54: 45894 | C54: CUST1148 | D54: PROD89 | E54: STORE6 | F54: 3 | I54: Credit Card | J54: 486.0633
A55: SALE53 | B55: 45677 | C55: CUST1324 | D55: PROD20 | E55: STORE8 | F55: 1 | G55: 900.35 | H55: 0.13 | I55: COD | J55: 783.3045
A56: SALE54 | B56: 45706 | C56: CUST1095 | D56: PROD40 | E56: STORE10 | F56: 4 | G56: 428.09 | H56: 0.07 | I56: Credit Card | J56: 1592.4948
A57: SALE55 | B57: 45589 | C57: CUST1416 | D57: PROD49 | E57: STORE11 | F57: 2 | G57: 559.71 | H57: 0.3 | I57: COD | J57: 783.594
A58: SALE56 | B58: 45282 | C58: CUST1080 | D58: PROD34 | E58: STORE6 | F58: 2 | G58: 833.7 | H58: 0.06 | I58: PayPal | J58: 1567.356
A59: SALE57 | B59: 45462 | C59: CUST1467 | D59: PROD47 | E59: STORE14 | F59: 2 | G59: 680.16 | H59: 0.28 | I59: Credit Card | J59: 979.4304
A60: SALE58 | B60: 45633 | C60: CUST1404 | D60: PROD15 | E60: STORE7 | F60: 4 | G60: 733.42 | I60: PayPal | J60: 2552.3016
A61: SALE59 | B61: 45257 | C61: CUST1367 | D61: PROD89 | E61: STORE11 | F61: 1 | G61: 996.33 | H61: 0.23 | I61: PayPal | J61: 767.1741
A62: SALE60 | B62: 45854 | C62: CUST1408 | D62: PROD31 | E62: STORE10 | F62: 1 | G62: 198.83 | H62: 0.09 | I62: COD | J62: 180.9353
A63: SALE61 | B63: 45716 | C63: CUST1239 | D63: PROD19 | E63: STORE7 | F63: 1 | G63: 374.92 | H63: 0.18 | I63: PayPal | J63: 307.4344
A64: SALE62 | B64: 45515 | C64: CUST1464 | D64: PROD93 | E64: STORE16 | F64: 1 | G64: 468.94 | H64: 0.12 | I64: Credit Card | J64: 412.6672
A65: SALE63 | B65: 45927 | C65: CUST1126 | D65: PROD89 | E65: STORE12 | F65: 2 | G65: 121.37 | H65: 0.05 | I65: Credit Card | J65: 230.603
A66: SALE64 | B66: 45914 | C66: CUST1255 | D66: PROD53 | E66: STORE10 | F66: 3 | G66: 480.06 | H66: 0.01 | I66: Credit Card
A67: SALE65 | B67: 45290 | C67: CUST1162 | D67: PROD99 | E67: STORE17 | F67: 2 | G67: 856.57 | H67: 0.24 | I67: Credit Card | J67: 1301.9864
A68: SALE66 | B68: 45213 | C68: CUST1269 | D68: PROD77 | E68: STORE2 | F68: 4 | G68: 814.25 | H68: 0.18 | I68: Credit Card | J68: 2670.74
A69: SALE67 | B69: 45255 | C69: CUST1483 | D69: PROD12 | E69: STORE2 | F69: 1 | G69: 989.17 | H69: 0.2 | I69: PayPal | J69: 791.336
A70: SALE68 | B70: 45270 | C70: CUST1372 | D70: PROD72 | E70: STORE10 | F70: 4 | G70: 62.48 | H70: 0.18 | I70: Credit Card | J70: 204.9344
A71: SALE69 | B71: 45897 | C71: CUST1423 | D71: PROD13 | E71: STORE16 | F71: 4 | G71: 561.24 | H71: 0.24 | I71: Credit Card | J71: 1706.1696
A72: SALE70 | B72: 45849 | C72: CUST1058 | D72: PROD60 | E72: STORE5 | F72: 3 | G72: 92.24 | H72: 0.28 | I72: COD
A73: SALE71 | B73: 45889 | C73: CUST1168 | D73: PROD72 | E73: STORE1 | F73: 2 | G73: 668.3 | H73: 0.07 | I73: Credit Card | J73: 1243.038
A74: SALE72 | B74: 45533 | C74: CUST1409 | D74: PROD38 | E74: STORE5 | F74: 1 | G74: 553.82 | H74: 0.09 | I74: Credit Card | J74: 503.9762
A75: SALE73 | B75: 45626 | C75: CUST1037 | D75: PROD45 | E75: STORE11 | F75: 2 | G75: 556.43 | H75: 0.13 | I75: Credit Card | J75: 968.1882
A76: SALE74 | B76: 45942 | C76: CUST1273 | D76: PROD20 | E76: STORE8 | F76: 1 | G76: 184.98 | H76: 0.1 | I76: COD | J76: 166.482
A77: SALE75 | B77: 45500 | C77: CUST1035 | D77: PROD97 | E77: STORE12 | F77: 4 | G77: 700.18 | H77: 0.23 | I77: Credit Card | J77: 2156.5544
A78: SALE76 | B78: 45285 | C78: CUST1019 | D78: PROD76 | E78: STORE10 | F78: 2 | G78: 686.31 | H78: 0.25 | I78: Credit Card | J78: 1029.465
A79: SALE77 | B79: 45800 | C79: CUST1007 | D79: PROD67 | E79: STORE15 | F79: 1 | G79: 687.82 | H79: 0.27 | I79: COD | J79: 502.1086
A80: SALE78 | B80: 45609 | C80: CUST1221 | D80: PROD83 | E80: STORE8 | F80: 2 | G80: 900.55 | H80: 0.16 | I80: Credit Card | J80: 1512.924
A81: SALE79 | B81: 45268 | C81: CUST1115 | D81: PROD21 | E81: STORE2 | F81: 1 | G81: 341.17 | H81: 0.15 | I81: Credit Card | J81: 289.9945
A82: SALE80 | B82: 45885 | C82: CUST1176 | D82: PROD52 | E82: STORE8 | F82: 1 | G82: 442.27 | H82: 0.06 | I82: COD | J82: 415.7338
A83: SALE81 | B83: 45616 | C83: CUST1253 | D83: PROD71 | E83: STORE9 | F83: 1 | G83: 363.73 | H83: 0.25 | I83: PayPal | J83: 272.7975
A84: SALE82 | B84: 45518 | C84: CUST1378 | D84: PROD91 | E84: STORE17 | F84: 2 | G84: 601.33 | H84: 0.16 | I84: PayPal | J84: 1010.2344
A85: SALE83 | B85: 45427 | C85: CUST1403 | D85: PROD17 | E85: STORE18 | F85: 4 | G85: 34.39 | H85: 0.03 | I85: PayPal | J85: 133.4332
A86: SALE84 | B86: 45268 | C86: CUST1423 | D86: PROD46 | E86: STORE17 | F86: 1 | G86: 773.57 | H86: 0.05 | I86: COD
A87: SALE85 | B87: 45282 | C87: CUST1054 | D87: PROD88 | E87: STORE7 | F87: 4 | G87: 127.1 | H87: 0.24 | I87: COD | J87: 386.384
A88: SALE86 | B88: 45545 | C88: CUST1303 | D88: PROD20 | E88: STORE3 | F88: 3 | G88: 899.58 | H88: 0.28 | I88: PayPal | J88: 1943.0928
A89: SALE87 | B89: 45755 | C89: CUST1327 | D89: PROD1 | E89: STORE10 | F89: 3 | G89: 964.39 | H89: 0.04 | I89: Credit Card | J89: 2777.4432
A90: SALE88 | B90: 45588 | C90: CUST1183 | D90: PROD38 | E90: STORE0 | F90: 2 | G90: 217.83 | H90: 0.14 | I90: PayPal | J90: 374.6676
A91: SALE89 | B91: 45848 | C91: CUST1143 | D91: PROD17 | E91: STORE1 | F91: 4 | G91: 187.71 | H91: 0.06 | I91: COD | J91: 705.7896
A92: SALE90 | B92: 45577 | C92: CUST1010 | D92: PROD33 | E92: STORE18 | F92: 2 | G92: 350.12 | H92: 0.12 | I92: COD | J92: 616.2112
A93: SALE91 | B93: 45312 | C93: CUST1406 | D93: PROD16 | E93: STORE1 | F93: 4 | G93: 102.19 | H93: 0.17 | I93: PayPal | J93: 339.2708
A94: SALE92 | B94: 45350 | C94: CUST1007 | D94: PROD86 | E94: STORE4 | F94: 1 | G94: 696.53 | H94: 0.17 | I94: Credit Card | J94: 578.1199
A95: SALE93 | B95: 45657 | C95: CUST1065 | D95: PROD19 | E95: STORE4 | F95: 2 | G95: 327.52 | H95: 0.15 | I95: PayPal | J95: 556.784
A96: SALE94 | B96: 45530 | C96: CUST1298 | D96: PROD97 | E96: STORE19 | F96: 2 | G96: 569.36 | H96: 0.01 | I96: PayPal
A97: SALE95 | B97: 45556 | C97: CUST1321 | D97: PROD99 | E97: STORE6 | F97: 2 | G97: 68.29 | H97: 0.14 | I97: COD | J97: 117.4588
A98: SALE96 | B98: 45523 | C98: CUST1244 | D98: PROD50 | E98: STORE10 | F98: 1 | G98: 842.9 | H98: 0.06 | I98: COD | J98: 792.326
A99: SALE97 | B99: 45587 | C99: CUST1287 | D99: PROD3 | E99: STORE3 | F99: 3 | G99: 751.94 | H99: 0.26 | I99: PayPal | J99: 1669.3068
A100: SALE98 | B100: 45580 | C100: CUST1131 | D100: PROD56 | E100: STORE7 | F100: 4 | G100: 476.28 | H100: 0.17 | I100: Credit Card | J100: 1581.2496
...

Sheet Cleen customer data
A1: Customer_ID | B1: Name | C1: Column1 | D1: Age | E1: Gender | F1: State | G1: Country | H1: Loyality level | I1: Loyalty_Level
A2: CUST1000 | B2: sheena bonilla | C2: =PROPER(TRIM(B2)) -> Sheena Bonilla | D2: 55 | E2: Male | F2: North Carolina | G2: USA | H2: =IF(ISBLANK(Table2[[#This Row],[Loyalty_Level]]),"Unknown",I2) -> Unknown
A3: CUST1001 | B3: Eugene Nelson | C3: =PROPER(TRIM(B3)) -> Eugene Nelson | D3: 26 | E3: Female | F3: North Dakota | G3: USA | H3: =IF(ISBLANK(Table2[[#This Row],[Loyalty_Level]]),"Unknown",I3) -> Platinum | I3: Platinum
A4: CUST1002 | B4: dr. Benjamin Price | C4: =PROPER(TRIM(B4)) -> Dr. Benjamin Price | D4: 29 | E4: Female | F4: Alabama | G4: USA | H4: =IF(ISBLANK(Table2[[#This Row],[Loyalty_Level]]),"Unknown",I4) -> Platinum | I4: Platinum
A5: CUST1003 | B5: jeremy harris | C5: =PROPER(TRIM(B5)) -> Jeremy Harris | D5: 59 | E5: Female | F5: Ohio | G5: USA | H5: =IF(ISBLANK(Table2[[#This Row],[Loyalty_Level]]),"Unknown",I5) -> Bronze | I5: Bronze
A6: CUST1004 | B6: Caroline Collins | C6: =PROPER(TRIM(B6)) -> Caroline Collins | D6: 64 | E6: Female | F6: California | G6: USA | H6: =IF(ISBLANK(Table2[[#This Row],[Loyalty_Level]]),"Unknown",I6) -> Silver | I6: Silver
A7: CUST1005 | B7: Christine Vaughn | C7: =PROPER(TRIM(B7)) -> Christine Vaughn | D7: 24 | E7: Male | F7: Oregon | G7: USA | H7: =IF(ISBLANK(Table2[[#This Row],[Loyalty_Level]]),"Unknown",I7) -> Bronze | I7: Bronze
A8: CUST1006 | B8: Amber Jackson | C8: =PROPER(TRIM(B8)) -> Amber Jackson | D8: 29 | E8: Female | F8: South Dakota | G8: USA | H8: =IF(ISBLANK(Table2[[#This Row],[Loyalty_Level]]),"Unknown",I8) -> Platinum | I8: Platinum
A9: CUST1007 | B9: Daniel Boyd | C9: =PROPER(TRIM(B9)) -> Daniel Boyd | D9: 29 | E9: Female | F9: West Virginia | G9: USA | H9: =IF(ISBLANK(Table2[[#This Row],[Loyalty_Level]]),"Unknown",I9) -> Bronze | I9: Bronze
A10: CUST1008 | B10: Melissa Howard | C10: =PROPER(TRIM(B10)) -> Melissa Howard | D10: 53 | E10: Female | F10: New Hampshire | G10: USA | H10: =IF(ISBLANK(Table2[[#This Row],[Loyalty_Level]]),"Unknown",I10) -> Gold | I10: Gold
A11: CUST1009 | B11: Ms. Maria Leach | C11: =PROPER(TRIM(B11)) -> Ms. Maria Leach | D11: 64 | E11: Male | F11: Pennsylvania | G11: USA | H11: =IF(ISBLANK(Table2[[#This Row],[Loyalty_Level]]),"Unknown",I11) -> Platinum | I11: Platinum
A12: CUST1010 | B12: Dominic Page | C12: =PROPER(TRIM(B12)) -> Dominic Page | D12: 53 | E12: Male | F12: Pennsylvania | G12: USA | H12: =IF(ISBLANK(Table2[[#This Row],[Loyalty_Level]]),"Unknown",I12) -> Bronze | I12: Bronze
A13: CUST1011 | B13: Brian Lopez | C13: =PROPER(TRIM(B13)) -> Brian Lopez | D13: 28 | E13: Female | F13: New York | G13: USA | H13: =IF(ISBLANK(Table2[[#This Row],[Loyalty_Level]]),"Unknown",I13) -> Gold | I13: Gold
A14: CUST1012 | B14: Kenneth Lambert | C14: =PROPER(TRIM(B14)) -> Kenneth Lambert | D14: 55 | E14: Female | F14: Kansas | G14: USA | H14: =IF(ISBLANK(Table2[[#This Row],[Loyalty_Level]]),"Unknown",I14) -> Platinum | I14: Platinum
... A19: CUST1017 | B19: Adam Cruz | C19: =PROPER(TRIM(B19)) -> Adam Cruz | D19: 60 | E19: Female | F19: Georgia | G19: USA | H19: =IF(ISBLANK(Table2[[#This Row],[Loyalty_Level]]),"Unknown",I19) -> Platinum | I19: Platinum
A20: CUST1018 | B20: Rhonda Moss | C20: =PROPER(TRIM(B20)) -> Rhonda Moss | D20: 43 | E20: Male | F20: Kansas | G20: USA | H20: =IF(ISBLANK(Table2[[#This Row],[Loyalty_Level]]),"Unknown",I20) -> Unknown
A21: CUST1019 | B21: Michael Torres | C21: =PROPER(TRIM(B21)) -> Michael Torres | D21: 46 | E21: Female | F21: New Jersey | G21: USA | H21: =IF(ISBLANK(Table2[[#This Row],[Loyalty_Level]]),"Unknown",I21) -> Platinum | I21: Platinum
A22: CUST1020 | B22: Bridget Allen | C22: =PROPER(TRIM(B22)) -> Bridget Allen | D22: 59 | E22: Male | F22: Delaware | G22: USA | H22: =IF(ISBLANK(Table2[[#This Row],[Loyalty_Level]]),"Unknown",I22) -> Silver | I22: Silver
A23: CUST1021 | B23: Jeff Martinez | C23: =PROPER(TRIM(B23)) -> Jeff Martinez | D23: 36 | E23: Female | F23: Oklahoma | G23: USA | H23: =IF(ISBLANK(Table2[[#This Row],[Loyalty_Level]]),"Unknown",I23) -> Gold | I23: Gold
A24: CUST1022 | B24: paul fox | C24: =PROPER(TRIM(B24)) -> Paul Fox | D24: 33 | E24: Female | F24: Hawaii | G24: USA | H24: =IF(ISBLANK(Table2[[#This Row],[Loyalty_Level]]),"Unknown",I24) -> Silver | I24: Silver
A25: CUST1023 | B25: Jonathan Steele | C25: =PROPER(TRIM(B25)) -> Jonathan Steele | D25: 52 | E25: Female | F25: Oregon | G25: USA | H25: =IF(ISBLANK(Table2[[#This Row],[Loyalty_Level]]),"Unknown",I25) -> Silver | I25: Silver
A26: CUST1024 | B26: Heather Collins | C26: =PROPER(TRIM(B26)) -> Heather Collins | D26: 40 | E26: Male | F26: Idaho | G26: USA | H26: =IF(ISBLANK(Table2[[#This Row],[Loyalty_Level]]),"Unknown",I26) -> Platinum | I26: Platinum
A27: CUST1025 | B27: Diana Taylor | C27: =PROPER(TRIM(B27)) -> Diana Taylor | D27: 59 | E27: Female | F27: California | G27: USA | H27: =IF(ISBLANK(Table2[[#This Row],[Loyalty_Level]]),"Unknown",I27) -> Bronze | I27: Bronze
A28: CUST1026 | B28: Amber Carlson | C28: =PROPER(TRIM(B28)) -> Amber Carlson | D28: 18 | E28: Female | F28: Missouri | G28: USA | H28: =IF(ISBLANK(Table2[[#This Row],[Loyalty_Level]]),"Unknown",I28) -> Gold | I28: Gold
A29: CUST1027 | B29: Leslie Johnson | C29: =PROPER(TRIM(B29)) -> Leslie Johnson | D29: 31 | E29: Male | F29: Utah | G29: USA | H29: =IF(ISBLANK(Table2[[#This Row],[Loyalty_Level]]),"Unknown",I29) -> Unknown
A30: CUST1028 | B30: Joshua Ryan | C30: =PROPER(TRIM(B30)) -> Joshua Ryan | D30: 27 | E30: Female | F30: New Jersey | G30: USA | H30: =IF(ISBLANK(Table2[[#This Row],[Loyalty_Level]]),"Unknown",I30) -> Platinum | I30: Platinum
A31: CUST1029 | B31: David Arnold | C31: =PROPER(TRIM(B31)) -> David Arnold | D31: 54 | E31: Female | F31: California | G31: USA | H31: =IF(ISBLANK(Table2[[#This Row],[Loyalty_Level]]),"Unknown",I31) -> Silver | I31: Silver
A32: CUST1030 | B32: Jessica Acevedo | C32: =PROPER(TRIM(B32)) -> Jessica Acevedo | D32: 64 | E32: Female | F32: Pennsylvania | G32: USA | H32: =IF(ISBLANK(Table2[[#This Row],[Loyalty_Level]]),"Unknown",I32) -> Bronze | I32: Bronze
A33: CUST1031 | B33: Sarah Vance | C33: =PROPER(TRIM(B33)) -> Sarah Vance | D33: 41 | E33: Male | F33: Oregon | G33: USA | H33: =IF(ISBLANK(Table2[[#This Row],[Loyalty_Level]]),"Unknown",I33) -> Silver | I33: Silver
A34: CUST1032 | B34: Mike Jennings | C34: =PROPER(TRIM(B34)) -> Mike Jennings | D34: 48 | E34: Female | F34: Arizona | G34: USA | H34: =IF(ISBLANK(Table2[[#This Row],[Loyalty_Level]]),"Unknown",I34) -> Gold | I34: Gold
A35: CUST1033 | B35: Robert Jones DDS | C35: =PROPER(TRIM(B35)) -> Robert Jones Dds | D35: 25 | E35: Male | F35: Oklahoma | G35: USA | H35: =IF(ISBLANK(Table2[[#This Row],[Loyalty_Level]]),"Unknown",I35) -> Platinum | I35: Platinum
A36: CUST1034 | B36: Christopher Olson | C36: =PROPER(TRIM(B36)) -> Christopher Olson | D36: 27 | E36: Female | F36: Maryland | G36: USA | H36: =IF(ISBLANK(Table2[[#This Row],[Loyalty_Level]]),"Unknown",I36) -> Platinum | I36: Platinum
A37: CUST1035 | B37: Rachel Myers | C37: =PROPER(TRIM(B37)) -> Rachel Myers | D37: 52 | E37: Male | F37: North Dakota | G37: USA | H37: =IF(ISBLANK(Table2[[#This Row],[Loyalty_Level]]),"Unknown",I37) -> Silver | I37: Silver
A38: CUST1036 | B38: Thomas Phillips | C38: =PROPER(TRIM(B38)) -> Thomas Phillips | D38: 20 | E38: Female | F38: Georgia | G38: USA | H38: =IF(ISBLANK(Table2[[#This Row],[Loyalty_Level]]),"Unknown",I38) -> Gold | I38: Gold
A39: CUST1037 | B39: Christopher Carter | C39: =PROPER(TRIM(B39)) -> Christopher Carter | D39: 27 | E39: Female | F39: South Dakota | G39: USA | H39: =IF(ISBLANK(Table2[[#This Row],[Loyalty_Level]]),"Unknown",I39) -> Unknown
A40: CUST1038 | B40: Deanna Simpson | C40: =PROPER(TRIM(B40)) -> Deanna Simpson | D40: 35 | E40: Female | F40: North Dakota | G40: USA | H40: =IF(ISBLANK(Table2[[#This Row],[Loyalty_Level]]),"Unknown",I40) -> Bronze | I40: Bronze
A41: CUST1039 | B41: Tonya Reynolds | C41: =PROPER(TRIM(B41)) -> Tonya Reynolds | D41: 55 | E41: Female | F41: Michigan | G41: USA | H41: =IF(ISBLANK(Table2[[#This Row],[Loyalty_Level]]),"Unknown",I41) -> Gold | I41: Gold
A42: CUST1040 | B42: Eric Vega | C42: =PROPER(TRIM(B42)) -> Eric Vega | D42: 50 | E42: Male | F42: Kansas | G42: USA | H42: =IF(ISBLANK(Table2[[#This Row],[Loyalty_Level]]),"Unknown",I42) -> Gold | I42: Gold
A43: CUST1041 | B43: James Gibbs | C43: =PROPER(TRIM(B43)) -> James Gibbs | D43: 21 | E43: Male | F43: Alaska | G43: USA | H43: =IF(ISBLANK(Table2[[#This Row],[Loyalty_Level]]),"Unknown",I43) -> Platinum | I43: Platinum
A44: CUST1042 | B44: William Martin | C44: =PROPER(TRIM(B44)) -> William Martin | D44: 19 | E44: Male | F44: Connecticut | G44: USA | H44: =IF(ISBLANK(Table2[[#This Row],[Loyalty_Level]]),"Unknown",I44) -> Platinum | I44: Platinum
A45: CUST1043 | B45: Joseph Snow | C45: =PROPER(TRIM(B45)) -> Joseph Snow | D45: 45 | E45: Male | F45: Vermont | G45: USA | H45: =IF(ISBLANK(Table2[[#This Row],[Loyalty_Level]]),"Unknown",I45) -> Gold | I45: Gold
A46: CUST1044 | B46: Denise Williams | C46: =PROPER(TRIM(B46)) -> Denise Williams | D46: 34 | E46: Male | F46: Hawaii | G46: USA | H46: =IF(ISBLANK(Table2[[#This Row],[Loyalty_Level]]),"Unknown",I46) -> Bronze | I46: Bronze
A47: CUST1045 | B47: Jordan Jackson DDS | C47: =PROPER(TRIM(B47)) -> Jordan Jackson Dds | D47: 54 | E47: Male | F47: Arizona | G47: USA | H47: =IF(ISBLANK(Table2[[#This Row],[Loyalty_Level]]),"Unknown",I47) -> Gold | I47: Gold
A48: CUST1046 | B48: Michelle Garcia DDS | C48: =PROPER(TRIM(B48)) -> Michelle Garcia Dds | D48: 55 | E48: Female | F48: Ohio | G48: USA | H48: =IF(ISBLANK(Table2[[#This Row],[Loyalty_Level]]),"Unknown",I48) -> Platinum | I48: Platinum
A49: CUST1047 | B49: Gina Knight | C49: =PROPER(TRIM(B49)) -> Gina Knight | D49: 54 | E49: Female | F49: Nevada | G49: USA | H49: =IF(ISBLANK(Table2[[#This Row],[Loyalty_Level]]),"Unknown",I49) -> Silver | I49: Silver
A50: CUST1048 | B50: April Mullins | C50: =PROPER(TRIM(B50)) -> April Mullins | D50: 54 | E50: Male | F50: North Carolina | G50: USA | H50: =IF(ISBLANK(Table2[[#This Row],[Loyalty_Level]]),"Unknown",I50) -> Platinum | I50: Platinum
A51: CUST1049 | B51: Timothy Weaver | C51: =PROPER(TRIM(B51)) -> Timothy Weaver | D51: 45 | E51: Female | F51: Ohio | G51: USA | H51: =IF(ISBLANK(Table2[[#This Row],[Loyalty_Level]]),"Unknown",I51) -> Gold | I51: Gold
... A501: C-1499 | B501: Philip Pennington | C501: =PROPER(TRIM(B501)) -> Philip Pennington | D501: 27 | E501: Female | F501: Oregon | G501: USA | H501: =IF(ISBLANK(Table2[[#This Row],[Loyalty_Level]]),"Unknown",I501) -> Platinum | I501: Platinum

Sheet customer data final
A1: Customer_ID | B1: Name | C1: Age | D1: Gender | E1: State | F1: Country | G1: Loyalty_Level
A2: CUST1000 | B2: Sheena Bonilla | C2: 55 | D2: Male | E2: North Carolina | F2: USA | G2: Unknown
A3: CUST1001 | B3: Eugene Nelson | C3: 26 | D3: Female | E3: North Dakota | F3: USA | G3: Platinum
A4: CUST1002 | B4: Dr. Benjamin Price | C4: 29 | D4: Female | E4: Alabama | F4: USA | G4: Platinum
A5: CUST1003 | B5: Jeremy Harris | C5: 59 | D5: Female | E5: Ohio | F5: USA | G5: Bronze
A6: CUST1004 | B6: Caroline Collins | C6: 64 | D6: Female | E6: California | F6: USA | G6: Silver
A7: CUST1005 | B7: Christine Vaughn | C7: 24 | D7: Male | E7: Oregon | F7: USA | G7: Bronze
A8: CUST1006 | B8: Amber Jackson | C8: 29 | D8: Female | E8: South Dakota | F8: USA | G8: Platinum
A9: CUST1007 | B9: Daniel Boyd | C9: 29 | D9: Female | E9: West Virginia | F9: USA | G9: Bronze
A10: CUST1008 | B10: Melissa Howard | C10: 53 | D10: Female | E10: New Hampshire | F10: USA | G10: Gold
A11: CUST1009 | B11: Ms. Maria Leach | C11: 64 | D11: Male | E11: Pennsylvania | F11: USA | G11: Platinum
A12: CUST1010 | B12: Dominic Page | C12: 53 | D12: Male | E12: Pennsylvania | F12: USA | G12: Bronze
A13: CUST1011 | B13: Brian Lopez | C13: 28 | D13: Female | E13: New York | F13: USA | G13: Gold
... A501: C-1499 | B501: Philip Pennington | C501: 27 | D501: Female | E501: Oregon | F501: USA | G501: Platinum

Sheet Clean Product_Dim (2)
A1: Product_ID | B1: Product_Name | C1: Category | D1: Brand | E1: Cost | F1: Cost2 | G1: Stocks | H1: Stock
A2: PROD0 | B2: Brother Laser Printer | C2: Electronics | D2: Hunt Inc | E2: =IF(ISBLANK(Table3[[#This Row],[Cost2]]),"Not Found",F2) -> 112.42 | F2: 112.42 | G2: =IF(ISBLANK(Table3[[#This Row],[Cost2]]),"0",F2) -> 112.42 | H2: 416
A3: PROD1 | B3: Men's Graphic T-Shirt | C3: Clothing | D3: Terry-Moore | E3: =IF(ISBLANK(Table3[[#This Row],[Cost2]]),"Not Found",F3) -> 342.56 | F3: 342.56 | G3: =IF(ISBLANK(Table3[[#This Row],[Stock]]),"0",H3) -> 181 | H3: 181
A4: PROD2 | B4: Women's Casual Hoodie | C4: Clothing | D4: Sims Inc | E4: =IF(ISBLANK(Table3[[#This Row],[Cost2]]),"Not Found",F4) -> Not Found | G4: =IF(ISBLANK(Table3[[#This Row],[Stock]]),"0",H4) -> 352 | H4: 352
A5: P-3 | B5: Men's Running Jacket | C5: Clothing | D5: Pineda Ltd | E5: =IF(ISBLANK(Table3[[#This Row],[Cost2]]),"Not Found",F5) -> 364.67 | F5: 364.67 | G5: =IF(ISBLANK(Table3[[#This Row],[Stock]]),"0",H5) -> 452 | H5: 452
A6: PROD4 | B6: Women's Yoga Pants | C6: Clothing | D6: Gonzales-Davis | E6: =IF(ISBLANK(Table3[[#This Row],[Cost2]]),"Not Found",F6) -> 306.46 | F6: 306.46 | G6: =IF(ISBLANK(Table3[[#This Row],[Stock]]),"0",H6) -> 487 | H6: 487
A7: PROD5 | B7: Men's Leather Belt | C7: Clothing | D7: Baldwin, Garza and Gonzalez | E7: =IF(ISBLANK(Table3[[#This Row],[Cost2]]),"Not Found",F7) -> 261 | F7: 261 | G7: =IF(ISBLANK(Table3[[#This Row],[Stock]]),"0",H7) -> 59 | H7: 59
A8: PROD6 | B8: Herbal Face Moisturizer | C8: Beauty | D8: Davidson PLC | E8: =IF(ISBLANK(Table3[[#This Row],[Cost2]]),"Not Found",F8) -> 312.8 | F8: 312.8 | G8: =IF(ISBLANK(Table3[[#This Row],[Stock]]),"0",H8) -> 350 | H8: 350
A9: PROD7 | B9: LED Table Lamp | C9: Home | D9: Harrell LLC | E9: =IF(ISBLANK(Table3[[#This Row],[Cost2]]),"Not Found",F9) -> 218.86 | F9: 218.86 | G9: =IF(ISBLANK(Table3[[#This Row],[Stock]]),"0",H9) -> 170 | H9: 170
A10: PROD8 | B10: Wireless Bluetooth Earbuds | C10: Electronics | D10: Perez-Johnston | E10: =IF(ISBLANK(Table3[[#This Row],[Cost2]]),"Not Found",F10) -> 439.07 | F10: 439.07 | G10: =IF(ISBLANK(Table3[[#This Row],[Stock]]),"0",H10) -> 142 | H10: 142
A11: PROD9 | B11: Adjustable Dumbbell Set | C11: Sports | D11: Hill PLC | E11: =IF(ISBLANK(Table3[[#This Row],[Cost2]]),"Not Found",F11) -> 495.72 | F11: 495.72 | G11: =IF(ISBLANK(Table3[[#This Row],[Stock]]),"0",H11) -> 323 | H11: 323
A12: PROD10 | B12: Ceramic Kitchen Bowl Set | C12: Home | D12: Hamilton Group | E12: =IF(ISBLANK(Table3[[#This Row],[Cost2]]),"Not Found",F12) -> 298.86 | F12: 298.86 | G12: =IF(ISBLANK(Table3[[#This Row],[Stock]]),"0",H12) -> 308 | H12: 308
A13: PROD11 | B13: HD Smart TV Stick | C13: Electronics | D13: Gibson, Hobbs and Weaver | E13: =IF(ISBLANK(Table3[[#This Row],[Cost2]]),"Not Found",F13) -> 449.4 | F13: 449.4 | G13: =IF(ISBLANK(Table3[[#This Row],[Stock]]),"0",H13) -> 0
A14: PROD12 | B14: Hair Strengthening Shampoo | C14: Beauty | D14: Rice LLC | E14: =IF(ISBLANK(Table3[[#This Row],[Cost2]]),"Not Found",F14) -> 115.82 | F14: 115.82 | G14: =IF(ISBLANK(Table3[[#This Row],[Stock]]),"0",H14) -> 460 | H14: 460
A15: PROD13 | B15: USB-C Fast Charger | C15: Electronics | D15: Dawson-Perkins | E15: =IF(ISBLANK(Table3[[#This Row],[Cost2]]),"Not Found",F15) -> 242.23 | F15: 242.23 | G15: =IF(ISBLANK(Table3[[#This Row],[Stock]]),"0",H15) -> 453 | H15: 453
A16: PROD14 | B16: Decorative Wall Mirror | C16: Home | D16: Luna, Anderson and Bowman | E16: =IF(ISBLANK(Table3[[#This Row],[Cost2]]),"Not Found",F16) -> 48.01 | F16: 48.01 | G16: =IF(ISBLANK(Table3[[#This Row],[Stock]]),"0",H16) -> 439 | H16: 439
A17: PROD15 | B17: 4K Home Projector | C17: Electronics | D17: Thomas LLC | E17: =IF(ISBLANK(Table3[[#This Row],[Cost2]]),"Not Found",F17) -> 465.34 | F17: 465.34 | G17: =IF(ISBLANK(Table3[[#This Row],[Stock]]),"0",H17) -> 301 | H17: 301
A18: P-16 | B18: Beard Grooming Kit | C18: Beauty | D18: Erickson-Green | E18: =IF(ISBLANK(Table3[[#This Row],[Cost2]]),"Not Found",F18) -> 337.42 | F18: 337.42 | G18: =IF(ISBLANK(Table3[[#This Row],[Stock]]),"0",H18) -> 256 | H18: 256
A19: PROD17 | B19: Soccer Training Cone Set | C19: Sports | D19: Ford, Murphy and Wilson | E19: =IF(ISBLANK(Table3[[#This Row],[Cost2]]),"Not Found",F19) -> 144.53 | F19: 144.53 | G19: =IF(ISBLANK(Table3[[#This Row],[Stock]]),"0",H19) -> 367 | H19: 367
A20: PROD18 | B20: Women's Denim Jeans | C20: Clothing | D20: Guerra-Hendrix | E20: =IF(ISBLANK(Table3[[#This Row],[Cost2]]),"Not Found",F20) -> Not Found | G20: =IF(ISBLANK(Table3[[#This Row],[Stock]]),"0",H20) -> 343 | H20: 343
A21: PROD19 | B21: Knee Support Brace | C21: Sports | D21: May-Reese | E21: =IF(ISBLANK(Table3[[#This Row],[Cost2]]),"Not Found",F21) -> 21.34 | F21: 21.34 | G21: =IF(ISBLANK(Table3[[#This Row],[Stock]]),"0",H21) -> 65 | H21: 65
A22: PROD20 | B22: Outdoor Sports Water Bottle | C22: Sports | D22: Soto-Ellis | E22: =IF(ISBLANK(Table3[[#This Row],[Cost2]]),"Not Found",F22) -> 131.51 | F22: 131.51 | G22: =IF(ISBLANK(Table3[[#This Row],[Stock]]),"0",H22) -> 0
A23: PROD21 | B23: Multi-Purpose Storage Box | C23: Home | D23: Gardner-Montes | E23: =IF(ISBLANK(Table3[[#This Row],[Cost2]]),"Not Found",F23) -> 123.46 | F23: 123.46 | G23: =IF(ISBLANK(Table3[[#This Row],[Stock]]),"0",H23) -> 76 | H23: 76
A24: PROD22 | B24: Carbon Fiber Tennis Racket | C24: Sports | D24: Flores, Pineda and Rodriguez | E24: =IF(ISBLANK(Table3[[#This Row],[Cost2]]),"Not Found",F24) -> 484.62 | F24: 484.62 | G24: =IF(ISBLANK(Table3[[#This Row],[Stock]]),"0",H24) -> 432 | H24: 432
A25: PROD23 | B25: Men's Formal Shirt | C25: Clothing | D25: Moon, Mora and Santos | E25: =IF(ISBLANK(Table3[[#This Row],[Cost2]]),"Not Found",F25) -> Not Found | G25: =IF(ISBLANK(Table3[[#This Row],[Stock]]),"0",H25) -> 360 | H25: 360
A26: PROD24 | B26: Foldable Camping Chair | C26: Sports | D26: Cook Ltd | E26: =IF(ISBLANK(Table3[[#This Row],[Cost2]]),"Not Found",F26) -> 166.06 | F26: 166.06 | G26: =IF(ISBLANK(Table3[[#This Row],[Stock]]),"0",H26) -> 340 | H26: 340
A27: PROD25 | B27: Women's Scarf Set | C27: Clothing | D27: Brown and Sons | E27: =IF(ISBLANK(Table3[[#This Row],[Cost2]]),"Not Found",F27) -> 174.02 | F27: 174.02 | G27: =IF(ISBLANK(Table3[[#This Row],[Stock]]),"0",H27) -> 268 | H27: 268
A28: PROD26 | B28: Wireless Bluetooth Speaker | C28: Electronics | D28: Reed-Schmidt | E28: =IF(ISBLANK(Table3[[#This Row],[Cost2]]),"Not Found",F28) -> 322.41 | F28: 322.41 | G28: =IF(ISBLANK(Table3[[#This Row],[Stock]]),"0",H28) -> 213 | H28: 213
A29: PROD27 | B29: Decorative Floor Vase | C29: Home | D29: Khan, Jones and Paul | E29: =IF(ISBLANK(Table3[[#This Row],[Cost2]]),"Not Found",F29) -> Not Found | G29: =IF(ISBLANK(Table3[[#This Row],[Stock]]),"0",H29) -> 378 | H29: 378
A30: PROD28 | B30: Sports Stopwatch Timer | C30: Sports | D30: Burns-Hansen | E30: =IF(ISBLANK(Table3[[#This Row],[Cost2]]),"Not Found",F30) -> 38.76 | F30: 38.76 | G30: =IF(ISBLANK(Table3[[#This Row],[Stock]]),"0",H30) -> 137 | H30: 137
A31: PROD29 | B31: Fabric Sofa Throw Blanket | C31: Home | D31: Hoffman Group | E31: =IF(ISBLANK(Table3[[#This Row],[Cost2]]),"Not Found",F31) -> 218.48 | F31: 218.48 | G31: =IF(ISBLANK(Table3[[#This Row],[Stock]]),"0",H31) -> 276 | H31: 276
A32: PROD30 | B32: Stainless Steel Cutlery Set | C32: Home | D32: Stevens, Fernandez and Martin | E32: =IF(ISBLANK(Table3[[#This Row],[Cost2]]),"Not Found",F32) -> 19.52 | F32: 19.52 | G32: =IF(ISBLANK(Table3[[#This Row],[Stock]]),"0",H32) -> 57 | H32: 57
A33: PROD31 | B33: Basketball | C33: Sports | D33: Nolan-Snow | E33: =IF(ISBLANK(Table3[[#This Row],[Cost2]]),"Not Found",F33) -> 204.39 | F33: 204.39 | G33: =IF(ISBLANK(Table3[[#This Row],[Stock]]),"0",H33) -> 281 | H33: 281
A34: PROD32 | B34: Vitamin C Face Serum | C34: Beauty | D34: Griffin Ltd | E34: =IF(ISBLANK(Table3[[#This Row],[Cost2]]),"Not Found",F34) -> 283.83 | F34: 283.83 | G34: =IF(ISBLANK(Table3[[#This Row],[Stock]]),"0",H34) -> 244 | H34: 244
A35: PROD33 | B35: Modern Wall Clock | C35: Home | D35: Weiss-Watson | E35: =IF(ISBLANK(Table3[[#This Row],[Cost2]]),"Not Found",F35) -> 179.77 | F35: 179.77 | G35: =IF(ISBLANK(Table3[[#This Row],[Stock]]),"0",H35) -> 305 | H35: 305
A36: PROD34 | B36: Gaming Mechanical Keyboard | C36: Electronics | D36: Lucero LLC | E36: =IF(ISBLANK(Table3[[#This Row],[Cost2]]),"Not Found",F36) -> 419.28 | F36: 419.28 | G36: =IF(ISBLANK(Table3[[#This Row],[Stock]]),"0",H36) -> 86 | H36: 86
A37: PROD35 | B37: Bedroom Table Lamp | C37: Home | D37: Jones LLC | E37: =IF(ISBLANK(Table3[[#This Row],[Cost2]]),"Not Found",F37) -> 382.22 | F37: 382.22 | G37: =IF(ISBLANK(Table3[[#This Row],[Stock]]),"0",H37) -> 329 | H37: 329
A38: PROD36 | B38: Women's Summer Dress | C38: Clothing | D38: Smith-Mills | E38: =IF(ISBLANK(Table3[[#This Row],[Cost2]]),"Not Found",F38) -> 223.43 | F38: 223.43 | G38: =IF(ISBLANK(Table3[[#This Row],[Stock]]),"0",H38) -> 154 | H38: 154
A39: PROD37 | B39: Men's Casual Sneakers | C39: Clothing | D39: Hogan-Lee | E39: =IF(ISBLANK(Table3[[#This Row],[Cost2]]),"Not Found",F39) -> 353.47 | F39: 353.47 | G39: =IF(ISBLANK(Table3[[#This Row],[Stock]]),"0",H39) -> 214 | H39: 214
A40: PROD38 | B40: Sports Water Hydration Pack | C40: Sports | D40: Sims-Smith | E40: =IF(ISBLANK(Table3[[#This Row],[Cost2]]),"Not Found",F40) -> 135.61 | F40: 135.61 | G40: =IF(ISBLANK(Table3[[#This Row],[Stock]]),"0",H40) -> 394 | H40: 394
A41: PROD39 | B41: Portable Power Bank | C41: Electronics | D41: Cummings and Sons | E41: =IF(ISBLANK(Table3[[#This Row],[Cost2]]),"Not Found",F41) -> 326.06 | F41: 326.06 | G41: =IF(ISBLANK(Table3[[#This Row],[Stock]]),"0",H41) -> 301 | H41: 301
... A48: PROD46 | B48: Men's Winter Jacket | C48: Clothing | D48: Kelly, Smith and Perez | E48: =IF(ISBLANK(Table3[[#This Row],[Cost2]]),"Not Found",F48) -> 167.34 | F48: 167.34 | G48: =IF(ISBLANK(Table3[[#This Row],[Stock]]),"0",H48) -> 296 | H48: 296
A49: PROD47 | B49: Makeup Brush Set | C49: Beauty | D49: Cook Inc | E49: =IF(ISBLANK(Table3[[#This Row],[Cost2]]),"Not Found",F49) -> Not Found | G49: =IF(ISBLANK(Table3[[#This Row],[Stock]]),"0",H49) -> 431 | H49: 431
A50: PROD48 | B50: Car Dashboard Phone Holder | C50: Electronics | D50: Byrd, Stewart and Valdez | E50: =IF(ISBLANK(Table3[[#This Row],[Cost2]]),"Not Found",F50) -> 177.98 | F50: 177.98 | G50: =IF(ISBLANK(Table3[[#This Row],[Stock]]),"0",H50) -> 103 | H50: 103
A51: PROD49 | B51: Men's Roll-On Perfume | C51: Beauty | D51: Sullivan and Sons | E51: =IF(ISBLANK(Table3[[#This Row],[Cost2]]),"Not Found",F51) -> 43.29 | F51: 43.29 | G51: =IF(ISBLANK(Table3[[#This Row],[Stock]]),"0",H51) -> 267 | H51: 267
A52: PROD50 | B52: Boxing Hand Wraps | C52: Sports | D52: Smith-King | E52: =IF(ISBLANK(Table3[[#This Row],[Cost2]]),"Not Found",F52) -> 190.29 | F52: 190.29 | G52: =IF(ISBLANK(Table3[[#This Row],[Stock]]),"0",H52) -> 260 | H52: 260
A53: PROD51 | B53: HDMI Cable – 2m | C53: Electronics | D53: Bautista, Green and Hale | E53: =IF(ISBLANK(Table3[[#This Row],[Cost2]]),"Not Found",F53) -> 88.49 | F53: 88.49 | G53: =IF(ISBLANK(Table3[[#This Row],[Stock]]),"0",H53) -> 246 | H53: 246
A54: PROD52 | B54: Rugby Ball | C54: Sports | D54: Harris Inc | E54: =IF(ISBLANK(Table3[[#This Row],[Cost2]]),"Not Found",F54) -> 212.26 | F54: 212.26 | G54: =IF(ISBLANK(Table3[[#This Row],[Stock]]),"0",H54) -> 82 | H54: 82
A55: PROD53 | B55: Men's Track Pants | C55: Clothing | D55: Hamilton, Woods and Walker | E55: =IF(ISBLANK(Table3[[#This Row],[Cost2]]),"Not Found",F55) -> 386.56 | F55: 386.56 | G55: =IF(ISBLANK(Table3[[#This Row],[Stock]]),"0",H55) -> 125 | H55: 125
A56: PROD54 | B56: Sports Stopwatch Pro | C56: Sports | D56: Thompson-French | E56: =IF(ISBLANK(Table3[[#This Row],[Cost2]]),"Not Found",F56) -> 434.84 | F56: 434.84 | G56: =IF(ISBLANK(Table3[[#This Row],[Stock]]),"0",H56) -> 185 | H56: 185
A57: PROD55 | B57: Ceramic Plant Pot | C57: Home | D57: Hatfield, Baird and Torres | E57: =IF(ISBLANK(Table3[[#This Row],[Cost2]]),"Not Found",F57) -> 81.75 | F57: 81.75 | G57: =IF(ISBLANK(Table3[[#This Row],[Stock]]),"0",H57) -> 0
A58: PROD56 | B58: Premium Blanket Throw | C58: Home | D58: Hernandez, Kennedy and Porter | E58: =IF(ISBLANK(Table3[[#This Row],[Cost2]]),"Not Found",F58) -> 461.47 | F58: 461.47 | G58: =IF(ISBLANK(Table3[[#This Row],[Stock]]),"0",H58) -> 190 | H58: 190
A59: PROD57 | B59: Foam Roller | C59: Sports | D59: Atkinson, Camacho and Oliver | E59: =IF(ISBLANK(Table3[[#This Row],[Cost2]]),"Not Found",F59) -> 30.62 | F59: 30.62 | G59: =IF(ISBLANK(Table3[[#This Row],[Stock]]),"0",H59) -> 138 | H59: 138
A60: PROD58 | B60: Womens Cotton Scarf | C60: Clothing | D60: Shepherd-Gould | E60: =IF(ISBLANK(Table3[[#This Row],[Cost2]]),"Not Found",F60) -> 113.83 | F60: 113.83 | G60: =IF(ISBLANK(Table3[[#This Row],[Stock]]),"0",H60) -> 485 | H60: 485
A61: PROD59 | B61: Men's Hair Styling Gel | C61: Beauty | D61: Cline-Mccarthy | E61: =IF(ISBLANK(Table3[[#This Row],[Cost2]]),"Not Found",F61) -> 17.31 | F61: 17.31 | G61: =IF(ISBLANK(Table3[[#This Row],[Stock]]),"0",H61) -> 399 | H61: 399
A62: PROD60 | B62: Luxury Perfume Spray | C62: Beauty | D62: Gibson, Green and Lopez | E62: =IF(ISBLANK(Table3[[#This Row],[Cost2]]),"Not Found",F62) -> 482.75 | F62: 482.75 | G62: =IF(ISBLANK(Table3[[#This Row],[Stock]]),"0",H62) -> 444 | H62: 444
A63: PROD61 | B63: Tennis Ball 3-Pack | C63: Sports | D63: Lopez LLC | E63: =IF(ISBLANK(Table3[[#This Row],[Cost2]]),"Not Found",F63) -> 103.45 | F63: 103.45 | G63: =IF(ISBLANK(Table3[[#This Row],[Stock]]),"0",H63) -> 465 | H63: 465
A64: PROD62 | B64: Laptop Cooling Pad | C64: Electronics | D64: Murray, Gould and Ware | E64: =IF(ISBLANK(Table3[[#This Row],[Cost2]]),"Not Found",F64) -> 86.42 | F64: 86.42 | G64: =IF(ISBLANK(Table3[[#This Row],[Stock]]),"0",H64) -> 222 | H64: 222
A65: PROD63 | B65: Organic Sunscreen Lotion | C65: Beauty | D65: Anderson-Riley | E65: =IF(ISBLANK(Table3[[#This Row],[Cost2]]),"Not Found",F65) -> 266.86 | F65: 266.86 | G65: =IF(ISBLANK(Table3[[#This Row],[Stock]]),"0",H65) -> 458 | H65: 458
A66: PROD64 | B66: Matte Lipstick Set | C66: Beauty | D66: Zhang Inc | E66: =IF(ISBLANK(Table3[[#This Row],[Cost2]]),"Not Found",F66) -> 299.11 | F66: 299.11 | G66: =IF(ISBLANK(Table3[[#This Row],[Stock]]),"0",H66) -> 118 | H66: 118
A67: PROD65 | B67: Adjustable Dumbbells 20kg | C67: Sports | D67: Montgomery, Benton and Miller | E67: =IF(ISBLANK(Table3[[#This Row],[Cost2]]),"Not Found",F67) -> 240.63 | F67: 240.63 | G67: =IF(ISBLANK(Table3[[#This Row],[Stock]]),"0",H67) -> 423 | H67: 423
A68: PROD66 | B68: Women's Hair Dryer Brush | C68: Beauty | D68: Torres, Spencer and Potter | E68: =IF(ISBLANK(Table3[[#This Row],[Cost2]]),"Not Found",F68) -> 340.39 | F68: 340.39 | G68: =IF(ISBLANK(Table3[[#This Row],[Stock]]),"0",H68) -> 177 | H68: 177
A69: PROD67 | B69: Smart LED Light Strip | C69: Electronics | D69: Flores-Davis | E69: =IF(ISBLANK(Table3[[#This Row],[Cost2]]),"Not Found",F69) -> 349.17 | F69: 349.17 | G69: =IF(ISBLANK(Table3[[#This Row],[Stock]]),"0",H69) -> 476 | H69: 476
... A84: PROD82 | B84: Fitness Resistance Bands | C84: Sports | D84: Reese-Watson | E84: =IF(ISBLANK(Table3[[#This Row],[Cost2]]),"Not Found",F84) -> 152.92 | F84: 152.92 | G84: =IF(ISBLANK(Table3[[#This Row],[Stock]]),"0",H84) -> 281 | H84: 281
A85: PROD83 | B85: Hydrating Face Cleanser | C85: Beauty | D85: Butler Group | E85: =IF(ISBLANK(Table3[[#This Row],[Cost2]]),"Not Found",F85) -> Not Found | G85: =IF(ISBLANK(Table3[[#This Row],[Stock]]),"0",H85) -> 159 | H85: 159
A86: PROD84 | B86: Wooden Bookshelf | C86: Home | D86: Collins-Stephenson | E86: =IF(ISBLANK(Table3[[#This Row],[Cost2]]),"Not Found",F86) -> 388.46 | F86: 388.46 | G86: =IF(ISBLANK(Table3[[#This Row],[Stock]]),"0",H86) -> 208 | H86: 208
A87: PROD85 | B87: Women's Beanie Hat | C87: Clothing | D87: Richardson-Carrillo | E87: =IF(ISBLANK(Table3[[#This Row],[Cost2]]),"Not Found",F87) -> 119.57 | F87: 119.57 | G87: =IF(ISBLANK(Table3[[#This Row],[Stock]]),"0",H87) -> 210 | H87: 210
A88: PROD86 | B88: Kitchen Cutting Board | C88: Home | D88: Taylor, Dodson and Johnston | E88: =IF(ISBLANK(Table3[[#This Row],[Cost2]]),"Not Found",F88) -> 176.07 | F88: 176.07 | G88: =IF(ISBLANK(Table3[[#This Row],[Stock]]),"0",H88) -> 82 | H88: 82
A89: PROD87 | B89: LED Bedside Lamp | C89: Home | D89: Aguilar, Horton and Lewis | E89: =IF(ISBLANK(Table3[[#This Row],[Cost2]]),"Not Found",F89) -> 371.38 | F89: 371.38 | G89: =IF(ISBLANK(Table3[[#This Row],[Stock]]),"0",H89) -> 220 | H89: 220
A90: PROD88 | B90: Sports Wrist Sweatbands | C90: Sports | D90: Olsen-Daniels | E90: =IF(ISBLANK(Table3[[#This Row],[Cost2]]),"Not Found",F90) -> 131.24 | F90: 131.24 | G90: =IF(ISBLANK(Table3[[#This Row],[Stock]]),"0",H90) -> 232 | H90: 232
A91: PROD89 | B91: Face Foundation Kit | C91: Beauty | D91: Taylor-Elliott | E91: =IF(ISBLANK(Table3[[#This Row],[Cost2]]),"Not Found",F91) -> 183.04 | F91: 183.04 | G91: =IF(ISBLANK(Table3[[#This Row],[Stock]]),"0",H91) -> 457 | H91: 457
A92: PROD90 | B92: Gaming Mouse Pad XL | C92: Electronics | D92: Sharp, Taylor and Rodriguez | E92: =IF(ISBLANK(Table3[[#This Row],[Cost2]]),"Not Found",F92) -> 340.14 | F92: 340.14 | G92: =IF(ISBLANK(Table3[[#This Row],[Stock]]),"0",H92) -> 361 | H92: 361
A93: PROD91 | B93: Women's High Heels | C93: Clothing | D93: Smith-Charles | E93: =IF(ISBLANK(Table3[[#This Row],[Cost2]]),"Not Found",F93) -> 438.25 | F93: 438.25 | G93: =IF(ISBLANK(Table3[[#This Row],[Stock]]),"0",H93) -> 496 | H93: 496
A94: PROD92 | B94: Microwave Oven | C94: Home | D94: Green, Powell and Palmer | E94: =IF(ISBLANK(Table3[[#This Row],[Cost2]]),"Not Found",F94) -> 447.43 | F94: 447.43 | G94: =IF(ISBLANK(Table3[[#This Row],[Stock]]),"0",H94) -> 191 | H94: 191
A95: PROD93 | B95: USB-C Laptop Charger | C95: Electronics | D95: Martin LLC | E95: =IF(ISBLANK(Table3[[#This Row],[Cost2]]),"Not Found",F95) -> 377.52 | F95: 377.52 | G95: =IF(ISBLANK(Table3[[#This Row],[Stock]]),"0",H95) -> 485 | H95: 485
A96: PROD94 | B96: Vitamin E Body Lotion | C96: Beauty | D96: Hoffman-Williams | E96: =IF(ISBLANK(Table3[[#This Row],[Cost2]]),"Not Found",F96) -> 358.47 | F96: 358.47 | G96: =IF(ISBLANK(Table3[[#This Row],[Stock]]),"0",H96) -> 213 | H96: 213
A97: PROD95 | B97: Sports Stopwatch Basic | C97: Sports | D97: Wilson Group | E97: =IF(ISBLANK(Table3[[#This Row],[Cost2]]),"Not Found",F97) -> 60.65 | F97: 60.65 | G97: =IF(ISBLANK(Table3[[#This Row],[Stock]]),"0",H97) -> 75 | H97: 75
... A101: PROD99 | B101: Stainless Steel Cookware Set | C101: Home | D101: Campbell Ltd | E101: =IF(ISBLANK(Table3[[#This Row],[Cost2]]),"Not Found",F101) -> 201.41 | F101: 201.41 | G101: =IF(ISBLANK(Table3[[#This Row],[Stock]]),"0",H101) -> 146 | H101: 146

Sheet clean product final
A1: Product_ID | B1: Product_Name | C1: Category | D1: Brand | E1: Cost | F1: Stock
A2: PROD0 | B2: Brother Laser Printer | C2: Electronics | D2: Hunt Inc | E2: 112.42 | F2: 416
A3: PROD1 | B3: Men's Graphic T-Shirt | C3: Clothing | D3: Terry-Moore | E3: 342.56 | F3: 181
A4: PROD2 | B4: Women's Casual Hoodie | C4: Clothing | D4: Sims Inc | E4: Not Found | F4: 352
A5: PROD3 | B5: Men's Running Jacket | C5: Clothing | D5: Pineda Ltd | E5: 364.67 | F5: 452
A6: PROD4 | B6: Women's Yoga Pants | C6: Clothing | D6: Gonzales-Davis | E6: 306.46 | F6: 487
A7: PROD5 | B7: Men's Leather Belt | C7: Clothing | D7: Baldwin, Garza and Gonzalez | E7: 261 | F7: 59
A8: PROD6 | B8: Herbal Face Moisturizer | C8: Beauty | D8: Davidson PLC | E8: 312.8 | F8: 350
A9: PROD7 | B9: LED Table Lamp | C9: Home | D9: Harrell LLC | E9: 218.86 | F9: 170
A10: PROD8 | B10: Wireless Bluetooth Earbuds | C10: Electronics | D10: Perez-Johnston | E10: 439.07 | F10: 142
A11: PROD9 | B11: Adjustable Dumbbell Set | C11: Sports | D11: Hill PLC | E11: 495.72 | F11: 323
A12: PROD10 | B12: Ceramic Kitchen Bowl Set | C12: Home | D12: Hamilton Group | E12: 298.86 | F12: 308
A13: PROD11 | B13: HD Smart TV Stick | C13: Electronics | D13: Gibson, Hobbs and Weaver | E13: 449.4 | F13: 0
A14: PROD12 | B14: Hair Strengthening Shampoo | C14: Beauty | D14: Rice LLC | E14: 115.82 | F14: 460
A15: PROD13 | B15: USB-C Fast Charger | C15: Electronics | D15: Dawson-Perkins | E15: 242.23 | F15: 453
A16: PROD14 | B16: Decorative Wall Mirror | C16: Home | D16: Luna, Anderson and Bowman | E16: 48.01 | F16: 439
... A19: PROD17 | B19: Soccer Training Cone Set | C19: Sports | D19: Ford, Murphy and Wilson | E19: 144.53 | F19: 367
A20: PROD18 | B20: Women's Denim Jeans | C20: Clothing | D20: Guerra-Hendrix | E20: Not Found | F20: 343
A21: PROD19 | B21: Knee Support Brace | C21: Sports | D21: May-Reese | E21: 21.34 | F21: 65
A22: PROD20 | B22: Outdoor Sports Water Bottle | C22: Sports | D22: Soto-Ellis | E22: 131.51 | F22: 0
A23: PROD21 | B23: Multi-Purpose Storage Box | C23: Home | D23: Gardner-Montes | E23: 123.46 | F23: 76
A24: PROD22 | B24: Carbon Fiber Tennis Racket | C24: Sports | D24: Flores, Pineda and Rodriguez | E24: 484.62 | F24: 432
A25: PROD23 | B25: Men's Formal Shirt | C25: Clothing | D25: Moon, Mora and Santos | E25: 242.965 | F25: 360
A26: PROD24 | B26: Foldable Camping Chair | C26: Sports | D26: Cook Ltd | E26: 166.06 | F26: 340
A27: PROD25 | B27: Women's Scarf Set | C27: Clothing | D27: Brown and Sons | E27: 174.02 | F27: 268
A28: PROD26 | B28: Wireless Bluetooth Speaker | C28: Electronics | D28: Reed-Schmidt | E28: 322.41 | F28: 213
A29: PROD27 | B29: Decorative Floor Vase | C29: Home | D29: Khan, Jones and Paul | E29: Not Found | F29: 378
A30: PROD28 | B30: Sports Stopwatch Timer | C30: Sports | D30: Burns-Hansen | E30: 38.76 | F30: 137
A31: PROD29 | B31: Fabric Sofa Throw Blanket | C31: Home | D31: Hoffman Group | E31: 218.48 | F31: 276
A32: PROD30 | B32: Stainless Steel Cutlery Set | C32: Home | D32: Stevens, Fernandez and Martin | E32: 19.52 | F32: 57
A33: PROD31 | B33: Basketball | C33: Sports | D33: Nolan-Snow | E33: 204.39 | F33: 281
A34: PROD32 | B34: Vitamin C Face Serum | C34: Beauty | D34: Griffin Ltd | E34: 283.83 | F34: 244
A35: PROD33 | B35: Modern Wall Clock | C35: Home | D35: Weiss-Watson | E35: 179.77 | F35: 305
A36: PROD34 | B36: Gaming Mechanical Keyboard | C36: Electronics | D36: Lucero LLC | E36: 419.28 | F36: 86
A37: PROD35 | B37: Bedroom Table Lamp | C37: Home | D37: Jones LLC | E37: 382.22 | F37: 329
A38: PROD36 | B38: Women's Summer Dress | C38: Clothing | D38: Smith-Mills | E38: 223.43 | F38: 154
A39: PROD37 | B39: Men's Casual Sneakers | C39: Clothing | D39: Hogan-Lee | E39: 353.47 | F39: 214
A40: PROD38 | B40: Sports Water Hydration Pack | C40: Sports | D40: Sims-Smith | E40: 135.61 | F40: 394
A41: PROD39 | B41: Portable Power Bank | C41: Electronics | D41: Cummings and Sons | E41: 326.06 | F41: 301
... A48: PROD46 | B48: Men's Winter Jacket | C48: Clothing | D48: Kelly, Smith and Perez | E48: 167.34 | F48: 296
A49: PROD47 | B49: Makeup Brush Set | C49: Beauty | D49: Cook Inc | E49: Not Found | F49: 431
A50: PROD48 | B50: Car Dashboard Phone Holder | C50: Electronics | D50: Byrd, Stewart and Valdez | E50: 177.98 | F50: 103
A51: PROD49 | B51: Men's Roll-On Perfume | C51: Beauty | D51: Sullivan and Sons | E51: 43.29 | F51: 267
A52: PROD50 | B52: Boxing Hand Wraps | C52: Sports | D52: Smith-King | E52: 190.29 | F52: 260
A53: PROD51 | B53: HDMI Cable – 2m | C53: Electronics | D53: Bautista, Green and Hale | E53: 88.49 | F53: 246
A54: PROD52 | B54: Rugby Ball | C54: Sports | D54: Harris Inc | E54: 212.26 | F54: 82
A55: PROD53 | B55: Men's Track Pants | C55: Clothing | D55: Hamilton, Woods and Walker | E55: 386.56 | F55: 125
A56: PROD54 | B56: Sports Stopwatch Pro | C56: Sports | D56: Thompson-French | E56: 434.84 | F56: 185
A57: PROD55 | B57: Ceramic Plant Pot | C57: Home | D57: Hatfield, Baird and Torres | E57: 81.75 | F57: 0
A58: PROD56 | B58: Premium Blanket Throw | C58: Home | D58: Hernandez, Kennedy and Porter | E58: 461.47 | F58: 190
A59: PROD57 | B59: Foam Roller | C59: Sports | D59: Atkinson, Camacho and Oliver | E59: 30.62 | F59: 138
A60: PROD58 | B60: Womens Cotton Scarf | C60: Clothing | D60: Shepherd-Gould | E60: 113.83 | F60: 485
A61: PROD59 | B61: Men's Hair Styling Gel | C61: Beauty | D61: Cline-Mccarthy | E61: 17.31 | F61: 399
... A84: PROD82 | B84: Fitness Resistance Bands | C84: Sports | D84: Reese-Watson | E84: 152.92 | F84: 281
A85: PROD83 | B85: Hydrating Face Cleanser | C85: Beauty | D85: Butler Group | E85: Not Found | F85: 159
A86: PROD84 | B86: Wooden Bookshelf | C86: Home | D86: Collins-Stephenson | E86: 388.46 | F86: 208
A87: PROD85 | B87: Women's Beanie Hat | C87: Clothing | D87: Richardson-Carrillo | E87: 119.57 | F87: 210
A88: PROD86 | B88: Kitchen Cutting Board | C88: Home | D88: Taylor, Dodson and Johnston | E88: 176.07 | F88: 82
A89: PROD87 | B89: LED Bedside Lamp | C89: Home | D89: Aguilar, Horton and Lewis | E89: 371.38 | F89: 220
A90: PROD88 | B90: Sports Wrist Sweatbands | C90: Sports | D90: Olsen-Daniels | E90: 131.24 | F90: 232
A91: PROD89 | B91: Face Foundation Kit | C91: Beauty | D91: Taylor-Elliott | E91: 183.04 | F91: 457
A92: PROD90 | B92: Gaming Mouse Pad XL | C92: Electronics | D92: Sharp, Taylor and Rodriguez | E92: 340.14 | F92: 361
A93: PROD91 | B93: Women's High Heels | C93: Clothing | D93: Smith-Charles | E93: 438.25 | F93: 496
A94: PROD92 | B94: Microwave Oven | C94: Home | D94: Green, Powell and Palmer | E94: 447.43 | F94: 191
A95: PROD93 | B95: USB-C Laptop Charger | C95: Electronics | D95: Martin LLC | E95: 377.52 | F95: 485
A96: PROD94 | B96: Vitamin E Body Lotion | C96: Beauty | D96: Hoffman-Williams | E96: 358.47 | F96: 213
A97: PROD95 | B97: Sports Stopwatch Basic | C97: Sports | D97: Wilson Group | E97: 60.65 | F97: 75
... A101: PROD99 | B101: Stainless Steel Cookware Set | C101: Home | D101: Campbell Ltd | E101: 201.41 | F101: 146

Sheet Clean Store_Dim (2)
A1: Store_ID | B1: Store_Name | C1: Region | D1: City | E1: Store_Type
A2: STORE0 | B2: Rivera-Warner | C2: East | D2: Washingtonfurt | E2: Flagship
A3: STORE1 | B3: Martinez, Adkins and Johnson | C3: North | D3: Danielmouth | E3: Flagship
A4: STORE2 | B4: Black-Horn | C4: South | D4: North Nancyview | E4: Outlet
A5: STORE3 | B5: Johnson-Wright | C5: North | D5: Hoodberg | E5: Outlet
A6: STORE4 | B6: Alexander Group | C6: South | D6: Port Sharon | E6: Online
A7: STORE5 | B7: Gray Ltd | C7: North | D7: New Michaelchester | E7: Outlet
A8: STORE6 | B8: Benson-Elliott | C8: East | D8: Port Josephberg | E8: Online
A9: STORE7 | B9: Martinez-Mullins | C9: South | D9: Williamsfurt | E9: Online
A10: STORE8 | B10: Bean, Jones and Park | C10: West | D10: Thompsonborough | E10: Online
A11: STORE9 | B11: Moore, Padilla and Butler | C11: South | D11: East Johnstad | E11: Flagship
A12: STORE10 | B12: Hill, Wagner and Ballard | C12: East | D12: East Davidville | E12: Online
... A21: STORE19 | B21: Mann-Austin | C21: East | D21: Vasquezborough | E21: Online

Sheet Clean Sales_Fact (2)
A1: Sales_ID | B1: Order_Date | C1: Customer_ID | D1: Product_ID | E1: Store_ID | F1: Quantity | G1: Unit_Price | H1: Discount | I1: Payment_Type | J1: Total_Amount
A2: SALE0 | B2: 45480 | C2: CUST1409 | D2: PROD97 | E2: STORE3 | F2: 1 | G2: 218.04 | H2: 0.09 | I2: Credit Card | J2: 198.4164
A3: SALE1 | B3: 45285 | C3: CUST1467 | D3: PROD74 | E3: STORE17 | F3: 3 | G3: 104.47 | H3: 0.27 | I3: PayPal | J3: 228.7893
A4: SALE2 | B4: 45446 | C4: CUST1056 | D4: PROD49 | E4: STORE8 | F4: 4 | G4: 914.05 | H4: 0.25 | I4: Credit Card | J4: 2742.15
A5: SALE3 | B5: 45259 | C5: CUST1346 | D5: PROD76 | E5: STORE8 | F5: 1 | G5: 921.51 | H5: 0.16 | I5: COD | J5: 774.0684
A6: SALE4 | B6: 45297 | C6: CUST1493 | D6: PROD59 | E6: STORE5 | F6: 3 | G6: 745.3 | H6: 0.18 | I6: Credit Card | J6: 1833.438
A7: SALE5 | B7: 45499 | C7: CUST1116 | D7: PROD15 | E7: STORE7 | F7: 3 | G7: 147.01 | H7: 0.19 | I7: COD | J7: 357.2343
A8: SALE6 | B8: 45850 | C8: CUST1016 | D8: PROD56 | E8: STORE4 | F8: 2 | G8: 785.31 | H8: 0.15 | I8: PayPal | J8: 1335.027
A9: SALE7 | B9: 45248 | C9: CUST1152 | D9: PROD70 | E9: STORE8 | F9: 4 | G9: 342.39 | H9: 0.23 | I9: PayPal | J9: 1054.5612
A10: SALE8 | B10: 45781 | C10: CUST1187 | D10: PROD99 | E10: STORE5 | F10: =Table5[[#This Row],[Total_Amount]]/(G10*(1-Table5[[#This Row],[Discount]])) -> 3 | G10: 448.25 | H10: 0.07 | I10: PayPal | J10: 1250.6175
A11: SALE9 | B11: 45869 | C11: CUST1464 | D11: PROD33 | E11: STORE0 | F11: =Table5[[#This Row],[Total_Amount]]/(G11*(1-Table5[[#This Row],[Discount]])) -> 2 | G11: 873.17 | H11: 0.23 | I11: PayPal | J11: 1344.6818
A12: SALE10 | B12: 45335 | C12: CUST1065 | D12: PROD24 | E12: STORE14 | F12: =Table5[[#This Row],[Total_Amount]]/(G12*(1-Table5[[#This Row],[Discount]])) -> 1 | G12: 278.63 | H12: 0.07 | I12: Credit Card | J12: 259.1259
A13: SALE11 | B13: 45801 | C13: CUST1320 | D13: PROD39 | E13: STORE1 | F13: =Table5[[#This Row],[Total_Amount]]/(G13*(1-Table5[[#This Row],[Discount]])) -> 4 | G13: 286.92 | H13: 0.17 | I13: Credit Card | J13: 952.5744
A14: SALE12 | B14: 45528 | C14: CUST1237 | D14: PROD88 | E14: STORE4 | F14: =Table5[[#This Row],[Total_Amount]]/(G14*(1-Table5[[#This Row],[Discount]])) -> 4 | G14: 644.58 | H14: 0.01 | I14: Credit Card | J14: 2552.5368
A15: SALE13 | B15: 45875 | C15: CUST1443 | D15: PROD34 | E15: STORE16 | F15: =Table5[[#This Row],[Total_Amount]]/(G15*(1-Table5[[#This Row],[Discount]])) -> 2 | G15: 316.9 | H15: 0.3 | I15: PayPal | J15: 443.66
A16: SALE14 | B16: 45829 | C16: CUST1348 | D16: PROD24 | E16: STORE15 | F16: =Table5[[#This Row],[Total_Amount]]/(G16*(1-Table5[[#This Row],[Discount]])) -> 4 | G16: 403.47 | H16: 0.29 | I16: PayPal | J16: 1145.8548
A17: SALE15 | B17: 45636 | C17: CUST1435 | D17: PROD36 | E17: STORE9 | F17: =Table5[[#This Row],[Total_Amount]]/(G17*(1-Table5[[#This Row],[Discount]])) -> 3 | G17: 871.34 | H17: 0.04 | I17: COD | J17: 2509.4592
A18: SALE16 | B18: 45913 | C18: CUST1276 | D18: PROD65 | E18: STORE19 | F18: =Table5[[#This Row],[Total_Amount]]/(G18*(1-Table5[[#This Row],[Discount]])) -> 2 | G18: 451.98 | H18: 0.25 | I18: Credit Card | J18: 677.97
A19: SALE17 | B19: 45637 | C19: CUST1079 | D19: PROD27 | E19: STORE4 | F19: =Table5[[#This Row],[Total_Amount]]/(G19*(1-Table5[[#This Row],[Discount]])) -> 2 | G19: 502.69 | H19: 0.23 | I19: Credit Card | J19: 774.1426
A20: SALE18 | B20: 45517 | C20: CUST1094 | D20: PROD39 | E20: STORE4 | F20: =Table5[[#This Row],[Total_Amount]]/(G20*(1-Table5[[#This Row],[Discount]])) -> 2 | G20: 559.23 | H20: 0.25 | I20: COD | J20: 838.845
A21: SALE19 | B21: 45369 | C21: CUST1239 | D21: PROD60 | E21: STORE13 | F21: Uknown | G21: Unknown | H21: 0.04 | I21: COD | J21: 1782.4512
A22: SALE20 | B22: 45843 | C22: CUST1144 | D22: PROD72 | E22: STORE17 | F22: =Table5[[#This Row],[Total_Amount]]/(G22*(1-Table5[[#This Row],[Discount]])) -> 3 | G22: 986.04 | H22: 0.27 | I22: COD | J22: 2159.4276
A23: SALE21 | B23: 45447 | C23: CUST1396 | D23: PROD43 | E23: STORE18 | F23: =Table5[[#This Row],[Total_Amount]]/(G23*(1-Table5[[#This Row],[Discount]])) -> 1 | G23: 589.56 | H23: 0.22 | I23: Credit Card | J23: 459.8568
A24: SALE22 | B24: 45394 | C24: CUST1476 | D24: PROD69 | E24: STORE10 | F24: =Table5[[#This Row],[Total_Amount]]/(G24*(1-Table5[[#This Row],[Discount]])) -> 3 | G24: 979.42 | H24: 0.03 | I24: PayPal | J24: 2850.1122
A25: SALE23 | B25: 45466 | C25: CUST1368 | D25: PROD12 | E25: STORE8 | F25: =Table5[[#This Row],[Total_Amount]]/(G25*(1-Table5[[#This Row],[Discount]])) -> 1 | G25: 719.28 | H25: 0.08 | I25: Credit Card | J25: 661.7376
A26: SALE24 | B26: 45908 | C26: CUST1186 | D26: PROD67 | E26: STORE6 | F26: =Table5[[#This Row],[Total_Amount]]/(G26*(1-Table5[[#This Row],[Discount]])) -> 3 | G26: 77.6 | H26: 0.07 | I26: Credit Card | J26: 216.504
A27: SALE25 | B27: 45552 | C27: CUST1381 | D27: PROD5 | E27: STORE3 | F27: =Table5[[#This Row],[Total_Amount]]/(G27*(1-Table5[[#This Row],[Discount]])) -> 4 | G27: 852.71 | H27: 0.14 | I27: PayPal | J27: 2933.3224
A28: SALE26 | B28: 45294 | C28: CUST1213 | D28: PROD98 | E28: STORE8 | F28: Uknown | G28: 156.16 | H28: Unknown | I28: Credit Card | J28: 599.6544
A29: SALE27 | B29: 45710 | C29: CUST1200 | D29: PROD77 | E29: STORE8 | F29: =Table5[[#This Row],[Total_Amount]]/(G29*(1-Table5[[#This Row],[Discount]])) -> 3 | G29: 815.49 | H29: 0.17 | I29: Credit Card | J29: 2030.5701
A30: SALE28 | B30: 45923 | C30: CUST1148 | D30: PROD13 | E30: STORE2 | F30: =Table5[[#This Row],[Total_Amount]]/(G30*(1-Table5[[#This Row],[Discount]])) -> 2 | G30: 74.21 | H30: 0.11 | I30: PayPal | J30: 132.0938
A31: SALE29 | B31: 45302 | C31: CUST1348 | D31: PROD99 | E31: STORE3 | F31: =Table5[[#This Row],[Total_Amount]]/(G31*(1-Table5[[#This Row],[Discount]])) -> 4 | G31: 451.67 | H31: 0.15 | I31: Credit Card | J31: 1535.678
A32: SALE30 | B32: 45217 | C32: CUST1028 | D32: PROD5 | E32: STORE19 | F32: =Table5[[#This Row],[Total_Amount]]/(G32*(1-Table5[[#This Row],[Discount]])) -> 1 | G32: 429.38 | H32: 0.13 | I32: PayPal | J32: 373.5606
A33: SALE31 | B33: 45593 | C33: CUST1412 | D33: PROD53 | E33: STORE12 | F33: =Table5[[#This Row],[Total_Amount]]/(G33*(1-Table5[[#This Row],[Discount]])) -> 2 | G33: 148.96 | H33: 0.03 | I33: COD | J33: 288.9824
A34: SALE32 | B34: 45597 | C34: CUST1398 | D34: PROD75 | E34: STORE8 | F34: =Table5[[#This Row],[Total_Amount]]/(G34*(1-Table5[[#This Row],[Discount]])) -> 4 | G34: 313.83 | H34: 0.08 | I34: Credit Card | J34: 1154.8944
A35: SALE33 | B35: 45620 | C35: CUST1453 | D35: PROD12 | E35: STORE6 | F35: =Table5[[#This Row],[Total_Amount]]/(G35*(1-Table5[[#This Row],[Discount]])) -> 2 | G35: 717.31 | H35: 0.15 | I35: Credit Card | J35: 1219.427
A36: SALE34 | B36: 45215 | C36: CUST1344 | D36: PROD79 | E36: STORE1 | F36: =Table5[[#This Row],[Total_Amount]]/(G36*(1-Table5[[#This Row],[Discount]])) -> 3 | G36: 873.22 | H36: 0.18 | I36: Credit Card | J36: 2148.1212
A37: SALE35 | B37: 45878 | C37: CUST1218 | D37: PROD16 | E37: STORE3 | F37: =Table5[[#This Row],[Total_Amount]]/(G37*(1-Table5[[#This Row],[Discount]])) -> 4 | G37: 109.36 | H37: 0.19 | I37: COD | J37: 354.3264
A38: SALE36 | B38: 45635 | C38: CUST1086 | D38: PROD5 | E38: STORE7 | F38: =Table5[[#This Row],[Total_Amount]]/(G38*(1-Table5[[#This Row],[Discount]])) -> 3 | G38: 559.52 | H38: 0.16 | I38: PayPal | J38: 1409.9904
A39: SALE37 | B39: 45329 | C39: CUST1492 | D39: PROD10 | E39: STORE17 | F39: =Table5[[#This Row],[Total_Amount]]/(G39*(1-Table5[[#This Row],[Discount]])) -> 3 | G39: 121.76 | H39: 0.27 | I39: PayPal | J39: 266.6544
A40: SALE38 | B40: 45378 | C40: CUST1189 | D40: PROD33 | E40: STORE13 | F40: =Table5[[#This Row],[Total_Amount]]/(G40*(1-Table5[[#This Row],[Discount]])) -> 4 | G40: 735.32 | H40: 0.06 | I40: COD | J40: 2764.8032
... A53: SALE51 | B53: 45689 | C53: CUST1142 | D53: PROD69 | E53: STORE7 | F53: =Table5[[#This Row],[Total_Amount]]/(G53*(1-Table5[[#This Row],[Discount]])) -> 3 | G53: 76.57 | H53: 0.26 | I53: Credit Card | J53: 169.9854
A54: SALE52 | B54: 45894 | C54: CUST1148 | D54: PROD89 | E54: STORE6 | F54: Uknown | G54: Unknown | H54: Unknown | I54: Credit Card | J54: 486.0633
A55: SALE53 | B55: 45677 | C55: CUST1324 | D55: PROD20 | E55: STORE8 | F55: =Table5[[#This Row],[Total_Amount]]/(G55*(1-Table5[[#This Row],[Discount]])) -> 1 | G55: 900.35 | H55: 0.13 | I55: COD | J55: 783.3045
A56: SALE54 | B56: 45706 | C56: CUST1095 | D56: PROD40 | E56: STORE10 | F56: =Table5[[#This Row],[Total_Amount]]/(G56*(1-Table5[[#This Row],[Discount]])) -> 4 | G56: 428.09 | H56: 0.07 | I56: Credit Card | J56: 1592.4948
A57: SALE55 | B57: 45589 | C57: CUST1416 | D57: PROD49 | E57: STORE11 | F57: =Table5[[#This Row],[Total_Amount]]/(G57*(1-Table5[[#This Row],[Discount]])) -> 2 | G57: 559.71 | H57: 0.3 | I57: COD | J57: 783.594
A58: SALE56 | B58: 45282 | C58: CUST1080 | D58: PROD34 | E58: STORE6 | F58: =Table5[[#This Row],[Total_Amount]]/(G58*(1-Table5[[#This Row],[Discount]])) -> 2 | G58: 833.7 | H58: 0.06 | I58: PayPal | J58: 1567.356
A59: SALE57 | B59: 45462 | C59: CUST1467 | D59: PROD47 | E59: STORE14 | F59: =Table5[[#This Row],[Total_Amount]]/(G59*(1-Table5[[#This Row],[Discount]])) -> 2 | G59: 680.16 | H59: 0.28 | I59: Credit Card | J59: 979.4304
A60: SALE58 | B60: 45633 | C60: CUST1404 | D60: PROD15 | E60: STORE7 | F60: Uknown | G60: 733.42 | H60: Unknown | I60: PayPal | J60: 2552.3016
A61: SALE59 | B61: 45257 | C61: CUST1367 | D61: PROD89 | E61: STORE11 | F61: =Table5[[#This Row],[Total_Amount]]/(G61*(1-Table5[[#This Row],[Discount]])) -> 1 | G61: 996.33 | H61: 0.23 | I61: PayPal | J61: 767.1741
A62: SALE60 | B62: 45854 | C62: CUST1408 | D62: PROD31 | E62: STORE10 | F62: =Table5[[#This Row],[Total_Amount]]/(G62*(1-Table5[[#This Row],[Discount]])) -> 1 | G62: 198.83 | H62: 0.09 | I62: COD | J62: 180.9353
A63: SALE61 | B63: 45716 | C63: CUST1239 | D63: PROD19 | E63: STORE7 | F63: =Table5[[#This Row],[Total_Amount]]/(G63*(1-Table5[[#This Row],[Discount]])) -> 1 | G63: 374.92 | H63: 0.18 | I63: PayPal | J63: 307.4344
A64: SALE62 | B64: 45515 | C64: CUST1464 | D64: PROD93 | E64: STORE16 | F64: =Table5[[#This Row],[Total_Amount]]/(G64*(1-Table5[[#This Row],[Discount]])) -> 1 | G64: 468.94 | H64: 0.12 | I64: Credit Card | J64: 412.6672
A65: SALE63 | B65: 45927 | C65: CUST1126 | D65: PROD89 | E65: STORE12 | F65: =Table5[[#This Row],[Total_Amount]]/(G65*(1-Table5[[#This Row],[Discount]])) -> 2 | G65: 121.37 | H65: 0.05 | I65: Credit Card | J65: 230.603
A66: SALE64 | B66: 45914 | C66: CUST1255 | D66: PROD53 | E66: STORE10 | F66: =Table5[[#This Row],[Total_Amount]]/(G66*(1-Table5[[#This Row],[Discount]])) -> 0 | G66: 480.06 | H66: 0.01 | I66: Credit Card
A67: SALE65 | B67: 45290 | C67: CUST1162 | D67: PROD99 | E67: STORE17 | F67: =Table5[[#This Row],[Total_Amount]]/(G67*(1-Table5[[#This Row],[Discount]])) -> 2 | G67: 856.57 | H67: 0.24 | I67: Credit Card | J67: 1301.9864
A68: SALE66 | B68: 45213 | C68: CUST1269 | D68: PROD77 | E68: STORE2 | F68: =Table5[[#This Row],[Total_Amount]]/(G68*(1-Table5[[#This Row],[Discount]])) -> 4 | G68: 814.25 | H68: 0.18 | I68: Credit Card | J68: 2670.74
A69: SALE67 | B69: 45255 | C69: CUST1483 | D69: PROD12 | E69: STORE2 | F69: =Table5[[#This Row],[Total_Amount]]/(G69*(1-Table5[[#This Row],[Discount]])) -> 1 | G69: 989.17 | H69: 0.2 | I69: PayPal | J69: 791.336
A70: SALE68 | B70: 45270 | C70: CUST1372 | D70: PROD72 | E70: STORE10 | F70: =Table5[[#This Row],[Total_Amount]]/(G70*(1-Table5[[#This Row],[Discount]])) -> 4 | G70: 62.48 | H70: 0.18 | I70: Credit Card | J70: 204.9344
A71: SALE69 | B71: 45897 | C71: CUST1423 | D71: PROD13 | E71: STORE16 | F71: =Table5[[#This Row],[Total_Amount]]/(G71*(1-Table5[[#This Row],[Discount]])) -> 4 | G71: 561.24 | H71: 0.24 | I71: Credit Card | J71: 1706.1696
A72: SALE70 | B72: 45849 | C72: CUST1058 | D72: PROD60 | E72: STORE5 | F72: =Table5[[#This Row],[Total_Amount]]/(G72*(1-Table5[[#This Row],[Discount]])) -> 0 | G72: 92.24 | H72: 0.28 | I72: COD
A73: SALE71 | B73: 45889 | C73: CUST1168 | D73: PROD72 | E73: STORE1 | F73: =Table5[[#This Row],[Total_Amount]]/(G73*(1-Table5[[#This Row],[Discount]])) -> 2 | G73: 668.3 | H73: 0.07 | I73: Credit Card | J73: 1243.038
A74: SALE72 | B74: 45533 | C74: CUST1409 | D74: PROD38 | E74: STORE5 | F74: =Table5[[#This Row],[Total_Amount]]/(G74*(1-Table5[[#This Row],[Discount]])) -> 1 | G74: 553.82 | H74: 0.09 | I74: Credit Card | J74: 503.9762
A75: SALE73 | B75: 45626 | C75: CUST1037 | D75: PROD45 | E75: STORE11 | F75: =Table5[[#This Row],[Total_Amount]]/(G75*(1-Table5[[#This Row],[Discount]])) -> 2 | G75: 556.43 | H75: 0.13 | I75: Credit Card | J75: 968.1882
A76: SALE74 | B76: 45942 | C76: CUST1273 | D76: PROD20 | E76: STORE8 | F76: =Table5[[#This Row],[Total_Amount]]/(G76*(1-Table5[[#This Row],[Discount]])) -> 1 | G76: 184.98 | H76: 0.1 | I76: COD | J76: 166.482
A77: SALE75 | B77: 45500 | C77: CUST1035 | D77: PROD97 | E77: STORE12 | F77: =Table5[[#This Row],[Total_Amount]]/(G77*(1-Table5[[#This Row],[Discount]])) -> 4 | G77: 700.18 | H77: 0.23 | I77: Credit Card | J77: 2156.5544
A78: SALE76 | B78: 45285 | C78: CUST1019 | D78: PROD76 | E78: STORE10 | F78: =Table5[[#This Row],[Total_Amount]]/(G78*(1-Table5[[#This Row],[Discount]])) -> 2 | G78: 686.31 | H78: 0.25 | I78: Credit Card | J78: 1029.465
A79: SALE77 | B79: 45800 | C79: CUST1007 | D79: PROD67 | E79: STORE15 | F79: =Table5[[#This Row],[Total_Amount]]/(G79*(1-Table5[[#This Row],[Discount]])) -> 1 | G79: 687.82 | H79: 0.27 | I79: COD | J79: 502.1086
A80: SALE78 | B80: 45609 | C80: CUST1221 | D80: PROD83 | E80: STORE8 | F80: =Table5[[#This Row],[Total_Amount]]/(G80*(1-Table5[[#This Row],[Discount]])) -> 2 | G80: 900.55 | H80: 0.16 | I80: Credit Card | J80: 1512.924
A81: SALE79 | B81: 45268 | C81: CUST1115 | D81: PROD21 | E81: STORE2 | F81: =Table5[[#This Row],[Total_Amount]]/(G81*(1-Table5[[#This Row],[Discount]])) -> 1 | G81: 341.17 | H81: 0.15 | I81: Credit Card | J81: 289.9945
A82: SALE80 | B82: 45885 | C82: CUST1176 | D82: PROD52 | E82: STORE8 | F82: =Table5[[#This Row],[Total_Amount]]/(G82*(1-Table5[[#This Row],[Discount]])) -> 1 | G82: 442.27 | H82: 0.06 | I82: COD | J82: 415.7338
A83: SALE81 | B83: 45616 | C83: CUST1253 | D83: PROD71 | E83: STORE9 | F83: =Table5[[#This Row],[Total_Amount]]/(G83*(1-Table5[[#This Row],[Discount]])) -> 1 | G83: 363.73 | H83: 0.25 | I83: PayPal | J83: 272.7975
A84: SALE82 | B84: 45518 | C84: CUST1378 | D84: PROD91 | E84: STORE17 | F84: =Table5[[#This Row],[Total_Amount]]/(G84*(1-Table5[[#This Row],[Discount]])) -> 2 | G84: 601.33 | H84: 0.16 | I84: PayPal | J84: 1010.2344
A85: SALE83 | B85: 45427 | C85: CUST1403 | D85: PROD17 | E85: STORE18 | F85: =Table5[[#This Row],[Total_Amount]]/(G85*(1-Table5[[#This Row],[Discount]])) -> 4 | G85: 34.39 | H85: 0.03 | I85: PayPal | J85: 133.4332
A86: SALE84 | B86: 45268 | C86: CUST1423 | D86: PROD46 | E86: STORE17 | F86: =Table5[[#This Row],[Total_Amount]]/(G86*(1-Table5[[#This Row],[Discount]])) -> 0 | G86: 773.57 | H86: 0.05 | I86: COD
A87: SALE85 | B87: 45282 | C87: CUST1054 | D87: PROD88 | E87: STORE7 | F87: =Table5[[#This Row],[Total_Amount]]/(G87*(1-Table5[[#This Row],[Discount]])) -> 4 | G87: 127.1 | H87: 0.24 | I87: COD | J87: 386.384
A88: SALE86 | B88: 45545 | C88: CUST1303 | D88: PROD20 | E88: STORE3 | F88: =Table5[[#This Row],[Total_Amount]]/(G88*(1-Table5[[#This Row],[Discount]])) -> 3 | G88: 899.58 | H88: 0.28 | I88: PayPal | J88: 1943.0928
A89: SALE87 | B89: 45755 | C89: CUST1327 | D89: PROD1 | E89: STORE10 | F89: =Table5[[#This Row],[Total_Amount]]/(G89*(1-Table5[[#This Row],[Discount]])) -> 3 | G89: 964.39 | H89: 0.04 | I89: Credit Card | J89: 2777.4432
A90: SALE88 | B90: 45588 | C90: CUST1183 | D90: PROD38 | E90: STORE0 | F90: =Table5[[#This Row],[Total_Amount]]/(G90*(1-Table5[[#This Row],[Discount]])) -> 2 | G90: 217.83 | H90: 0.14 | I90: PayPal | J90: 374.6676
A91: SALE89 | B91: 45848 | C91: CUST1143 | D91: PROD17 | E91: STORE1 | F91: =Table5[[#This Row],[Total_Amount]]/(G91*(1-Table5[[#This Row],[Discount]])) -> 4 | G91: 187.71 | H91: 0.06 | I91: COD | J91: 705.7896
A92: SALE90 | B92: 45577 | C92: CUST1010 | D92: PROD33 | E92: STORE18 | F92: =Table5[[#This Row],[Total_Amount]]/(G92*(1-Table5[[#This Row],[Discount]])) -> 2 | G92: 350.12 | H92: 0.12 | I92: COD | J92: 616.2112
A93: SALE91 | B93: 45312 | C93: CUST1406 | D93: PROD16 | E93: STORE1 | F93: =Table5[[#This Row],[Total_Amount]]/(G93*(1-Table5[[#This Row],[Discount]])) -> 4 | G93: 102.19 | H93: 0.17 | I93: PayPal | J93: 339.2708
A94: SALE92 | B94: 45350 | C94: CUST1007 | D94: PROD86 | E94: STORE4 | F94: =Table5[[#This Row],[Total_Amount]]/(G94*(1-Table5[[#This Row],[Discount]])) -> 1 | G94: 696.53 | H94: 0.17 | I94: Credit Card | J94: 578.1199
A95: SALE93 | B95: 45657 | C95: CUST1065 | D95: PROD19 | E95: STORE4 | F95: =Table5[[#This Row],[Total_Amount]]/(G95*(1-Table5[[#This Row],[Discount]])) -> 2 | G95: 327.52 | H95: 0.15 | I95: PayPal | J95: 556.784
A96: SALE94 | B96: 45530 | C96: CUST1298 | D96: PROD97 | E96: STORE19 | F96: =Table5[[#This Row],[Total_Amount]]/(G96*(1-Table5[[#This Row],[Discount]])) -> 0 | G96: 569.36 | H96: 0.01 | I96: PayPal
A97: SALE95 | B97: 45556 | C97: CUST1321 | D97: PROD99 | E97: STORE6 | F97: =Table5[[#This Row],[Total_Amount]]/(G97*(1-Table5[[#This Row],[Discount]])) -> 2 | G97: 68.29 | H97: 0.14 | I97: COD | J97: 117.4588
A98: SALE96 | B98: 45523 | C98: CUST1244 | D98: PROD50 | E98: STORE10 | F98: =Table5[[#This Row],[Total_Amount]]/(G98*(1-Table5[[#This Row],[Discount]])) -> 1 | G98: 842.9 | H98: 0.06 | I98: COD | J98: 792.326
A99: SALE97 | B99: 45587 | C99: CUST1287 | D99: PROD3 | E99: STORE3 | F99: =Table5[[#This Row],[Total_Amount]]/(G99*(1-Table5[[#This Row],[Discount]])) -> 3 | G99: 751.94 | H99: 0.26 | I99: PayPal | J99: 1669.3068
A100: SALE98 | B100: 45580 | C100: CUST1131 | D100: PROD56 | E100: STORE7 | F100: =Table5[[#This Row],[Total_Amount]]/(G100*(1-Table5[[#This Row],[Discount]])) -> 4 | G100: 476.28 | H100: 0.17 | I100: Credit Card | J100: 1581.2496
A101: SALE99 | B101: 45479 | C101: CUST1325 | D101: PROD54 | E101: STORE3 | F101: =Table5[[#This Row],[Total_Amount]]/(G101*(1-Table5[[#This Row],[Discount]])) -> 3 | G101: 541.99 | H101: 0.24 | I101: COD | J101: 1235.7372
A102: SALE100 | B102: 45677 | C102: CUST1369 | D102: PROD33 | E102: STORE5 | F102: =Table5[[#This Row],[Total_Amount]]/(G102*(1-Table5[[#This Row],[Discount]])) -> 2 | G102: 401.5 | H102: 0.18 | I102: Credit Card | J102: 658.46
A103: SALE101 | B103: 45453 | C103: CUST1084 | D103: PROD25 | E103: STORE13 | F103: =Table5[[#This Row],[Total_Amount]]/(G103*(1-Table5[[#This Row],[Discount]])) -> 3 | G103: 359.56 | H103: 0.17 | I103: PayPal | J103: 895.3044
A104: SALE102 | B104: 45552 | C104: CUST1097 | D104: PROD80 | E104: STORE12 | F104: =Table5[[#This Row],[Total_Amount]]/(G104*(1-Table5[[#This Row],[Discount]])) -> 2 | G104: 471.88 | H104: 0.24 | I104: PayPal | J104: 717.2576
A105: SALE103 | B105: 45907 | C105: CUST1182 | D105: PROD34 | E105: STORE4 | F105: =Table5[[#This Row],[Total_Amount]]/(G105*(1-Table5[[#This Row],[Discount]])) -> 4 | G105: 925.19 | H105: 0.19 | I105: PayPal | J105: 2997.6156
A106: SALE104 | B106: 45330 | C106: CUST1029 | D106: PROD86 | E106: STORE11 | F106: =Table5[[#This Row],[Total_Amount]]/(G106*(1-Table5[[#This Row],[Discount]])) -> 2 | G106: 879.63 | H106: 0.07 | I106: COD | J106: 1636.1118
A107: SALE105 | B107: 45214 | C107: CUST1002 | D107: PROD79 | E107: STORE17 | F107: =Table5[[#This Row],[Total_Amount]]/(G107*(1-Table5[[#This Row],[Discount]])) -> 2 | G107: 418.23 | H107: 0.28 | I107: Credit Card | J107: 602.2512
A108: SALE106 | B108: 45891 | C108: CUST1269 | D108: PROD19 | E108: STORE18 | F108: =Table5[[#This Row],[Total_Amount]]/(G108*(1-Table5[[#This Row],[Discount]])) -> 3 | G108: 551.72 | H108: 0.03 | I108: COD | J108: 1605.5052
... A260: SALE258 | B260: 45300 | C260: CUST1136 | D260: PROD35 | E260: STORE17 | F260: =Table5[[#This Row],[Total_Amount]]/(G260*(1-Table5[[#This Row],[Discount]])) -> 1 | G260: 222.94 | H260: 0.19 | I260: Credit Card | J260: 180.5814
A261: SALE259 | B261: 45773 | C261: CUST1248 | D261: PROD35 | E261: STORE2 | F261: Uknown | G261: 355.3 | H261: Unknown | I261: PayPal | J261: 589.798
A262: SALE260 | B262: 45497 | C262: CUST1103 | D262: PROD89 | E262: STORE19 | F262: =Table5[[#This Row],[Total_Amount]]/(G262*(1-Table5[[#This Row],[Discount]])) -> 4 | G262: 611.3 | H262: 0.11 | I262: PayPal | J262: 2176.228
A263: SALE261 | B263: 45742 | C263: CUST1333 | D263: PROD0 | E263: STORE8 | F263: =Table5[[#This Row],[Total_Amount]]/(G263*(1-Table5[[#This Row],[Discount]])) -> 4 | G263: 849.21 | H263: 0.07 | I263: Credit Card | J263: 3159.0612
...

Sheet Clean Sales_vlook up
A1: Sales_ID | B1: Order_Date | C1: Customer_ID | D1: Product_ID | E1: Store_ID | F1: Store name | G1: Product name | H1: Category | I1: Region | J1: Customer Name | K1: Quantity | L1: Unit_Price | M1: Discount | N1: Payment_Type | O1: Total_Amount
A2: SALE0 | B2: 45480 | C2: CUST1409 | D2: PROD97 | E2: STORE3 | F2: =[1]Raw_Customer_Dim!$A$2 -> CUST1000 | G2: =_xlfn.XLOOKUP(E2,Store_Dim!A:A,Store_Dim!B:B,"Not Found") -> Johnson-Wright | H2: =_xlfn.XLOOKUP(D2,Product_Dim!A:A,Product_Dim!C:C,"Not Found") -> Sports | I2: =_xlfn.XLOOKUP(E2,Store_Dim!A:A,Store_Dim!C:C,"Not Found") -> North | J2: =_xlfn.XLOOKUP(C2,Customer_Dim!A:A,Customer_Dim!B:B,"Not Found") -> Sarah Smith | K2: 1 | L2: 218.04 | M2: 0.09 | N2: Credit Card | O2: 198.4164 | Q2: Sales
A3: SALE1 | B3: 45285 | C3: CUST1467 | D3: PROD74 | E3: STORE17 | F3: =[1]Raw_Customer_Dim!$A$2 -> CUST1000 | G3: =_xlfn.XLOOKUP(E3,Store_Dim!A:A,Store_Dim!B:B,"Not Found") -> Holloway Ltd | H3: =_xlfn.XLOOKUP(D3,Product_Dim!A:A,Product_Dim!C:C,"Not Found") -> Electronics | I3: =_xlfn.XLOOKUP(E3,Store_Dim!A:A,Store_Dim!C:C,"Not Found") -> North | J3: =_xlfn.XLOOKUP(C3,Customer_Dim!A:A,Customer_Dim!B:B,"Not Found") -> Michael Foley | K3: 3 | L3: 104.47 | M3: 0.27 | N3: PayPal | O3: 228.7893 | Q3: tools | R3: result
A4: SALE2 | B4: 45446 | C4: CUST1056 | D4: PROD49 | E4: STORE8 | F4: =[1]Raw_Customer_Dim!$A$2 -> CUST1000 | G4: =_xlfn.XLOOKUP(E4,Store_Dim!A:A,Store_Dim!B:B,"Not Found") -> Bean, Jones and Park | H4: =_xlfn.XLOOKUP(D4,Product_Dim!A:A,Product_Dim!C:C,"Not Found") -> Beauty | I4: =_xlfn.XLOOKUP(E4,Store_Dim!A:A,Store_Dim!C:C,"Not Found") -> West | J4: =_xlfn.XLOOKUP(C4,Customer_Dim!A:A,Customer_Dim!B:B,"Not Found") -> Christopher Sutton | K4: 4 | L4: 914.05 | M4: 0.25 | N4: Credit Card | O4: 2742.15 | Q4: Sum | R4: =SUM(Table511[[#All],[Total_Amount]]) -> 2170907.5
A5: SALE3 | B5: 45259 | C5: CUST1346 | D5: PROD76 | E5: STORE8 | F5: =[1]Raw_Customer_Dim!$A$2 -> CUST1000 | G5: =_xlfn.XLOOKUP(E5,Store_Dim!A:A,Store_Dim!B:B,"Not Found") -> Bean, Jones and Park | H5: =_xlfn.XLOOKUP(D5,Product_Dim!A:A,Product_Dim!C:C,"Not Found") -> Electronics | I5: =_xlfn.XLOOKUP(E5,Store_Dim!A:A,Store_Dim!C:C,"Not Found") -> West | J5: =_xlfn.XLOOKUP(C5,Customer_Dim!A:A,Customer_Dim!B:B,"Not Found") -> John Jordan | K5: 1 | L5: 921.51 | M5: 0.16 | N5: COD | O5: 774.0684 | Q5: Mean | R5: =AVERAGE(Table511[Total_Amount]) -> 1087.629
A6: SALE4 | B6: 45297 | C6: CUST1493 | D6: PROD59 | E6: STORE5 | F6: =[1]Raw_Customer_Dim!$A$2 -> CUST1000 | G6: =_xlfn.XLOOKUP(E6,Store_Dim!A:A,Store_Dim!B:B,"Not Found") -> Gray Ltd | H6: =_xlfn.XLOOKUP(D6,Product_Dim!A:A,Product_Dim!C:C,"Not Found") -> Beauty | I6: =_xlfn.XLOOKUP(E6,Store_Dim!A:A,Store_Dim!C:C,"Not Found") -> North | J6: =_xlfn.XLOOKUP(C6,Customer_Dim!A:A,Customer_Dim!B:B,"Not Found") -> Amanda Powell | K6: 3 | L6: 745.3 | M6: 0.18 | N6: Credit Card | O6: 1833.438 | Q6: Median | R6: =MEDIAN(Table511[Total_Amount]) -> 868.7182
A7: SALE5 | B7: 45499 | C7: CUST1116 | D7: PROD15 | E7: STORE7 | F7: =[1]Raw_Customer_Dim!$A$2 -> CUST1000 | G7: =_xlfn.XLOOKUP(E7,Store_Dim!A:A,Store_Dim!B:B,"Not Found") -> Martinez-Mullins | H7: =_xlfn.XLOOKUP(D7,Product_Dim!A:A,Product_Dim!C:C,"Not Found") -> Electronics | I7: =_xlfn.XLOOKUP(E7,Store_Dim!A:A,Store_Dim!C:C,"Not Found") -> South | J7: =_xlfn.XLOOKUP(C7,Customer_Dim!A:A,Customer_Dim!B:B,"Not Found") -> Anthony Phillips | K7: 3 | L7: 147.01 | M7: 0.19 | N7: COD | O7: 357.2343 | Q7: Standard Deviation | R7: =_xlfn.STDEV.P(Table511[Total_Amount]) -> 819.9203
A8: SALE6 | B8: 45850 | C8: CUST1016 | D8: PROD56 | E8: STORE4 | F8: =[1]Raw_Customer_Dim!$A$2 -> CUST1000 | G8: =_xlfn.XLOOKUP(E8,Store_Dim!A:A,Store_Dim!B:B,"Not Found") -> Alexander Group | H8: =_xlfn.XLOOKUP(D8,Product_Dim!A:A,Product_Dim!C:C,"Not Found") -> Home | I8: =_xlfn.XLOOKUP(E8,Store_Dim!A:A,Store_Dim!C:C,"Not Found") -> South | J8: =_xlfn.XLOOKUP(C8,Customer_Dim!A:A,Customer_Dim!B:B,"Not Found") -> John Scott | K8: 2 | L8: 785.31 | M8: 0.15 | N8: PayPal | O8: 1335.027 | Q8: Min | R8: =MIN(Table511[[#All],[Total_Amount]]) -> 18.459
A9: SALE7 | B9: 45248 | C9: CUST1152 | D9: PROD70 | E9: STORE8 | F9: =[1]Raw_Customer_Dim!$A$2 -> CUST1000 | G9: =_xlfn.XLOOKUP(E9,Store_Dim!A:A,Store_Dim!B:B,"Not Found") -> Bean, Jones and Park | H9: =_xlfn.XLOOKUP(D9,Product_Dim!A:A,Product_Dim!C:C,"Not Found") -> Home | I9: =_xlfn.XLOOKUP(E9,Store_Dim!A:A,Store_Dim!C:C,"Not Found") -> West | J9: =_xlfn.XLOOKUP(C9,Customer_Dim!A:A,Customer_Dim!B:B,"Not Found") -> Patrick Roberts | K9: 4 | L9: 342.39 | M9: 0.23 | N9: PayPal | O9: 1054.5612 | Q9: Max | R9: =MAX(Table511[[#All],[Total_Amount]]) -> 3908.2428
A10: SALE8 | B10: 45781 | C10: CUST1187 | D10: PROD99 | E10: STORE5 | F10: =[1]Raw_Customer_Dim!$A$2 -> CUST1000 | G10: =_xlfn.XLOOKUP(E10,Store_Dim!A:A,Store_Dim!B:B,"Not Found") -> Gray Ltd | H10: =_xlfn.XLOOKUP(D10,Product_Dim!A:A,Product_Dim!C:C,"Not Found") -> Home | I10: =_xlfn.XLOOKUP(E10,Store_Dim!A:A,Store_Dim!C:C,"Not Found") -> North | J10: =_xlfn.XLOOKUP(C10,Customer_Dim!A:A,Customer_Dim!B:B,"Not Found") -> Dr. Suzanne Bullock | K10: =Table511[[#This Row],[Total_Amount]]/(L10*(1-Table511[[#This Row],[Discount]])) -> 3 | L10: 448.25 | M10: 0.07 | N10: PayPal | O10: 1250.6175 | Q10: Average | R10: =AVERAGE(Table511[[#All],[Total_Amount]]) -> 1087.629
A11: SALE9 | B11: 45869 | C11: CUST1464 | D11: PROD33 | E11: STORE0 | F11: =[1]Raw_Customer_Dim!$A$2 -> CUST1000 | G11: =_xlfn.XLOOKUP(E11,Store_Dim!A:A,Store_Dim!B:B,"Not Found") -> Rivera-Warner | H11: =_xlfn.XLOOKUP(D11,Product_Dim!A:A,Product_Dim!C:C,"Not Found") -> Home | I11: =_xlfn.XLOOKUP(E11,Store_Dim!A:A,Store_Dim!C:C,"Not Found") -> East | J11: =_xlfn.XLOOKUP(C11,Customer_Dim!A:A,Customer_Dim!B:B,"Not Found") -> Not Found | K11: =Table511[[#This Row],[Total_Amount]]/(L11*(1-Table511[[#This Row],[Discount]])) -> 2 | L11: 873.17 | M11: 0.23 | N11: PayPal | O11: 1344.6818 | Q11: mode of quantity | R11: =_xlfn.MODE.SNGL(K:K) -> 2
A12: SALE10 | B12: 45335 | C12: CUST1065 | D12: PROD24 | E12: STORE14 | F12: =[1]Raw_Customer_Dim!$A$2 -> CUST1000 | G12: =_xlfn.XLOOKUP(E12,Store_Dim!A:A,Store_Dim!B:B,"Not Found") -> Mcdonald Inc | H12: =_xlfn.XLOOKUP(D12,Product_Dim!A:A,Product_Dim!C:C,"Not Found") -> Sports | I12: =_xlfn.XLOOKUP(E12,Store_Dim!A:A,Store_Dim!C:C,"Not Found") -> South | J12: =_xlfn.XLOOKUP(C12,Customer_Dim!A:A,Customer_Dim!B:B,"Not Found") -> Michael Thomas | K12: =Table511[[#This Row],[Total_Amount]]/(L12*(1-Table511[[#This Row],[Discount]])) -> 1 | L12: 278.63 | M12: 0.07 | N12: Credit Card | O12: 259.1259
A13: SALE11 | B13: 45801 | C13: CUST1320 | D13: PROD39 | E13: STORE1 | F13: =[1]Raw_Customer_Dim!$A$2 -> CUST1000 | G13: =_xlfn.XLOOKUP(E13,Store_Dim!A:A,Store_Dim!B:B,"Not Found") -> Martinez, Adkins and Johnson | H13: =_xlfn.XLOOKUP(D13,Product_Dim!A:A,Product_Dim!C:C,"Not Found") -> Electronics | I13: =_xlfn.XLOOKUP(E13,Store_Dim!A:A,Store_Dim!C:C,"Not Found") -> North | J13: =_xlfn.XLOOKUP(C13,Customer_Dim!A:A,Customer_Dim!B:B,"Not Found") -> Jessica Gonzalez | K13: =Table511[[#This Row],[Total_Amount]]/(L13*(1-Table511[[#This Row],[Discount]])) -> 4 | L13: 286.92 | M13: 0.17 | N13: Credit Card | O13: 952.5744
A14: SALE12 | B14: 45528 | C14: CUST1237 | D14: PROD88 | E14: STORE4 | F14: =[1]Raw_Customer_Dim!$A$2 -> CUST1000 | G14: =_xlfn.XLOOKUP(E14,Store_Dim!A:A,Store_Dim!B:B,"Not Found") -> Alexander Group | H14: =_xlfn.XLOOKUP(D14,Product_Dim!A:A,Product_Dim!C:C,"Not Found") -> Sports | I14: =_xlfn.XLOOKUP(E14,Store_Dim!A:A,Store_Dim!C:C,"Not Found") -> South | J14: =_xlfn.XLOOKUP(C14,Customer_Dim!A:A,Customer_Dim!B:B,"Not Found") -> Wesley Short | K14: =Table511[[#This Row],[Total_Amount]]/(L14*(1-Table511[[#This Row],[Discount]])) -> 4 | L14: 644.58 | M14: 0.01 | N14: Credit Card | O14: 2552.5368
A15: SALE13 | B15: 45875 | C15: CUST1443 | D15: PROD34 | E15: STORE16 | F15: =[1]Raw_Customer_Dim!$A$2 -> CUST1000 | G15: =_xlfn.XLOOKUP(E15,Store_Dim!A:A,Store_Dim!B:B,"Not Found") -> Frederick-Wright | H15: =_xlfn.XLOOKUP(D15,Product_Dim!A:A,Product_Dim!C:C,"Not Found") -> Electronics | I15: =_xlfn.XLOOKUP(E15,Store_Dim!A:A,Store_Dim!C:C,"Not Found") -> West | J15: =_xlfn.XLOOKUP(C15,Customer_Dim!A:A,Customer_Dim!B:B,"Not Found") -> Adam Castro | K15: =Table511[[#This Row],[Total_Amount]]/(L15*(1-Table511[[#This Row],[Discount]])) -> 2 | L15: 316.9 | M15: 0.3 | N15: PayPal | O15: 443.66
A16: SALE14 | B16: 45829 | C16: CUST1348 | D16: PROD24 | E16: STORE15 | F16: =[1]Raw_Customer_Dim!$A$2 -> CUST1000 | G16: =_xlfn.XLOOKUP(E16,Store_Dim!A:A,Store_Dim!B:B,"Not Found") -> Shelton PLC | H16: =_xlfn.XLOOKUP(D16,Product_Dim!A:A,Product_Dim!C:C,"Not Found") -> Sports | I16: =_xlfn.XLOOKUP(E16,Store_Dim!A:A,Store_Dim!C:C,"Not Found") -> North | J16: =_xlfn.XLOOKUP(C16,Customer_Dim!A:A,Customer_Dim!B:B,"Not Found") -> Sherry Cabrera | K16: =Table511[[#This Row],[Total_Amount]]/(L16*(1-Table511[[#This Row],[Discount]])) -> 4 | L16: 403.47 | M16: 0.29 | N16: PayPal | O16: 1145.8548
A17: SALE15 | B17: 45636 | C17: CUST1435 | D17: PROD36 | E17: STORE9 | F17: =[1]Raw_Customer_Dim!$A$2 -> CUST1000 | G17: =_xlfn.XLOOKUP(E17,Store_Dim!A:A,Store_Dim!B:B,"Not Found") -> Moore, Padilla and Butler | H17: =_xlfn.XLOOKUP(D17,Product_Dim!A:A,Product_Dim!C:C,"Not Found") -> Clothing | I17: =_xlfn.XLOOKUP(E17,Store_Dim!A:A,Store_Dim!C:C,"Not Found") -> South | J17: =_xlfn.XLOOKUP(C17,Customer_Dim!A:A,Customer_Dim!B:B,"Not Found") -> Lindsay Beasley | K17: =Table511[[#This Row],[Total_Amount]]/(L17*(1-Table511[[#This Row],[Discount]])) -> 3 | L17: 871.34 | M17: 0.04 | N17: COD | O17: 2509.4592
A18: SALE16 | B18: 45913 | C18: CUST1276 | D18: PROD65 | E18: STORE19 | F18: =[1]Raw_Customer_Dim!$A$2 -> CUST1000 | G18: =_xlfn.XLOOKUP(E18,Store_Dim!A:A,Store_Dim!B:B,"Not Found") -> Mann-Austin | H18: =_xlfn.XLOOKUP(D18,Product_Dim!A:A,Product_Dim!C:C,"Not Found") -> Sports | I18: =_xlfn.XLOOKUP(E18,Store_Dim!A:A,Store_Dim!C:C,"Not Found") -> East | J18: =_xlfn.XLOOKUP(C18,Customer_Dim!A:A,Customer_Dim!B:B,"Not Found") -> Arthur Warren | K18: =Table511[[#This Row],[Total_Amount]]/(L18*(1-Table511[[#This Row],[Discount]])) -> 2 | L18: 451.98 | M18: 0.25 | N18: Credit Card | O18: 677.97
A19: SALE17 | B19: 45637 | C19: CUST1079 | D19: PROD27 | E19: STORE4 | F19: =[1]Raw_Customer_Dim!$A$2 -> CUST1000 | G19: =_xlfn.XLOOKUP(E19,Store_Dim!A:A,Store_Dim!B:B,"Not Found") -> Alexander Group | H19: =_xlfn.XLOOKUP(D19,Product_Dim!A:A,Product_Dim!C:C,"Not Found") -> Home | I19: =_xlfn.XLOOKUP(E19,Store_Dim!A:A,Store_Dim!C:C,"Not Found") -> South | J19: =_xlfn.XLOOKUP(C19,Customer_Dim!A:A,Customer_Dim!B:B,"Not Found") -> Molly Gardner | K19: =Table511[[#This Row],[Total_Amount]]/(L19*(1-Table511[[#This Row],[Discount]])) -> 2 | L19: 502.69 | M19: 0.23 | N19: Credit Card | O19: 774.1426
A20: SALE18 | B20: 45517 | C20: CUST1094 | D20: PROD39 | E20: STORE4 | F20: =[1]Raw_Customer_Dim!$A$2 -> CUST1000 | G20: =_xlfn.XLOOKUP(E20,Store_Dim!A:A,Store_Dim!B:B,"Not Found") -> Alexander Group | H20: =_xlfn.XLOOKUP(D20,Product_Dim!A:A,Product_Dim!C:C,"Not Found") -> Electronics | I20: =_xlfn.XLOOKUP(E20,Store_Dim!A:A,Store_Dim!C:C,"Not Found") -> South | J20: =_xlfn.XLOOKUP(C20,Customer_Dim!A:A,Customer_Dim!B:B,"Not Found") -> David Patterson | K20: =Table511[[#This Row],[Total_Amount]]/(L20*(1-Table511[[#This Row],[Discount]])) -> 2 | L20: 559.23 | M20: 0.25 | N20: COD | O20: 838.845
A21: SALE19 | B21: 45369 | C21: CUST1239 | D21: PROD60 | E21: STORE13 | F21: =[1]Raw_Customer_Dim!$A$2 -> CUST1000 | G21: =_xlfn.XLOOKUP(E21,Store_Dim!A:A,Store_Dim!B:B,"Not Found") -> Gardner, Humphrey and Contreras | H21: =_xlfn.XLOOKUP(D21,Product_Dim!A:A,Product_Dim!C:C,"Not Found") -> Beauty | I21: =_xlfn.XLOOKUP(E21,Store_Dim!A:A,Store_Dim!C:C,"Not Found") -> East | J21: =_xlfn.XLOOKUP(C21,Customer_Dim!A:A,Customer_Dim!B:B,"Not Found") -> Maria Hill | K21: Uknown | L21: Unknown | M21: 0.04 | N21: COD | O21: 1782.4512
A22: SALE20 | B22: 45843 | C22: CUST1144 | D22: PROD72 | E22: STORE17 | F22: =[1]Raw_Customer_Dim!$A$2 -> CUST1000 | G22: =_xlfn.XLOOKUP(E22,Store_Dim!A:A,Store_Dim!B:B,"Not Found") -> Holloway Ltd | H22: =_xlfn.XLOOKUP(D22,Product_Dim!A:A,Product_Dim!C:C,"Not Found") -> Sports | I22: =_xlfn.XLOOKUP(E22,Store_Dim!A:A,Store_Dim!C:C,"Not Found") -> North | J22: =_xlfn.XLOOKUP(C22,Customer_Dim!A:A,Customer_Dim!B:B,"Not Found") -> Justin Cross | K22: =Table511[[#This Row],[Total_Amount]]/(L22*(1-Table511[[#This Row],[Discount]])) -> 3 | L22: 986.04 | M22: 0.27 | N22: COD | O22: 2159.4276
A23: SALE21 | B23: 45447 | C23: CUST1396 | D23: PROD43 | E23: STORE18 | F23: =[1]Raw_Customer_Dim!$A$2 -> CUST1000 | G23: =_xlfn.XLOOKUP(E23,Store_Dim!A:A,Store_Dim!B:B,"Not Found") -> Guerrero-Schmitt | H23: =_xlfn.XLOOKUP(D23,Product_Dim!A:A,Product_Dim!C:C,"Not Found") -> Electronics | I23: =_xlfn.XLOOKUP(E23,Store_Dim!A:A,Store_Dim!C:C,"Not Found") -> East | J23: =_xlfn.XLOOKUP(C23,Customer_Dim!A:A,Customer_Dim!B:B,"Not Found") -> Alexander Byrd | K23: =Table511[[#This Row],[Total_Amount]]/(L23*(1-Table511[[#This Row],[Discount]])) -> 1 | L23: 589.56 | M23: 0.22 | N23: Credit Card | O23: 459.8568
A24: SALE22 | B24: 45394 | C24: CUST1476 | D24: PROD69 | E24: STORE10 | F24: =[1]Raw_Customer_Dim!$A$2 -> CUST1000 | G24: =_xlfn.XLOOKUP(E24,Store_Dim!A:A,Store_Dim!B:B,"Not Found") -> Hill, Wagner and Ballard | H24: =_xlfn.XLOOKUP(D24,Product_Dim!A:A,Product_Dim!C:C,"Not Found") -> Clothing | I24: =_xlfn.XLOOKUP(E24,Store_Dim!A:A,Store_Dim!C:C,"Not Found") -> East | J24: =_xlfn.XLOOKUP(C24,Customer_Dim!A:A,Customer_Dim!B:B,"Not Found") -> Elizabeth Foster | K24: =Table511[[#This Row],[Total_Amount]]/(L24*(1-Table511[[#This Row],[Discount]])) -> 3 | L24: 979.42 | M24: 0.03 | N24: PayPal | O24: 2850.1122
A25: SALE23 | B25: 45466 | C25: CUST1368 | D25: PROD12 | E25: STORE8 | F25: =[1]Raw_Customer_Dim!$A$2 -> CUST1000 | G25: =_xlfn.XLOOKUP(E25,Store_Dim!A:A,Store_Dim!B:B,"Not Found") -> Bean, Jones and Park | H25: =_xlfn.XLOOKUP(D25,Product_Dim!A:A,Product_Dim!C:C,"Not Found") -> Beauty | I25: =_xlfn.XLOOKUP(E25,Store_Dim!A:A,Store_Dim!C:C,"Not Found") -> West | J25: =_xlfn.XLOOKUP(C25,Customer_Dim!A:A,Customer_Dim!B:B,"Not Found") -> Miranda King | K25: =Table511[[#This Row],[Total_Amount]]/(L25*(1-Table511[[#This Row],[Discount]])) -> 1 | L25: 719.28 | M25: 0.08 | N25: Credit Card | O25: 661.7376
A26: SALE24 | B26: 45908 | C26: CUST1186 | D26: PROD67 | E26: STORE6 | F26: =[1]Raw_Customer_Dim!$A$2 -> CUST1000 | G26: =_xlfn.XLOOKUP(E26,Store_Dim!A:A,Store_Dim!B:B,"Not Found") -> Benson-Elliott | H26: =_xlfn.XLOOKUP(D26,Product_Dim!A:A,Product_Dim!C:C,"Not Found") -> Electronics | I26: =_xlfn.XLOOKUP(E26,Store_Dim!A:A,Store_Dim!C:C,"Not Found") -> East | J26: =_xlfn.XLOOKUP(C26,Customer_Dim!A:A,Customer_Dim!B:B,"Not Found") -> Jennifer Pruitt | K26: =Table511[[#This Row],[Total_Amount]]/(L26*(1-Table511[[#This Row],[Discount]])) -> 3 | L26: 77.6 | M26: 0.07 | N26: Credit Card | O26: 216.504
A27: SALE25 | B27: 45552 | C27: CUST1381 | D27: PROD5 | E27: STORE3 | F27: =[1]Raw_Customer_Dim!$A$2 -> CUST1000 | G27: =_xlfn.XLOOKUP(E27,Store_Dim!A:A,Store_Dim!B:B,"Not Found") -> Johnson-Wright | H27: =_xlfn.XLOOKUP(D27,Product_Dim!A:A,Product_Dim!C:C,"Not Found") -> Clothing | I27: =_xlfn.XLOOKUP(E27,Store_Dim!A:A,Store_Dim!C:C,"Not Found") -> North | J27: =_xlfn.XLOOKUP(C27,Customer_Dim!A:A,Customer_Dim!B:B,"Not Found") -> Erika Padilla | K27: =Table511[[#This Row],[Total_Amount]]/(L27*(1-Table511[[#This Row],[Discount]])) -> 4 | L27: 852.71 | M27: 0.14 | N27: PayPal | O27: 2933.3224
A28: SALE26 | B28: 45294 | C28: CUST1213 | D28: PROD98 | E28: STORE8 | F28: =[1]Raw_Customer_Dim!$A$2 -> CUST1000 | G28: =_xlfn.XLOOKUP(E28,Store_Dim!A:A,Store_Dim!B:B,"Not Found") -> Bean, Jones and Park | H28: =_xlfn.XLOOKUP(D28,Product_Dim!A:A,Product_Dim!C:C,"Not Found") -> Electronics | I28: =_xlfn.XLOOKUP(E28,Store_Dim!A:A,Store_Dim!C:C,"Not Found") -> West | J28: =_xlfn.XLOOKUP(C28,Customer_Dim!A:A,Customer_Dim!B:B,"Not Found") -> Stuart Johnson | K28: Uknown | L28: 156.16 | M28: Unknown | N28: Credit Card | O28: 599.6544
A29: SALE27 | B29: 45710 | C29: CUST1200 | D29: PROD77 | E29: STORE8 | F29: =[1]Raw_Customer_Dim!$A$2 -> CUST1000 | G29: =_xlfn.XLOOKUP(E29,Store_Dim!A:A,Store_Dim!B:B,"Not Found") -> Bean, Jones and Park | H29: =_xlfn.XLOOKUP(D29,Product_Dim!A:A,Product_Dim!C:C,"Not Found") -> Electronics | I29: =_xlfn.XLOOKUP(E29,Store_Dim!A:A,Store_Dim!C:C,"Not Found") -> West | J29: =_xlfn.XLOOKUP(C29,Customer_Dim!A:A,Customer_Dim!B:B,"Not Found") -> Anna Perez | K29: =Table511[[#This Row],[Total_Amount]]/(L29*(1-Table511[[#This Row],[Discount]])) -> 3 | L29: 815.49 | M29: 0.17 | N29: Credit Card | O29: 2030.5701
A30: SALE28 | B30: 45923 | C30: CUST1148 | D30: PROD13 | E30: STORE2 | F30: =[1]Raw_Customer_Dim!$A$2 -> CUST1000 | G30: =_xlfn.XLOOKUP(E30,Store_Dim!A:A,Store_Dim!B:B,"Not Found") -> Black-Horn | H30: =_xlfn.XLOOKUP(D30,Product_Dim!A:A,Product_Dim!C:C,"Not Found") -> Electronics | I30: =_xlfn.XLOOKUP(E30,Store_Dim!A:A,Store_Dim!C:C,"Not Found") -> South | J30: =_xlfn.XLOOKUP(C30,Customer_Dim!A:A,Customer_Dim!B:B,"Not Found") -> Theresa Campbell | K30: =Table511[[#This Row],[Total_Amount]]/(L30*(1-Table511[[#This Row],[Discount]])) -> 2 | L30: 74.21 | M30: 0.11 | N30: PayPal | O30: 132.0938
A31: SALE29 | B31: 45302 | C31: CUST1348 | D31: PROD99 | E31: STORE3 | F31: =[1]Raw_Customer_Dim!$A$2 -> CUST1000 | G31: =_xlfn.XLOOKUP(E31,Store_Dim!A:A,Store_Dim!B:B,"Not Found") -> Johnson-Wright | H31: =_xlfn.XLOOKUP(D31,Product_Dim!A:A,Product_Dim!C:C,"Not Found") -> Home | I31: =_xlfn.XLOOKUP(E31,Store_Dim!A:A,Store_Dim!C:C,"Not Found") -> North | J31: =_xlfn.XLOOKUP(C31,Customer_Dim!A:A,Customer_Dim!B:B,"Not Found") -> Sherry Cabrera | K31: =Table511[[#This Row],[Total_Amount]]/(L31*(1-Table511[[#This Row],[Discount]])) -> 4 | L31: 451.67 | M31: 0.15 | N31: Credit Card | O31: 1535.678
A32: SALE30 | B32: 45217 | C32: CUST1028 | D32: PROD5 | E32: STORE19 | F32: =[1]Raw_Customer_Dim!$A$2 -> CUST1000 | G32: =_xlfn.XLOOKUP(E32,Store_Dim!A:A,Store_Dim!B:B,"Not Found") -> Mann-Austin | H32: =_xlfn.XLOOKUP(D32,Product_Dim!A:A,Product_Dim!C:C,"Not Found") -> Clothing | I32: =_xlfn.XLOOKUP(E32,Store_Dim!A:A,Store_Dim!C:C,"Not Found") -> East | J32: =_xlfn.XLOOKUP(C32,Customer_Dim!A:A,Customer_Dim!B:B,"Not Found") -> Joshua Ryan | K32: =Table511[[#This Row],[Total_Amount]]/(L32*(1-Table511[[#This Row],[Discount]])) -> 1 | L32: 429.38 | M32: 0.13 | N32: PayPal | O32: 373.5606
A33: SALE31 | B33: 45593 | C33: CUST1412 | D33: PROD53 | E33: STORE12 | F33: =[1]Raw_Customer_Dim!$A$2 -> CUST1000 | G33: =_xlfn.XLOOKUP(E33,Store_Dim!A:A,Store_Dim!B:B,"Not Found") -> Thomas, Bridges and Harris | H33: =_xlfn.XLOOKUP(D33,Product_Dim!A:A,Product_Dim!C:C,"Not Found") -> Clothing | I33: =_xlfn.XLOOKUP(E33,Store_Dim!A:A,Store_Dim!C:C,"Not Found") -> North | J33: =_xlfn.XLOOKUP(C33,Customer_Dim!A:A,Customer_Dim!B:B,"Not Found") -> Shane Brown | K33: =Table511[[#This Row],[Total_Amount]]/(L33*(1-Table511[[#This Row],[Discount]])) -> 2 | L33: 148.96 | M33: 0.03 | N33: COD | O33: 288.9824
A34: SALE32 | B34: 45597 | C34: CUST1398 | D34: PROD75 | E34: STORE8 | F34: =[1]Raw_Customer_Dim!$A$2 -> CUST1000 | G34: =_xlfn.XLOOKUP(E34,Store_Dim!A:A,Store_Dim!B:B,"Not Found") -> Bean, Jones and Park | H34: =_xlfn.XLOOKUP(D34,Product_Dim!A:A,Product_Dim!C:C,"Not Found") -> Clothing | I34: =_xlfn.XLOOKUP(E34,Store_Dim!A:A,Store_Dim!C:C,"Not Found") -> West | J34: =_xlfn.XLOOKUP(C34,Customer_Dim!A:A,Customer_Dim!B:B,"Not Found") -> Jennifer Johnson | K34: =Table511[[#This Row],[Total_Amount]]/(L34*(1-Table511[[#This Row],[Discount]])) -> 4 | L34: 313.83 | M34: 0.08 | N34: Credit Card | O34: 1154.8944
A35: SALE33 | B35: 45620 | C35: CUST1453 | D35: PROD12 | E35: STORE6 | F35: =[1]Raw_Customer_Dim!$A$2 -> CUST1000 | G35: =_xlfn.XLOOKUP(E35,Store_Dim!A:A,Store_Dim!B:B,"Not Found") -> Benson-Elliott | H35: =_xlfn.XLOOKUP(D35,Product_Dim!A:A,Product_Dim!C:C,"Not Found") -> Beauty | I35: =_xlfn.XLOOKUP(E35,Store_Dim!A:A,Store_Dim!C:C,"Not Found") -> East | J35: =_xlfn.XLOOKUP(C35,Customer_Dim!A:A,Customer_Dim!B:B,"Not Found") -> April Phillips | K35: =Table511[[#This Row],[Total_Amount]]/(L35*(1-Table511[[#This Row],[Discount]])) -> 2 | L35: 717.31 | M35: 0.15 | N35: Credit Card | O35: 1219.427
A36: SALE34 | B36: 45215 | C36: CUST1344 | D36: PROD79 | E36: STORE1 | F36: =[1]Raw_Customer_Dim!$A$2 -> CUST1000 | G36: =_xlfn.XLOOKUP(E36,Store_Dim!A:A,Store_Dim!B:B,"Not Found") -> Martinez, Adkins and Johnson | H36: =_xlfn.XLOOKUP(D36,Product_Dim!A:A,Product_Dim!C:C,"Not Found") -> Home | I36: =_xlfn.XLOOKUP(E36,Store_Dim!A:A,Store_Dim!C:C,"Not Found") -> North | J36: =_xlfn.XLOOKUP(C36,Customer_Dim!A:A,Customer_Dim!B:B,"Not Found") -> Evelyn Brown | K36: =Table511[[#This Row],[Total_Amount]]/(L36*(1-Table511[[#This Row],[Discount]])) -> 3 | L36: 873.22 | M36: 0.18 | N36: Credit Card | O36: 2148.1212
A37: SALE35 | B37: 45878 | C37: CUST1218 | D37: PROD16 | E37: STORE3 | F37: =[1]Raw_Customer_Dim!$A$2 -> CUST1000 | G37: =_xlfn.XLOOKUP(E37,Store_Dim!A:A,Store_Dim!B:B,"Not Found") -> Johnson-Wright | H37: =_xlfn.XLOOKUP(D37,Product_Dim!A:A,Product_Dim!C:C,"Not Found") -> Not Found | I37: =_xlfn.XLOOKUP(E37,Store_Dim!A:A,Store_Dim!C:C,"Not Found") -> North | J37: =_xlfn.XLOOKUP(C37,Customer_Dim!A:A,Customer_Dim!B:B,"Not Found") -> Julia Jackson | K37: =Table511[[#This Row],[Total_Amount]]/(L37*(1-Table511[[#This Row],[Discount]])) -> 4 | L37: 109.36 | M37: 0.19 | N37: COD | O37: 354.3264
A38: SALE36 | B38: 45635 | C38: CUST1086 | D38: PROD5 | E38: STORE7 | F38: =[1]Raw_Customer_Dim!$A$2 -> CUST1000 | G38: =_xlfn.XLOOKUP(E38,Store_Dim!A:A,Store_Dim!B:B,"Not Found") -> Martinez-Mullins | H38: =_xlfn.XLOOKUP(D38,Product_Dim!A:A,Product_Dim!C:C,"Not Found") -> Clothing | I38: =_xlfn.XLOOKUP(E38,Store_Dim!A:A,Store_Dim!C:C,"Not Found") -> South | J38: =_xlfn.XLOOKUP(C38,Customer_Dim!A:A,Customer_Dim!B:B,"Not Found") -> Tammy Miller MD | K38: =Table511[[#This Row],[Total_Amount]]/(L38*(1-Table511[[#This Row],[Discount]])) -> 3 | L38: 559.52 | M38: 0.16 | N38: PayPal | O38: 1409.9904
A39: SALE37 | B39: 45329 | C39: CUST1492 | D39: PROD10 | E39: STORE17 | F39: =[1]Raw_Customer_Dim!$A$2 -> CUST1000 | G39: =_xlfn.XLOOKUP(E39,Store_Dim!A:A,Store_Dim!B:B,"Not Found") -> Holloway Ltd | H39: =_xlfn.XLOOKUP(D39,Product_Dim!A:A,Product_Dim!C:C,"Not Found") -> Home | I39: =_xlfn.XLOOKUP(E39,Store_Dim!A:A,Store_Dim!C:C,"Not Found") -> North | J39: =_xlfn.XLOOKUP(C39,Customer_Dim!A:A,Customer_Dim!B:B,"Not Found") -> Darrell Miller | K39: =Table511[[#This Row],[Total_Amount]]/(L39*(1-Table511[[#This Row],[Discount]])) -> 3 | L39: 121.76 | M39: 0.27 | N39: PayPal | O39: 266.6544
A40: SALE38 | B40: 45378 | C40: CUST1189 | D40: PROD33 | E40: STORE13 | F40: =[1]Raw_Customer_Dim!$A$2 -> CUST1000 | G40: =_xlfn.XLOOKUP(E40,Store_Dim!A:A,Store_Dim!B:B,"Not Found") -> Gardner, Humphrey and Contreras | H40: =_xlfn.XLOOKUP(D40,Product_Dim!A:A,Product_Dim!C:C,"Not Found") -> Home | I40: =_xlfn.XLOOKUP(E40,Store_Dim!A:A,Store_Dim!C:C,"Not Found") -> East | J40: =_xlfn.XLOOKUP(C40,Customer_Dim!A:A,Customer_Dim!B:B,"Not Found") -> Daniel Austin | K40: =Table511[[#This Row],[Total_Amount]]/(L40*(1-Table511[[#This Row],[Discount]])) -> 4 | L40: 735.32 | M40: 0.06 | N40: COD | O40: 2764.8032
... A53: SALE51 | B53: 45689 | C53: CUST1142 | D53: PROD69 | E53: STORE7 | F53: =[1]Raw_Customer_Dim!$A$2 -> CUST1000 | G53: =_xlfn.XLOOKUP(E53,Store_Dim!A:A,Store_Dim!B:B,"Not Found") -> Martinez-Mullins | H53: =_xlfn.XLOOKUP(D53,Product_Dim!A:A,Product_Dim!C:C,"Not Found") -> Clothing | I53: =_xlfn.XLOOKUP(E53,Store_Dim!A:A,Store_Dim!C:C,"Not Found") -> South | J53: =_xlfn.XLOOKUP(C53,Customer_Dim!A:A,Customer_Dim!B:B,"Not Found") -> Maria Ramirez | K53: =Table511[[#This Row],[Total_Amount]]/(L53*(1-Table511[[#This Row],[Discount]])) -> 3 | L53: 76.57 | M53: 0.26 | N53: Credit Card | O53: 169.9854
A54: SALE52 | B54: 45894 | C54: CUST1148 | D54: PROD89 | E54: STORE6 | F54: =[1]Raw_Customer_Dim!$A$2 -> CUST1000 | G54: =_xlfn.XLOOKUP(E54,Store_Dim!A:A,Store_Dim!B:B,"Not Found") -> Benson-Elliott | H54: =_xlfn.XLOOKUP(D54,Product_Dim!A:A,Product_Dim!C:C,"Not Found") -> Beauty | I54: =_xlfn.XLOOKUP(E54,Store_Dim!A:A,Store_Dim!C:C,"Not Found") -> East | J54: =_xlfn.XLOOKUP(C54,Customer_Dim!A:A,Customer_Dim!B:B,"Not Found") -> Theresa Campbell | K54: Uknown | L54: Unknown | M54: Unknown | N54: Credit Card | O54: 486.0633
A55: SALE53 | B55: 45677 | C55: CUST1324 | D55: PROD20 | E55: STORE8 | F55: =[1]Raw_Customer_Dim!$A$2 -> CUST1000 | G55: =_xlfn.XLOOKUP(E55,Store_Dim!A:A,Store_Dim!B:B,"Not Found") -> Bean, Jones and Park | H55: =_xlfn.XLOOKUP(D55,Product_Dim!A:A,Product_Dim!C:C,"Not Found") -> Sports | I55: =_xlfn.XLOOKUP(E55,Store_Dim!A:A,Store_Dim!C:C,"Not Found") -> West | J55: =_xlfn.XLOOKUP(C55,Customer_Dim!A:A,Customer_Dim!B:B,"Not Found") -> Alex Mann II | K55: =Table511[[#This Row],[Total_Amount]]/(L55*(1-Table511[[#This Row],[Discount]])) -> 1 | L55: 900.35 | M55: 0.13 | N55: COD | O55: 783.3045
A56: SALE54 | B56: 45706 | C56: CUST1095 | D56: PROD40 | E56: STORE10 | F56: =[1]Raw_Customer_Dim!$A$2 -> CUST1000 | G56: =_xlfn.XLOOKUP(E56,Store_Dim!A:A,Store_Dim!B:B,"Not Found") -> Hill, Wagner and Ballard | H56: =_xlfn.XLOOKUP(D56,Product_Dim!A:A,Product_Dim!C:C,"Not Found") -> Electronics | I56: =_xlfn.XLOOKUP(E56,Store_Dim!A:A,Store_Dim!C:C,"Not Found") -> East | J56: =_xlfn.XLOOKUP(C56,Customer_Dim!A:A,Customer_Dim!B:B,"Not Found") -> Amy Fowler | K56: =Table511[[#This Row],[Total_Amount]]/(L56*(1-Table511[[#This Row],[Discount]])) -> 4 | L56: 428.09 | M56: 0.07 | N56: Credit Card | O56: 1592.4948
A57: SALE55 | B57: 45589 | C57: CUST1416 | D57: PROD49 | E57: STORE11 | F57: =[1]Raw_Customer_Dim!$A$2 -> CUST1000 | G57: =_xlfn.XLOOKUP(E57,Store_Dim!A:A,Store_Dim!B:B,"Not Found") -> Aguirre-Keller | H57: =_xlfn.XLOOKUP(D57,Product_Dim!A:A,Product_Dim!C:C,"Not Found") -> Beauty | I57: =_xlfn.XLOOKUP(E57,Store_Dim!A:A,Store_Dim!C:C,"Not Found") -> South | J57: =_xlfn.XLOOKUP(C57,Customer_Dim!A:A,Customer_Dim!B:B,"Not Found") -> Jennifer Myers | K57: =Table511[[#This Row],[Total_Amount]]/(L57*(1-Table511[[#This Row],[Discount]])) -> 2 | L57: 559.71 | M57: 0.3 | N57: COD | O57: 783.594
A58: SALE56 | B58: 45282 | C58: CUST1080 | D58: PROD34 | E58: STORE6 | F58: =[1]Raw_Customer_Dim!$A$2 -> CUST1000 | G58: =_xlfn.XLOOKUP(E58,Store_Dim!A:A,Store_Dim!B:B,"Not Found") -> Benson-Elliott | H58: =_xlfn.XLOOKUP(D58,Product_Dim!A:A,Product_Dim!C:C,"Not Found") -> Electronics | I58: =_xlfn.XLOOKUP(E58,Store_Dim!A:A,Store_Dim!C:C,"Not Found") -> East | J58: =_xlfn.XLOOKUP(C58,Customer_Dim!A:A,Customer_Dim!B:B,"Not Found") -> Jennifer Garcia | K58: =Table511[[#This Row],[Total_Amount]]/(L58*(1-Table511[[#This Row],[Discount]])) -> 2 | L58: 833.7 | M58: 0.06 | N58: PayPal | O58: 1567.356
A59: SALE57 | B59: 45462 | C59: CUST1467 | D59: PROD47 | E59: STORE14 | F59: =[1]Raw_Customer_Dim!$A$2 -> CUST1000 | G59: =_xlfn.XLOOKUP(E59,Store_Dim!A:A,Store_Dim!B:B,"Not Found") -> Mcdonald Inc | H59: =_xlfn.XLOOKUP(D59,Product_Dim!A:A,Product_Dim!C:C,"Not Found") -> Beauty | I59: =_xlfn.XLOOKUP(E59,Store_Dim!A:A,Store_Dim!C:C,"Not Found") -> South | J59: =_xlfn.XLOOKUP(C59,Customer_Dim!A:A,Customer_Dim!B:B,"Not Found") -> Michael Foley | K59: =Table511[[#This Row],[Total_Amount]]/(L59*(1-Table511[[#This Row],[Discount]])) -> 2 | L59: 680.16 | M59: 0.28 | N59: Credit Card | O59: 979.4304
A60: SALE58 | B60: 45633 | C60: CUST1404 | D60: PROD15 | E60: STORE7 | F60: =[1]Raw_Customer_Dim!$A$2 -> CUST1000 | G60: =_xlfn.XLOOKUP(E60,Store_Dim!A:A,Store_Dim!B:B,"Not Found") -> Martinez-Mullins | H60: =_xlfn.XLOOKUP(D60,Product_Dim!A:A,Product_Dim!C:C,"Not Found") -> Electronics | I60: =_xlfn.XLOOKUP(E60,Store_Dim!A:A,Store_Dim!C:C,"Not Found") -> South | J60: =_xlfn.XLOOKUP(C60,Customer_Dim!A:A,Customer_Dim!B:B,"Not Found") -> David Ross | K60: Uknown | L60: 733.42 | M60: Unknown | N60: PayPal | O60: 2552.3016
A61: SALE59 | B61: 45257 | C61: CUST1367 | D61: PROD89 | E61: STORE11 | F61: =[1]Raw_Customer_Dim!$A$2 -> CUST1000 | G61: =_xlfn.XLOOKUP(E61,Store_Dim!A:A,Store_Dim!B:B,"Not Found") -> Aguirre-Keller | H61: =_xlfn.XLOOKUP(D61,Product_Dim!A:A,Product_Dim!C:C,"Not Found") -> Beauty | I61: =_xlfn.XLOOKUP(E61,Store_Dim!A:A,Store_Dim!C:C,"Not Found") -> South | J61: =_xlfn.XLOOKUP(C61,Customer_Dim!A:A,Customer_Dim!B:B,"Not Found") -> Melinda Johnson | K61: =Table511[[#This Row],[Total_Amount]]/(L61*(1-Table511[[#This Row],[Discount]])) -> 1 | L61: 996.33 | M61: 0.23 | N61: PayPal | O61: 767.1741
A62: SALE60 | B62: 45854 | C62: CUST1408 | D62: PROD31 | E62: STORE10 | F62: =[1]Raw_Customer_Dim!$A$2 -> CUST1000 | G62: =_xlfn.XLOOKUP(E62,Store_Dim!A:A,Store_Dim!B:B,"Not Found") -> Hill, Wagner and Ballard | H62: =_xlfn.XLOOKUP(D62,Product_Dim!A:A,Product_Dim!C:C,"Not Found") -> Sports | I62: =_xlfn.XLOOKUP(E62,Store_Dim!A:A,Store_Dim!C:C,"Not Found") -> East | J62: =_xlfn.XLOOKUP(C62,Customer_Dim!A:A,Customer_Dim!B:B,"Not Found") -> Isabel Foster | K62: =Table511[[#This Row],[Total_Amount]]/(L62*(1-Table511[[#This Row],[Discount]])) -> 1 | L62: 198.83 | M62: 0.09 | N62: COD | O62: 180.9353
A63: SALE61 | B63: 45716 | C63: CUST1239 | D63: PROD19 | E63: STORE7 | F63: =[1]Raw_Customer_Dim!$A$2 -> CUST1000 | G63: =_xlfn.XLOOKUP(E63,Store_Dim!A:A,Store_Dim!B:B,"Not Found") -> Martinez-Mullins | H63: =_xlfn.XLOOKUP(D63,Product_Dim!A:A,Product_Dim!C:C,"Not Found") -> Sports | I63: =_xlfn.XLOOKUP(E63,Store_Dim!A:A,Store_Dim!C:C,"Not Found") -> South | J63: =_xlfn.XLOOKUP(C63,Customer_Dim!A:A,Customer_Dim!B:B,"Not Found") -> Maria Hill | K63: =Table511[[#This Row],[Total_Amount]]/(L63*(1-Table511[[#This Row],[Discount]])) -> 1 | L63: 374.92 | M63: 0.18 | N63: PayPal | O63: 307.4344
A64: SALE62 | B64: 45515 | C64: CUST1464 | D64: PROD93 | E64: STORE16 | F64: =[1]Raw_Customer_Dim!$A$2 -> CUST1000 | G64: =_xlfn.XLOOKUP(E64,Store_Dim!A:A,Store_Dim!B:B,"Not Found") -> Frederick-Wright | H64: =_xlfn.XLOOKUP(D64,Product_Dim!A:A,Product_Dim!C:C,"Not Found") -> Electronics | I64: =_xlfn.XLOOKUP(E64,Store_Dim!A:A,Store_Dim!C:C,"Not Found") -> West | J64: =_xlfn.XLOOKUP(C64,Customer_Dim!A:A,Customer_Dim!B:B,"Not Found") -> Not Found | K64: =Table511[[#This Row],[Total_Amount]]/(L64*(1-Table511[[#This Row],[Discount]])) -> 1 | L64: 468.94 | M64: 0.12 | N64: Credit Card | O64: 412.6672
A65: SALE63 | B65: 45927 | C65: CUST1126 | D65: PROD89 | E65: STORE12 | F65: =[1]Raw_Customer_Dim!$A$2 -> CUST1000 | G65: =_xlfn.XLOOKUP(E65,Store_Dim!A:A,Store_Dim!B:B,"Not Found") -> Thomas, Bridges and Harris | H65: =_xlfn.XLOOKUP(D65,Product_Dim!A:A,Product_Dim!C:C,"Not Found") -> Beauty | I65: =_xlfn.XLOOKUP(E65,Store_Dim!A:A,Store_Dim!C:C,"Not Found") -> North | J65: =_xlfn.XLOOKUP(C65,Customer_Dim!A:A,Customer_Dim!B:B,"Not Found") -> James Wolfe | K65: =Table511[[#This Row],[Total_Amount]]/(L65*(1-Table511[[#This Row],[Discount]])) -> 2 | L65: 121.37 | M65: 0.05 | N65: Credit Card | O65: 230.603
A66: SALE64 | B66: 45914 | C66: CUST1255 | D66: PROD53 | E66: STORE10 | F66: =[1]Raw_Customer_Dim!$A$2 -> CUST1000 | G66: =_xlfn.XLOOKUP(E66,Store_Dim!A:A,Store_Dim!B:B,"Not Found") -> Hill, Wagner and Ballard | H66: =_xlfn.XLOOKUP(D66,Product_Dim!A:A,Product_Dim!C:C,"Not Found") -> Clothing | I66: =_xlfn.XLOOKUP(E66,Store_Dim!A:A,Store_Dim!C:C,"Not Found") -> East | J66: =_xlfn.XLOOKUP(C66,Customer_Dim!A:A,Customer_Dim!B:B,"Not Found") -> Damon Perez | K66: =Table511[[#This Row],[Total_Amount]]/(L66*(1-Table511[[#This Row],[Discount]])) -> 0 | L66: 480.06 | M66: 0.01 | N66: Credit Card
A67: SALE65 | B67: 45290 | C67: CUST1162 | D67: PROD99 | E67: STORE17 | F67: =[1]Raw_Customer_Dim!$A$2 -> CUST1000 | G67: =_xlfn.XLOOKUP(E67,Store_Dim!A:A,Store_Dim!B:B,"Not Found") -> Holloway Ltd | H67: =_xlfn.XLOOKUP(D67,Product_Dim!A:A,Product_Dim!C:C,"Not Found") -> Home | I67: =_xlfn.XLOOKUP(E67,Store_Dim!A:A,Store_Dim!C:C,"Not Found") -> North | J67: =_xlfn.XLOOKUP(C67,Customer_Dim!A:A,Customer_Dim!B:B,"Not Found") -> Mariah Brown | K67: =Table511[[#This Row],[Total_Amount]]/(L67*(1-Table511[[#This Row],[Discount]])) -> 2 | L67: 856.57 | M67: 0.24 | N67: Credit Card | O67: 1301.9864
A68: SALE66 | B68: 45213 | C68: CUST1269 | D68: PROD77 | E68: STORE2 | F68: =[1]Raw_Customer_Dim!$A$2 -> CUST1000 | G68: =_xlfn.XLOOKUP(E68,Store_Dim!A:A,Store_Dim!B:B,"Not Found") -> Black-Horn | H68: =_xlfn.XLOOKUP(D68,Product_Dim!A:A,Product_Dim!C:C,"Not Found") -> Electronics | I68: =_xlfn.XLOOKUP(E68,Store_Dim!A:A,Store_Dim!C:C,"Not Found") -> South | J68: =_xlfn.XLOOKUP(C68,Customer_Dim!A:A,Customer_Dim!B:B,"Not Found") -> Tyrone Olson | K68: =Table511[[#This Row],[Total_Amount]]/(L68*(1-Table511[[#This Row],[Discount]])) -> 4 | L68: 814.25 | M68: 0.18 | N68: Credit Card | O68: 2670.74
A69: SALE67 | B69: 45255 | C69: CUST1483 | D69: PROD12 | E69: STORE2 | F69: =[1]Raw_Customer_Dim!$A$2 -> CUST1000 | G69: =_xlfn.XLOOKUP(E69,Store_Dim!A:A,Store_Dim!B:B,"Not Found") -> Black-Horn | H69: =_xlfn.XLOOKUP(D69,Product_Dim!A:A,Product_Dim!C:C,"Not Found") -> Beauty | I69: =_xlfn.XLOOKUP(E69,Store_Dim!A:A,Store_Dim!C:C,"Not Found") -> South | J69: =_xlfn.XLOOKUP(C69,Customer_Dim!A:A,Customer_Dim!B:B,"Not Found") -> Sarah Smith | K69: =Table511[[#This Row],[Total_Amount]]/(L69*(1-Table511[[#This Row],[Discount]])) -> 1 | L69: 989.17 | M69: 0.2 | N69: PayPal | O69: 791.336
A70: SALE68 | B70: 45270 | C70: CUST1372 | D70: PROD72 | E70: STORE10 | F70: =[1]Raw_Customer_Dim!$A$2 -> CUST1000 | G70: =_xlfn.XLOOKUP(E70,Store_Dim!A:A,Store_Dim!B:B,"Not Found") -> Hill, Wagner and Ballard | H70: =_xlfn.XLOOKUP(D70,Product_Dim!A:A,Product_Dim!C:C,"Not Found") -> Sports | I70: =_xlfn.XLOOKUP(E70,Store_Dim!A:A,Store_Dim!C:C,"Not Found") -> East | J70: =_xlfn.XLOOKUP(C70,Customer_Dim!A:A,Customer_Dim!B:B,"Not Found") -> Jacqueline Anthony | K70: =Table511[[#This Row],[Total_Amount]]/(L70*(1-Table511[[#This Row],[Discount]])) -> 4 | L70: 62.48 | M70: 0.18 | N70: Credit Card | O70: 204.9344
A71: SALE69 | B71: 45897 | C71: CUST1423 | D71: PROD13 | E71: STORE16 | F71: =[1]Raw_Customer_Dim!$A$2 -> CUST1000 | G71: =_xlfn.XLOOKUP(E71,Store_Dim!A:A,Store_Dim!B:B,"Not Found") -> Frederick-Wright | H71: =_xlfn.XLOOKUP(D71,Product_Dim!A:A,Product_Dim!C:C,"Not Found") -> Electronics | I71: =_xlfn.XLOOKUP(E71,Store_Dim!A:A,Store_Dim!C:C,"Not Found") -> West | J71: =_xlfn.XLOOKUP(C71,Customer_Dim!A:A,Customer_Dim!B:B,"Not Found") -> Rebecca Baker | K71: =Table511[[#This Row],[Total_Amount]]/(L71*(1-Table511[[#This Row],[Discount]])) -> 4 | L71: 561.24 | M71: 0.24 | N71: Credit Card | O71: 1706.1696
A72: SALE70 | B72: 45849 | C72: CUST1058 | D72: PROD60 | E72: STORE5 | F72: =[1]Raw_Customer_Dim!$A$2 -> CUST1000 | G72: =_xlfn.XLOOKUP(E72,Store_Dim!A:A,Store_Dim!B:B,"Not Found") -> Gray Ltd | H72: =_xlfn.XLOOKUP(D72,Product_Dim!A:A,Product_Dim!C:C,"Not Found") -> Beauty | I72: =_xlfn.XLOOKUP(E72,Store_Dim!A:A,Store_Dim!C:C,"Not Found") -> North | J72: =_xlfn.XLOOKUP(C72,Customer_Dim!A:A,Customer_Dim!B:B,"Not Found") -> Cheryl Copeland | K72: =Table511[[#This Row],[Total_Amount]]/(L72*(1-Table511[[#This Row],[Discount]])) -> 0 | L72: 92.24 | M72: 0.28 | N72: COD
A73: SALE71 | B73: 45889 | C73: CUST1168 | D73: PROD72 | E73: STORE1 | F73: =[1]Raw_Customer_Dim!$A$2 -> CUST1000 | G73: =_xlfn.XLOOKUP(E73,Store_Dim!A:A,Store_Dim!B:B,"Not Found") -> Martinez, Adkins and Johnson | H73: =_xlfn.XLOOKUP(D73,Product_Dim!A:A,Product_Dim!C:C,"Not Found") -> Sports | I73: =_xlfn.XLOOKUP(E73,Store_Dim!A:A,Store_Dim!C:C,"Not Found") -> North | J73: =_xlfn.XLOOKUP(C73,Customer_Dim!A:A,Customer_Dim!B:B,"Not Found") -> Daniel Contreras | K73: =Table511[[#This Row],[Total_Amount]]/(L73*(1-Table511[[#This Row],[Discount]])) -> 2 | L73: 668.3 | M73: 0.07 | N73: Credit Card | O73: 1243.038
A74: SALE72 | B74: 45533 | C74: CUST1409 | D74: PROD38 | E74: STORE5 | F74: =[1]Raw_Customer_Dim!$A$2 -> CUST1000 | G74: =_xlfn.XLOOKUP(E74,Store_Dim!A:A,Store_Dim!B:B,"Not Found") -> Gray Ltd | H74: =_xlfn.XLOOKUP(D74,Product_Dim!A:A,Product_Dim!C:C,"Not Found") -> Sports | I74: =_xlfn.XLOOKUP(E74,Store_Dim!A:A,Store_Dim!C:C,"Not Found") -> North | J74: =_xlfn.XLOOKUP(C74,Customer_Dim!A:A,Customer_Dim!B:B,"Not Found") -> Sarah Smith | K74: =Table511[[#This Row],[Total_Amount]]/(L74*(1-Table511[[#This Row],[Discount]])) -> 1 | L74: 553.82 | M74: 0.09 | N74: Credit Card | O74: 503.9762
A75: SALE73 | B75: 45626 | C75: CUST1037 | D75: PROD45 | E75: STORE11 | F75: =[1]Raw_Customer_Dim!$A$2 -> CUST1000 | G75: =_xlfn.XLOOKUP(E75,Store_Dim!A:A,Store_Dim!B:B,"Not Found") -> Aguirre-Keller | H75: =_xlfn.XLOOKUP(D75,Product_Dim!A:A,Product_Dim!C:C,"Not Found") -> Sports | I75: =_xlfn.XLOOKUP(E75,Store_Dim!A:A,Store_Dim!C:C,"Not Found") -> South | J75: =_xlfn.XLOOKUP(C75,Customer_Dim!A:A,Customer_Dim!B:B,"Not Found") -> Christopher Carter | K75: =Table511[[#This Row],[Total_Amount]]/(L75*(1-Table511[[#This Row],[Discount]])) -> 2 | L75: 556.43 | M75: 0.13 | N75: Credit Card | O75: 968.1882
A76: SALE74 | B76: 45942 | C76: CUST1273 | D76: PROD20 | E76: STORE8 | F76: =[1]Raw_Customer_Dim!$A$2 -> CUST1000 | G76: =_xlfn.XLOOKUP(E76,Store_Dim!A:A,Store_Dim!B:B,"Not Found") -> Bean, Jones and Park | H76: =_xlfn.XLOOKUP(D76,Product_Dim!A:A,Product_Dim!C:C,"Not Found") -> Sports | I76: =_xlfn.XLOOKUP(E76,Store_Dim!A:A,Store_Dim!C:C,"Not Found") -> West | J76: =_xlfn.XLOOKUP(C76,Customer_Dim!A:A,Customer_Dim!B:B,"Not Found") -> Samantha Robinson | K76: =Table511[[#This Row],[Total_Amount]]/(L76*(1-Table511[[#This Row],[Discount]])) -> 1 | L76: 184.98 | M76: 0.1 | N76: COD | O76: 166.482
A77: SALE75 | B77: 45500 | C77: CUST1035 | D77: PROD97 | E77: STORE12 | F77: =[1]Raw_Customer_Dim!$A$2 -> CUST1000 | G77: =_xlfn.XLOOKUP(E77,Store_Dim!A:A,Store_Dim!B:B,"Not Found") -> Thomas, Bridges and Harris | H77: =_xlfn.XLOOKUP(D77,Product_Dim!A:A,Product_Dim!C:C,"Not Found") -> Sports | I77: =_xlfn.XLOOKUP(E77,Store_Dim!A:A,Store_Dim!C:C,"Not Found") -> North | J77: =_xlfn.XLOOKUP(C77,Customer_Dim!A:A,Customer_Dim!B:B,"Not Found") -> Rachel Myers | K77: =Table511[[#This Row],[Total_Amount]]/(L77*(1-Table511[[#This Row],[Discount]])) -> 4 | L77: 700.18 | M77: 0.23 | N77: Credit Card | O77: 2156.5544
A78: SALE76 | B78: 45285 | C78: CUST1019 | D78: PROD76 | E78: STORE10 | F78: =[1]Raw_Customer_Dim!$A$2 -> CUST1000 | G78: =_xlfn.XLOOKUP(E78,Store_Dim!A:A,Store_Dim!B:B,"Not Found") -> Hill, Wagner and Ballard | H78: =_xlfn.XLOOKUP(D78,Product_Dim!A:A,Product_Dim!C:C,"Not Found") -> Electronics | I78: =_xlfn.XLOOKUP(E78,Store_Dim!A:A,Store_Dim!C:C,"Not Found") -> East | J78: =_xlfn.XLOOKUP(C78,Customer_Dim!A:A,Customer_Dim!B:B,"Not Found") -> Michael Torres | K78: =Table511[[#This Row],[Total_Amount]]/(L78*(1-Table511[[#This Row],[Discount]])) -> 2 | L78: 686.31 | M78: 0.25 | N78: Credit Card | O78: 1029.465
A79: SALE77 | B79: 45800 | C79: CUST1007 | D79: PROD67 | E79: STORE15 | F79: =[1]Raw_Customer_Dim!$A$2 -> CUST1000 | G79: =_xlfn.XLOOKUP(E79,Store_Dim!A:A,Store_Dim!B:B,"Not Found") -> Shelton PLC | H79: =_xlfn.XLOOKUP(D79,Product_Dim!A:A,Product_Dim!C:C,"Not Found") -> Electronics | I79: =_xlfn.XLOOKUP(E79,Store_Dim!A:A,Store_Dim!C:C,"Not Found") -> North | J79: =_xlfn.XLOOKUP(C79,Customer_Dim!A:A,Customer_Dim!B:B,"Not Found") -> Daniel Boyd | K79: =Table511[[#This Row],[Total_Amount]]/(L79*(1-Table511[[#This Row],[Discount]])) -> 1 | L79: 687.82 | M79: 0.27 | N79: COD | O79: 502.1086
A80: SALE78 | B80: 45609 | C80: CUST1221 | D80: PROD83 | E80: STORE8 | F80: =[1]Raw_Customer_Dim!$A$2 -> CUST1000 | G80: =_xlfn.XLOOKUP(E80,Store_Dim!A:A,Store_Dim!B:B,"Not Found") -> Bean, Jones and Park | H80: =_xlfn.XLOOKUP(D80,Product_Dim!A:A,Product_Dim!C:C,"Not Found") -> Beauty | I80: =_xlfn.XLOOKUP(E80,Store_Dim!A:A,Store_Dim!C:C,"Not Found") -> West | J80: =_xlfn.XLOOKUP(C80,Customer_Dim!A:A,Customer_Dim!B:B,"Not Found") -> Lisa Young | K80: =Table511[[#This Row],[Total_Amount]]/(L80*(1-Table511[[#This Row],[Discount]])) -> 2 | L80: 900.55 | M80: 0.16 | N80: Credit Card | O80: 1512.924
A81: SALE79 | B81: 45268 | C81: CUST1115 | D81: PROD21 | E81: STORE2 | F81: =[1]Raw_Customer_Dim!$A$2 -> CUST1000 | G81: =_xlfn.XLOOKUP(E81,Store_Dim!A:A,Store_Dim!B:B,"Not Found") -> Black-Horn | H81: =_xlfn.XLOOKUP(D81,Product_Dim!A:A,Product_Dim!C:C,"Not Found") -> Home | I81: =_xlfn.XLOOKUP(E81,Store_Dim!A:A,Store_Dim!C:C,"Not Found") -> South | J81: =_xlfn.XLOOKUP(C81,Customer_Dim!A:A,Customer_Dim!B:B,"Not Found") -> Tyler Conrad | K81: =Table511[[#This Row],[Total_Amount]]/(L81*(1-Table511[[#This Row],[Discount]])) -> 1 | L81: 341.17 | M81: 0.15 | N81: Credit Card | O81: 289.9945
A82: SALE80 | B82: 45885 | C82: CUST1176 | D82: PROD52 | E82: STORE8 | F82: =[1]Raw_Customer_Dim!$A$2 -> CUST1000 | G82: =_xlfn.XLOOKUP(E82,Store_Dim!A:A,Store_Dim!B:B,"Not Found") -> Bean, Jones and Park | H82: =_xlfn.XLOOKUP(D82,Product_Dim!A:A,Product_Dim!C:C,"Not Found") -> Sports | I82: =_xlfn.XLOOKUP(E82,Store_Dim!A:A,Store_Dim!C:C,"Not Found") -> West | J82: =_xlfn.XLOOKUP(C82,Customer_Dim!A:A,Customer_Dim!B:B,"Not Found") -> John Bradford | K82: =Table511[[#This Row],[Total_Amount]]/(L82*(1-Table511[[#This Row],[Discount]])) -> 1 | L82: 442.27 | M82: 0.06 | N82: COD | O82: 415.7338
A83: SALE81 | B83: 45616 | C83: CUST1253 | D83: PROD71 | E83: STORE9 | F83: =[1]Raw_Customer_Dim!$A$2 -> CUST1000 | G83: =_xlfn.XLOOKUP(E83,Store_Dim!A:A,Store_Dim!B:B,"Not Found") -> Moore, Padilla and Butler | H83: =_xlfn.XLOOKUP(D83,Product_Dim!A:A,Product_Dim!C:C,"Not Found") -> Beauty | I83: =_xlfn.XLOOKUP(E83,Store_Dim!A:A,Store_Dim!C:C,"Not Found") -> South | J83: =_xlfn.XLOOKUP(C83,Customer_Dim!A:A,Customer_Dim!B:B,"Not Found") -> Dr. Ashley Yates MD | K83: =Table511[[#This Row],[Total_Amount]]/(L83*(1-Table511[[#This Row],[Discount]])) -> 1 | L83: 363.73 | M83: 0.25 | N83: PayPal | O83: 272.7975
A84: SALE82 | B84: 45518 | C84: CUST1378 | D84: PROD91 | E84: STORE17 | F84: =[1]Raw_Customer_Dim!$A$2 -> CUST1000 | G84: =_xlfn.XLOOKUP(E84,Store_Dim!A:A,Store_Dim!B:B,"Not Found") -> Holloway Ltd | H84: =_xlfn.XLOOKUP(D84,Product_Dim!A:A,Product_Dim!C:C,"Not Found") -> Clothing | I84: =_xlfn.XLOOKUP(E84,Store_Dim!A:A,Store_Dim!C:C,"Not Found") -> North | J84: =_xlfn.XLOOKUP(C84,Customer_Dim!A:A,Customer_Dim!B:B,"Not Found") -> Frank Stewart | K84: =Table511[[#This Row],[Total_Amount]]/(L84*(1-Table511[[#This Row],[Discount]])) -> 2 | L84: 601.33 | M84: 0.16 | N84: PayPal | O84: 1010.2344
A85: SALE83 | B85: 45427 | C85: CUST1403 | D85: PROD17 | E85: STORE18 | F85: =[1]Raw_Customer_Dim!$A$2 -> CUST1000 | G85: =_xlfn.XLOOKUP(E85,Store_Dim!A:A,Store_Dim!B:B,"Not Found") -> Guerrero-Schmitt | H85: =_xlfn.XLOOKUP(D85,Product_Dim!A:A,Product_Dim!C:C,"Not Found") -> Sports | I85: =_xlfn.XLOOKUP(E85,Store_Dim!A:A,Store_Dim!C:C,"Not Found") -> East | J85: =_xlfn.XLOOKUP(C85,Customer_Dim!A:A,Customer_Dim!B:B,"Not Found") -> Justin Ingram | K85: =Table511[[#This Row],[Total_Amount]]/(L85*(1-Table511[[#This Row],[Discount]])) -> 4 | L85: 34.39 | M85: 0.03 | N85: PayPal | O85: 133.4332
A86: SALE84 | B86: 45268 | C86: CUST1423 | D86: PROD46 | E86: STORE17 | F86: =[1]Raw_Customer_Dim!$A$2 -> CUST1000 | G86: =_xlfn.XLOOKUP(E86,Store_Dim!A:A,Store_Dim!B:B,"Not Found") -> Holloway Ltd | H86: =_xlfn.XLOOKUP(D86,Product_Dim!A:A,Product_Dim!C:C,"Not Found") -> Clothing | I86: =_xlfn.XLOOKUP(E86,Store_Dim!A:A,Store_Dim!C:C,"Not Found") -> North | J86: =_xlfn.XLOOKUP(C86,Customer_Dim!A:A,Customer_Dim!B:B,"Not Found") -> Rebecca Baker | K86: =Table511[[#This Row],[Total_Amount]]/(L86*(1-Table511[[#This Row],[Discount]])) -> 0 | L86: 773.57 | M86: 0.05 | N86: COD
A87: SALE85 | B87: 45282 | C87: CUST1054 | D87: PROD88 | E87: STORE7 | F87: =[1]Raw_Customer_Dim!$A$2 -> CUST1000 | G87: =_xlfn.XLOOKUP(E87,Store_Dim!A:A,Store_Dim!B:B,"Not Found") -> Martinez-Mullins | H87: =_xlfn.XLOOKUP(D87,Product_Dim!A:A,Product_Dim!C:C,"Not Found") -> Sports | I87: =_xlfn.XLOOKUP(E87,Store_Dim!A:A,Store_Dim!C:C,"Not Found") -> South | J87: =_xlfn.XLOOKUP(C87,Customer_Dim!A:A,Customer_Dim!B:B,"Not Found") -> Katherine Dorsey | K87: =Table511[[#This Row],[Total_Amount]]/(L87*(1-Table511[[#This Row],[Discount]])) -> 4 | L87: 127.1 | M87: 0.24 | N87: COD | O87: 386.384
A88: SALE86 | B88: 45545 | C88: CUST1303 | D88: PROD20 | E88: STORE3 | F88: =[1]Raw_Customer_Dim!$A$2 -> CUST1000 | G88: =_xlfn.XLOOKUP(E88,Store_Dim!A:A,Store_Dim!B:B,"Not Found") -> Johnson-Wright | H88: =_xlfn.XLOOKUP(D88,Product_Dim!A:A,Product_Dim!C:C,"Not Found") -> Sports | I88: =_xlfn.XLOOKUP(E88,Store_Dim!A:A,Store_Dim!C:C,"Not Found") -> North | J88: =_xlfn.XLOOKUP(C88,Customer_Dim!A:A,Customer_Dim!B:B,"Not Found") -> John Sloan | K88: =Table511[[#This Row],[Total_Amount]]/(L88*(1-Table511[[#This Row],[Discount]])) -> 3 | L88: 899.58 | M88: 0.28 | N88: PayPal | O88: 1943.0928
A89: SALE87 | B89: 45755 | C89: CUST1327 | D89: PROD1 | E89: STORE10 | F89: =[1]Raw_Customer_Dim!$A$2 -> CUST1000 | G89: =_xlfn.XLOOKUP(E89,Store_Dim!A:A,Store_Dim!B:B,"Not Found") -> Hill, Wagner and Ballard | H89: =_xlfn.XLOOKUP(D89,Product_Dim!A:A,Product_Dim!C:C,"Not Found") -> Clothing | I89: =_xlfn.XLOOKUP(E89,Store_Dim!A:A,Store_Dim!C:C,"Not Found") -> East | J89: =_xlfn.XLOOKUP(C89,Customer_Dim!A:A,Customer_Dim!B:B,"Not Found") -> Reginald Willis | K89: =Table511[[#This Row],[Total_Amount]]/(L89*(1-Table511[[#This Row],[Discount]])) -> 3 | L89: 964.39 | M89: 0.04 | N89: Credit Card | O89: 2777.4432
A90: SALE88 | B90: 45588 | C90: CUST1183 | D90: PROD38 | E90: STORE0 | F90: =[1]Raw_Customer_Dim!$A$2 -> CUST1000 | G90: =_xlfn.XLOOKUP(E90,Store_Dim!A:A,Store_Dim!B:B,"Not Found") -> Rivera-Warner | H90: =_xlfn.XLOOKUP(D90,Product_Dim!A:A,Product_Dim!C:C,"Not Found") -> Sports | I90: =_xlfn.XLOOKUP(E90,Store_Dim!A:A,Store_Dim!C:C,"Not Found") -> East | J90: =_xlfn.XLOOKUP(C90,Customer_Dim!A:A,Customer_Dim!B:B,"Not Found") -> Mario Jacobs | K90: =Table511[[#This Row],[Total_Amount]]/(L90*(1-Table511[[#This Row],[Discount]])) -> 2 | L90: 217.83 | M90: 0.14 | N90: PayPal | O90: 374.6676
A91: SALE89 | B91: 45848 | C91: CUST1143 | D91: PROD17 | E91: STORE1 | F91: =[1]Raw_Customer_Dim!$A$2 -> CUST1000 | G91: =_xlfn.XLOOKUP(E91,Store_Dim!A:A,Store_Dim!B:B,"Not Found") -> Martinez, Adkins and Johnson | H91: =_xlfn.XLOOKUP(D91,Product_Dim!A:A,Product_Dim!C:C,"Not Found") -> Sports | I91: =_xlfn.XLOOKUP(E91,Store_Dim!A:A,Store_Dim!C:C,"Not Found") -> North | J91: =_xlfn.XLOOKUP(C91,Customer_Dim!A:A,Customer_Dim!B:B,"Not Found") -> Carlos Skinner | K91: =Table511[[#This Row],[Total_Amount]]/(L91*(1-Table511[[#This Row],[Discount]])) -> 4 | L91: 187.71 | M91: 0.06 | N91: COD | O91: 705.7896
A92: SALE90 | B92: 45577 | C92: CUST1010 | D92: PROD33 | E92: STORE18 | F92: =[1]Raw_Customer_Dim!$A$2 -> CUST1000 | G92: =_xlfn.XLOOKUP(E92,Store_Dim!A:A,Store_Dim!B:B,"Not Found") -> Guerrero-Schmitt | H92: =_xlfn.XLOOKUP(D92,Product_Dim!A:A,Product_Dim!C:C,"Not Found") -> Home | I92: =_xlfn.XLOOKUP(E92,Store_Dim!A:A,Store_Dim!C:C,"Not Found") -> East | J92: =_xlfn.XLOOKUP(C92,Customer_Dim!A:A,Customer_Dim!B:B,"Not Found") -> Dominic Page | K92: =Table511[[#This Row],[Total_Amount]]/(L92*(1-Table511[[#This Row],[Discount]])) -> 2 | L92: 350.12 | M92: 0.12 | N92: COD | O92: 616.2112
A93: SALE91 | B93: 45312 | C93: CUST1406 | D93: PROD16 | E93: STORE1 | F93: =[1]Raw_Customer_Dim!$A$2 -> CUST1000 | G93: =_xlfn.XLOOKUP(E93,Store_Dim!A:A,Store_Dim!B:B,"Not Found") -> Martinez, Adkins and Johnson | H93: =_xlfn.XLOOKUP(D93,Product_Dim!A:A,Product_Dim!C:C,"Not Found") -> Not Found | I93: =_xlfn.XLOOKUP(E93,Store_Dim!A:A,Store_Dim!C:C,"Not Found") -> North | J93: =_xlfn.XLOOKUP(C93,Customer_Dim!A:A,Customer_Dim!B:B,"Not Found") -> David Lozano | K93: =Table511[[#This Row],[Total_Amount]]/(L93*(1-Table511[[#This Row],[Discount]])) -> 4 | L93: 102.19 | M93: 0.17 | N93: PayPal | O93: 339.2708
A94: SALE92 | B94: 45350 | C94: CUST1007 | D94: PROD86 | E94: STORE4 | F94: =[1]Raw_Customer_Dim!$A$2 -> CUST1000 | G94: =_xlfn.XLOOKUP(E94,Store_Dim!A:A,Store_Dim!B:B,"Not Found") -> Alexander Group | H94: =_xlfn.XLOOKUP(D94,Product_Dim!A:A,Product_Dim!C:C,"Not Found") -> Home | I94: =_xlfn.XLOOKUP(E94,Store_Dim!A:A,Store_Dim!C:C,"Not Found") -> South | J94: =_xlfn.XLOOKUP(C94,Customer_Dim!A:A,Customer_Dim!B:B,"Not Found") -> Daniel Boyd | K94: =Table511[[#This Row],[Total_Amount]]/(L94*(1-Table511[[#This Row],[Discount]])) -> 1 | L94: 696.53 | M94: 0.17 | N94: Credit Card | O94: 578.1199
A95: SALE93 | B95: 45657 | C95: CUST1065 | D95: PROD19 | E95: STORE4 | F95: =[1]Raw_Customer_Dim!$A$2 -> CUST1000 | G95: =_xlfn.XLOOKUP(E95,Store_Dim!A:A,Store_Dim!B:B,"Not Found") -> Alexander Group | H95: =_xlfn.XLOOKUP(D95,Product_Dim!A:A,Product_Dim!C:C,"Not Found") -> Sports | I95: =_xlfn.XLOOKUP(E95,Store_Dim!A:A,Store_Dim!C:C,"Not Found") -> South | J95: =_xlfn.XLOOKUP(C95,Customer_Dim!A:A,Customer_Dim!B:B,"Not Found") -> Michael Thomas | K95: =Table511[[#This Row],[Total_Amount]]/(L95*(1-Table511[[#This Row],[Discount]])) -> 2 | L95: 327.52 | M95: 0.15 | N95: PayPal | O95: 556.784
A96: SALE94 | B96: 45530 | C96: CUST1298 | D96: PROD97 | E96: STORE19 | F96: =[1]Raw_Customer_Dim!$A$2 -> CUST1000 | G96: =_xlfn.XLOOKUP(E96,Store_Dim!A:A,Store_Dim!B:B,"Not Found") -> Mann-Austin | H96: =_xlfn.XLOOKUP(D96,Product_Dim!A:A,Product_Dim!C:C,"Not Found") -> Sports | I96: =_xlfn.XLOOKUP(E96,Store_Dim!A:A,Store_Dim!C:C,"Not Found") -> East | J96: =_xlfn.XLOOKUP(C96,Customer_Dim!A:A,Customer_Dim!B:B,"Not Found") -> Tracy Stephens | K96: =Table511[[#This Row],[Total_Amount]]/(L96*(1-Table511[[#This Row],[Discount]])) -> 0 | L96: 569.36 | M96: 0.01 | N96: PayPal
A97: SALE95 | B97: 45556 | C97: CUST1321 | D97: PROD99 | E97: STORE6 | F97: =[1]Raw_Customer_Dim!$A$2 -> CUST1000 | G97: =_xlfn.XLOOKUP(E97,Store_Dim!A:A,Store_Dim!B:B,"Not Found") -> Benson-Elliott | H97: =_xlfn.XLOOKUP(D97,Product_Dim!A:A,Product_Dim!C:C,"Not Found") -> Home | I97: =_xlfn.XLOOKUP(E97,Store_Dim!A:A,Store_Dim!C:C,"Not Found") -> East | J97: =_xlfn.XLOOKUP(C97,Customer_Dim!A:A,Customer_Dim!B:B,"Not Found") -> Darren Burton | K97: =Table511[[#This Row],[Total_Amount]]/(L97*(1-Table511[[#This Row],[Discount]])) -> 2 | L97: 68.29 | M97: 0.14 | N97: COD | O97: 117.4588
A98: SALE96 | B98: 45523 | C98: CUST1244 | D98: PROD50 | E98: STORE10 | F98: =[1]Raw_Customer_Dim!$A$2 -> CUST1000 | G98: =_xlfn.XLOOKUP(E98,Store_Dim!A:A,Store_Dim!B:B,"Not Found") -> Hill, Wagner and Ballard | H98: =_xlfn.XLOOKUP(D98,Product_Dim!A:A,Product_Dim!C:C,"Not Found") -> Sports | I98: =_xlfn.XLOOKUP(E98,Store_Dim!A:A,Store_Dim!C:C,"Not Found") -> East | J98: =_xlfn.XLOOKUP(C98,Customer_Dim!A:A,Customer_Dim!B:B,"Not Found") -> Nancy Page | K98: =Table511[[#This Row],[Total_Amount]]/(L98*(1-Table511[[#This Row],[Discount]])) -> 1 | L98: 842.9 | M98: 0.06 | N98: COD | O98: 792.326
A99: SALE97 | B99: 45587 | C99: CUST1287 | D99: PROD3 | E99: STORE3 | F99: =[1]Raw_Customer_Dim!$A$2 -> CUST1000 | G99: =_xlfn.XLOOKUP(E99,Store_Dim!A:A,Store_Dim!B:B,"Not Found") -> Johnson-Wright | H99: =_xlfn.XLOOKUP(D99,Product_Dim!A:A,Product_Dim!C:C,"Not Found") -> Not Found | I99: =_xlfn.XLOOKUP(E99,Store_Dim!A:A,Store_Dim!C:C,"Not Found") -> North | J99: =_xlfn.XLOOKUP(C99,Customer_Dim!A:A,Customer_Dim!B:B,"Not Found") -> Cynthia Roberts | K99: =Table511[[#This Row],[Total_Amount]]/(L99*(1-Table511[[#This Row],[Discount]])) -> 3 | L99: 751.94 | M99: 0.26 | N99: PayPal | O99: 1669.3068
A100: SALE98 | B100: 45580 | C100: CUST1131 | D100: PROD56 | E100: STORE7 | F100: =[1]Raw_Customer_Dim!$A$2 -> CUST1000 | G100: =_xlfn.XLOOKUP(E100,Store_Dim!A:A,Store_Dim!B:B,"Not Found") -> Martinez-Mullins | H100: =_xlfn.XLOOKUP(D100,Product_Dim!A:A,Product_Dim!C:C,"Not Found") -> Home | I100: =_xlfn.XLOOKUP(E100,Store_Dim!A:A,Store_Dim!C:C,"Not Found") -> South | J100: =_xlfn.XLOOKUP(C100,Customer_Dim!A:A,Customer_Dim!B:B,"Not Found") -> Joseph Richards | K100: =Table511[[#This Row],[Total_Amount]]/(L100*(1-Table511[[#This Row],[Discount]])) -> 4 | L100: 476.28 | M100: 0.17 | N100: Credit Card | O100: 1581.2496
A101: SALE99 | B101: 45479 | C101: CUST1325 | D101: PROD54 | E101: STORE3 | F101: =[1]Raw_Customer_Dim!$A$2 -> CUST1000 | G101: =_xlfn.XLOOKUP(E101,Store_Dim!A:A,Store_Dim!B:B,"Not Found") -> Johnson-Wright | H101: =_xlfn.XLOOKUP(D101,Product_Dim!A:A,Product_Dim!C:C,"Not Found") -> Sports | I101: =_xlfn.XLOOKUP(E101,Store_Dim!A:A,Store_Dim!C:C,"Not Found") -> North | J101: =_xlfn.XLOOKUP(C101,Customer_Dim!A:A,Customer_Dim!B:B,"Not Found") -> Andrew Smith | K101: =Table511[[#This Row],[Total_Amount]]/(L101*(1-Table511[[#This Row],[Discount]])) -> 3 | L101: 541.99 | M101: 0.24 | N101: COD | O101: 1235.7372
A102: SALE100 | B102: 45677 | C102: CUST1369 | D102: PROD33 | E102: STORE5 | F102: =[1]Raw_Customer_Dim!$A$2 -> CUST1000 | G102: =_xlfn.XLOOKUP(E102,Store_Dim!A:A,Store_Dim!B:B,"Not Found") -> Gray Ltd | H102: =_xlfn.XLOOKUP(D102,Product_Dim!A:A,Product_Dim!C:C,"Not Found") -> Home | I102: =_xlfn.XLOOKUP(E102,Store_Dim!A:A,Store_Dim!C:C,"Not Found") -> North | J102: =_xlfn.XLOOKUP(C102,Customer_Dim!A:A,Customer_Dim!B:B,"Not Found") -> Gregory Allen | K102: =Table511[[#This Row],[Total_Amount]]/(L102*(1-Table511[[#This Row],[Discount]])) -> 2 | L102: 401.5 | M102: 0.18 | N102: Credit Card | O102: 658.46
A103: SALE101 | B103: 45453 | C103: CUST1084 | D103: PROD25 | E103: STORE13 | F103: =[1]Raw_Customer_Dim!$A$2 -> CUST1000 | G103: =_xlfn.XLOOKUP(E103,Store_Dim!A:A,Store_Dim!B:B,"Not Found") -> Gardner, Humphrey and Contreras | H103: =_xlfn.XLOOKUP(D103,Product_Dim!A:A,Product_Dim!C:C,"Not Found") -> Clothing | I103: =_xlfn.XLOOKUP(E103,Store_Dim!A:A,Store_Dim!C:C,"Not Found") -> East | J103: =_xlfn.XLOOKUP(C103,Customer_Dim!A:A,Customer_Dim!B:B,"Not Found") -> Christy Hoffman | K103: =Table511[[#This Row],[Total_Amount]]/(L103*(1-Table511[[#This Row],[Discount]])) -> 3 | L103: 359.56 | M103: 0.17 | N103: PayPal | O103: 895.3044
A104: SALE102 | B104: 45552 | C104: CUST1097 | D104: PROD80 | E104: STORE12 | F104: =[1]Raw_Customer_Dim!$A$2 -> CUST1000 | G104: =_xlfn.XLOOKUP(E104,Store_Dim!A:A,Store_Dim!B:B,"Not Found") -> Thomas, Bridges and Harris | H104: =_xlfn.XLOOKUP(D104,Product_Dim!A:A,Product_Dim!C:C,"Not Found") -> Home | I104: =_xlfn.XLOOKUP(E104,Store_Dim!A:A,Store_Dim!C:C,"Not Found") -> North | J104: =_xlfn.XLOOKUP(C104,Customer_Dim!A:A,Customer_Dim!B:B,"Not Found") -> David Cobb | K104: =Table511[[#This Row],[Total_Amount]]/(L104*(1-Table511[[#This Row],[Discount]])) -> 2 | L104: 471.88 | M104: 0.24 | N104: PayPal | O104: 717.2576
A105: SALE103 | B105: 45907 | C105: CUST1182 | D105: PROD34 | E105: STORE4 | F105: =[1]Raw_Customer_Dim!$A$2 -> CUST1000 | G105: =_xlfn.XLOOKUP(E105,Store_Dim!A:A,Store_Dim!B:B,"Not Found") -> Alexander Group | H105: =_xlfn.XLOOKUP(D105,Product_Dim!A:A,Product_Dim!C:C,"Not Found") -> Electronics | I105: =_xlfn.XLOOKUP(E105,Store_Dim!A:A,Store_Dim!C:C,"Not Found") -> South | J105: =_xlfn.XLOOKUP(C105,Customer_Dim!A:A,Customer_Dim!B:B,"Not Found") -> Melissa Hamilton | K105: =Table511[[#This Row],[Total_Amount]]/(L105*(1-Table511[[#This Row],[Discount]])) -> 4 | L105: 925.19 | M105: 0.19 | N105: PayPal | O105: 2997.6156
A106: SALE104 | B106: 45330 | C106: CUST1029 | D106: PROD86 | E106: STORE11 | F106: =[1]Raw_Customer_Dim!$A$2 -> CUST1000 | G106: =_xlfn.XLOOKUP(E106,Store_Dim!A:A,Store_Dim!B:B,"Not Found") -> Aguirre-Keller | H106: =_xlfn.XLOOKUP(D106,Product_Dim!A:A,Product_Dim!C:C,"Not Found") -> Home | I106: =_xlfn.XLOOKUP(E106,Store_Dim!A:A,Store_Dim!C:C,"Not Found") -> South | J106: =_xlfn.XLOOKUP(C106,Customer_Dim!A:A,Customer_Dim!B:B,"Not Found") -> David Arnold | K106: =Table511[[#This Row],[Total_Amount]]/(L106*(1-Table511[[#This Row],[Discount]])) -> 2 | L106: 879.63 | M106: 0.07 | N106: COD | O106: 1636.1118
A107: SALE105 | B107: 45214 | C107: CUST1002 | D107: PROD79 | E107: STORE17 | F107: =[1]Raw_Customer_Dim!$A$2 -> CUST1000 | G107: =_xlfn.XLOOKUP(E107,Store_Dim!A:A,Store_Dim!B:B,"Not Found") -> Holloway Ltd | H107: =_xlfn.XLOOKUP(D107,Product_Dim!A:A,Product_Dim!C:C,"Not Found") -> Home | I107: =_xlfn.XLOOKUP(E107,Store_Dim!A:A,Store_Dim!C:C,"Not Found") -> North | J107: =_xlfn.XLOOKUP(C107,Customer_Dim!A:A,Customer_Dim!B:B,"Not Found") -> dr. Benjamin Price | K107: =Table511[[#This Row],[Total_Amount]]/(L107*(1-Table511[[#This Row],[Discount]])) -> 2 | L107: 418.23 | M107: 0.28 | N107: Credit Card | O107: 602.2512
A108: SALE106 | B108: 45891 | C108: CUST1269 | D108: PROD19 | E108: STORE18 | F108: =[1]Raw_Customer_Dim!$A$2 -> CUST1000 | G108: =_xlfn.XLOOKUP(E108,Store_Dim!A:A,Store_Dim!B:B,"Not Found") -> Guerrero-Schmitt | H108: =_xlfn.XLOOKUP(D108,Product_Dim!A:A,Product_Dim!C:C,"Not Found") -> Sports | I108: =_xlfn.XLOOKUP(E108,Store_Dim!A:A,Store_Dim!C:C,"Not Found") -> East | J108: =_xlfn.XLOOKUP(C108,Customer_Dim!A:A,Customer_Dim!B:B,"Not Found") -> Tyrone Olson | K108: =Table511[[#This Row],[Total_Amount]]/(L108*(1-Table511[[#This Row],[Discount]])) -> 3 | L108: 551.72 | M108: 0.03 | N108: COD | O108: 1605.5052
... A260: SALE258 | B260: 45300 | C260: CUST1136 | D260: PROD35 | E260: STORE17 | F260: =[1]Raw_Customer_Dim!$A$2 -> CUST1000 | G260: =_xlfn.XLOOKUP(E260,Store_Dim!A:A,Store_Dim!B:B,"Not Found") -> Holloway Ltd | H260: =_xlfn.XLOOKUP(D260,Product_Dim!A:A,Product_Dim!C:C,"Not Found") -> Home | I260: =_xlfn.XLOOKUP(E260,Store_Dim!A:A,Store_Dim!C:C,"Not Found") -> North | J260: =_xlfn.XLOOKUP(C260,Customer_Dim!A:A,Customer_Dim!B:B,"Not Found") -> Patrick Coleman | K260: =Table511[[#This Row],[Total_Amount]]/(L260*(1-Table511[[#This Row],[Discount]])) -> 1 | L260: 222.94 | M260: 0.19 | N260: Credit Card | O260: 180.5814
A261: SALE259 | B261: 45773 | C261: CUST1248 | D261: PROD35 | E261: STORE2 | F261: =[1]Raw_Customer_Dim!$A$2 -> CUST1000 | G261: =_xlfn.XLOOKUP(E261,Store_Dim!A:A,Store_Dim!B:B,"Not Found") -> Black-Horn | H261: =_xlfn.XLOOKUP(D261,Product_Dim!A:A,Product_Dim!C:C,"Not Found") -> Home | I261: =_xlfn.XLOOKUP(E261,Store_Dim!A:A,Store_Dim!C:C,"Not Found") -> South | J261: =_xlfn.XLOOKUP(C261,Customer_Dim!A:A,Customer_Dim!B:B,"Not Found") -> Nicholas Webb | K261: Uknown | L261: 355.3 | M261: Unknown | N261: PayPal | O261: 589.798
A262: SALE260 | B262: 45497 | C262: CUST1103 | D262: PROD89 | E262: STORE19 | F262: =[1]Raw_Customer_Dim!$A$2 -> CUST1000 | G262: =_xlfn.XLOOKUP(E262,Store_Dim!A:A,Store_Dim!B:B,"Not Found") -> Mann-Austin | H262: =_xlfn.XLOOKUP(D262,Product_Dim!A:A,Product_Dim!C:C,"Not Found") -> Beauty | I262: =_xlfn.XLOOKUP(E262,Store_Dim!A:A,Store_Dim!C:C,"Not Found") -> East | J262: =_xlfn.XLOOKUP(C262,Customer_Dim!A:A,Customer_Dim!B:B,"Not Found") -> Steven Stein | K262: =Table511[[#This Row],[Total_Amount]]/(L262*(1-Table511[[#This Row],[Discount]])) -> 4 | L262: 611.3 | M262: 0.11 | N262: PayPal | O262: 2176.228
A263: SALE261 | B263: 45742 | C263: CUST1333 | D263: PROD0 | E263: STORE8 | F263: =[1]Raw_Customer_Dim!$A$2 -> CUST1000 | G263: =_xlfn.XLOOKUP(E263,Store_Dim!A:A,Store_Dim!B:B,"Not Found") -> Bean, Jones and Park | H263: =_xlfn.XLOOKUP(D263,Product_Dim!A:A,Product_Dim!C:C,"Not Found") -> Electronics | I263: =_xlfn.XLOOKUP(E263,Store_Dim!A:A,Store_Dim!C:C,"Not Found") -> West | J263: =_xlfn.XLOOKUP(C263,Customer_Dim!A:A,Customer_Dim!B:B,"Not Found") -> Teresa Johnson | K263: =Table511[[#This Row],[Total_Amount]]/(L263*(1-Table511[[#This Row],[Discount]])) -> 4 | L263: 849.21 | M263: 0.07 | N263: Credit Card | O263: 3159.0612
...

Sheet Pivot summary
A1: Pivot-Style Summaries
A2: Sales by Category Category | D2: Sales by Store
A3: Row Labels | B3: Sum of Total_Amount | D3: Row Labels | E3: Sum of Total_Amount
A4: Beauty | B4: 299613.5 | D4: Aguirre-Keller | E4: 93048.141
A5: Clothing | B5: 352743.79 | D5: Alexander Group | E5: 118814.12
A6: Electronics | B6: 504311.35 | D6: Bean, Jones and Park | E6: 158971.46
A7: Home | B7: 427295.8 | D7: Benson-Elliott | E7: 114533.8
A8: Not Found | B8: 46060.17 | D8: Black-Horn | E8: 98960.808
A9: Sports | B9: 540882.84 | D9: Frederick-Wright | E9: 111704.94
A10: Grand Total | B10: 2170907.5 | D10: Gardner, Humphrey and Contreras | E10: 114401.47
D11: Gray Ltd | E11: 81144.35
A12: Sales by Payment Type | D12: Guerrero-Schmitt | E12: 104313.05
A13: Row Labels | B13: Sum of Total_Amount | D13: Hill, Wagner and Ballard | E13: 108365.94
A14: COD | B14: 701525.29 | D14: Holloway Ltd | E14: 121441.66
A15: Credit Card | B15: 713754.93 | D15: Johnson-Wright | E15: 125011.83
A16: PayPal | B16: 755627.24 | D16: Mann-Austin | E16: 93098.39
A17: Grand Total | B17: 2170907.5 | D17: Martinez, Adkins and Johnson | E17: 101060.61
D18: Martinez-Mullins | E18: 108039.35
A19: Sales by Region | D19: Mcdonald Inc | E19: 106248.28
A20: Row Labels | B20: Sum of Total_Amount | D20: Moore, Padilla and Butler | E20: 110102.4
A21: East | B21: 619851.21 | D21: Rivera-Warner | E21: 85138.555
A22: North | B22: 645166.75 | D22: Shelton PLC | E22: 99679.086
A23: South | B23: 635213.1 | D23: Thomas, Bridges and Harris | E23: 116829.22
A24: West | B24: 270676.41 | D24: Grand Total | E24: 2170907.5
A25: Grand Total | B25: 2170907.5

Sheet Dashboard
F1: Sales Dashboard
